Workbook

Sheet README
A1: Lepas South Africa — August 2026 Media Performance Workbook
A2: Read me first. Dummy / illustrative data built to the structure of live platform exports. Not actual Lepas results.
A4: 1. WHAT THIS IS
B5: Campaign: Lepas SA — August 2026, national.
B6: Objective: Test drive bookings. That is the single conversion in this workbook.
B7: Conversion point: https://www.lepas-sa.co.za/offers → test drive booking form.
B8: Models in market: AMUR (1.5 M/T), JAVAN (1.5T DCT), PANTERA (1.5T DCT), on 0% and 10% deposit offers.
B9: Channels: Meta (Facebook + Instagram), TikTok, X, Programmatic (DV360).
B10: Total budget: R400,000 excl. VAT, 1 – 31 August 2026.
B11: Currency: South African Rand (ZAR), excluding VAT.
B13: ALL DATA IN THIS WORKBOOK IS SYNTHETIC. It is modelled on realistic South African automotive benchmarks so that it behaves like real data — but no figure here came from a live Lepas account. Replace Raw_Data with a genuine platform export and every other tab recalculates against it.
A16: 2. HOW THIS WORKBOOK IS WIRED
B17: • Raw_Data is the single source of truth. 2,551 rows at Day x Channel x Campaign x Ad Set x Creative.
B18: • Every reporting tab is built on live SUMIFS formulas pointing at Raw_Data. Nothing is pasted or hardcoded.
B19: • Assumptions is the control panel. Change a blue cell — budget, vehicle price, close rate, CPL target — and the whole workbook re-forecasts.
B20: • QA_Checks proves the tabs reconcile. Open it after any edit; every row should read PASS.
B21: • Breakdown tabs (Placements, Demographics, Location, Devices_Apps, Landing_Pages) are separate aggregates, exactly as platform exports are — you cannot cross-tab age against creative in Meta or DV360 either. They tie to the same channel totals.
A24: 3. TAB GUIDE
B25: Tab | C25: What it answers | D25: Rows | E25: Built from
B26: README | C26: You are here — definitions, method and caveats. | D26: — | E26: —
B27: Summary | C27: Headline KPIs, then performance by channel, model, audience strategy and week. | D27: ~30 | E27: SUMIFS on Raw_Data
B28: Daily_Trend | C28: Day-by-day delivery, cumulative pacing against the R400k plan, and per-channel spend / bookings / CPL. | D28: 31 | E28: SUMIFS on Raw_Data
B29: Channel_Detail | C29: Each channel cut by week, by model and by audience strategy. | D29: 64 | E29: SUMIFS on Raw_Data
B30: Campaign_AdSet | C30: Campaign roll-up, then every ad set / line item. | D30: 12+31 | E30: SUMIFS on Raw_Data
B31: Creative_Performance | C31: Every asset, its flight window, funnel efficiency and video engagement. | D31: 54 | E31: SUMIFS on Raw_Data
B32: Placements | C32: Where impressions served, indexed against each channel's own average. | D32: 22 | E32: Platform placement export
B33: Demographics | C33: Age band x gender per campaign. | D33: 216 | E33: Platform demo export
B34: Location | C34: Province and metro / non-metro, indexed to dealer density. | D34: 72 | E34: Platform geo export
B35: Devices_Apps | C35: Device and OS split, plus the app / domain inventory with viewability, IVT and brand safety. | D35: 22+25 | E35: Platform + DV360 export
B36: Landing_Pages | C36: On-site behaviour per destination URL: sessions, bounce, form starts and completions. | D36: 12 | E36: Analytics export
... B39: QA_Checks | C39: Reconciliation between every tab and Raw_Data. | D39: 24 | E39: Cross-tab formulas
A42: 4. DATA DICTIONARY
B43: Metric | C43: Definition
B44: Spend (ZAR) | C44: Media cost, excluding VAT and agency fee.
B45: Impressions | C45: Times an ad was rendered. Not unique people.
B46: Reach (sum of daily) | C46: Unique people reached, de-duplicated WITHIN a day. Summing 31 days overstates true monthly unique reach — treat as a delivery indicator, not a reach figure.
B47: Avg Daily Frequency | C47: Impressions ÷ sum of daily reach. Average times a person saw an ad per day, not across the month.
B48: Clicks (All) | C48: Every click, including profile taps, expands and reactions.
B49: Link Clicks | C49: Clicks that requested the destination URL. The number that matters.
B50: CTR (Link) | C50: Link Clicks ÷ Impressions.
B51: CPC (Link) | C51: Spend ÷ Link Clicks.
B52: CPM | C52: Spend ÷ Impressions × 1,000. Cost to reach a thousand impressions.
B53: Landing Page Views | C53: Sessions where the page actually rendered. Always lower than link clicks — the gap is bounce-before-load, and it is a site speed problem, not a media one.
B54: LPV Rate | C54: Landing Page Views ÷ Link Clicks. Below ~75% points at page load time.
... B74: Brand Safety Score | C74: Inventory quality rating out of 100.
A77: 5. HOW THE DUMMY DATA WAS MODELLED
B78: • Spend was allocated bottom-up by ad set and creative weight, then normalised so each channel hits its budget to the cent.
B79: • The funnel is derived, not invented: spend → impressions (via CPM) → link clicks (via CTR) → landing page views (via LPV rate) → bookings (via CVR). Change any input and the chain holds.
B80: • Daily volume follows a Thursday-to-Sunday curve, because that is when South Africans book test drives. Women's Day (observed 10 August) is indexed up.
B81: • Creatives fatigue: CTR and CVR decay roughly 1.1% per day of a creative's flight, floored at 72%. The 13 August refresh wave resets it.
B82: • Retargeting audiences convert ~1.85x prospecting; lookalikes ~1.28x. Frequency climbs through the month.
B83: • Sub-1.0 daily conversions are rounded stochastically, not to the nearest integer — otherwise thin channels like Programmatic would floor to zero and understate by an order of magnitude.
B84: • Full benchmark ranges, calendar flags and rate assumptions are on the Assumptions tab.
A87: 6. READ THIS BEFORE YOU QUOTE ANY NUMBER
B88: • The data is synthetic. Useful for building reports, testing dashboards, training and presenting structure — not for stating Lepas performance.
B89: • Attribution is last-click in-platform. Every platform marks its own homework, so channel bookings summed across platforms will exceed what analytics reports.
B90: • View-through and assisted conversions overlap with last-click bookings. Never add all three together.
B91: • Reach does not sum across days, channels or breakdowns.
B92: • Est. Revenue Pipeline is a forecast built on assumed attendance and close rates. Replace those two cells with dealer network actuals before it goes anywhere near a finance conversation.
B95: Workbook generated 2026-09-10 | Reporting period 2026-08-01 to 2026-08-31 | 2,551 raw rows | 14 tabs
A97: 8. CREATIVE FATIGUE TAB
A98: Creative_Fatigue derives first/latest 3-day CTR, CPL decay, creative frequency, thumb-stop, hold rate, watch-depth proxy, engagement proxy, message territory and a CMO refresh decision from Raw_Data.
A100: 9. BUDGET FORECAST TAB
A101: Budget_Forecast derives planned daily spend, actual daily spend, spend variance, required run-rate, forecast bookings/CPL/qualified leads, reallocation recommendation and recommended next-month budget from Raw_Data and Assumptions budget controls.

Sheet Summary
A1: Lepas South Africa — August 2026 Media Performance
A2: Campaign objective: Test Drive Bookings | Conversion point: lepas-sa.co.za/offers | All figures in ZAR, excl. VAT | Every cell below is a live formula over Raw_Data.
A4: HEADLINE — MONTH TO DATE
B5: TOTAL MEDIA SPEND | E5: IMPRESSIONS | H5: LINK CLICKS | K5: TEST DRIVE BOOKINGS | N5: BLENDED CPL | Q5: QUALIFIED BOOKINGS | T5: COST / QUALIFIED | W5: EST. REVENUE PIPELINE
B6: =SUM(Raw_Data!$R$2:$R$2552) | E6: =SUM(Raw_Data!$S$2:$S$2552) | H6: =SUM(Raw_Data!$W$2:$W$2552) | K6: =SUM(Raw_Data!$AL$2:$AL$2552) | N6: =IFERROR(B6/K6,"") | Q6: =SUM(Raw_Data!$AO$2:$AO$2552) | T6: =IFERROR(B6/Q6,"") | W6: =SUM(Raw_Data!$AU$2:$AU$2552)
B8: =IF(N6<=Assumptions!$C$29,"ON TARGET — blended CPL of R"&TEXT(N6,"#,##0")&" is at or under the R"&TEXT(Assumptions!$C$29,"#,##0")&" KPI","OVER TARGET — blended CPL of R"&TEXT(N6,"#,##0")&" vs the R"&TEXT(Assumptions!$C$29,"#,##0")&" KPI")
B9: ="Return on media: every R1 of spend is modelled to return R"&TEXT(IFERROR(W6/B6,0),"#,##0.00")&" of vehicle revenue pipeline "&"("&TEXT(IFERROR(Q6*Assumptions!$C$26*Assumptions!$C$27,0),"#,##0")&" units at the assumed attendance and close rates)."
A11: PERFORMANCE BY CHANNEL
A12: Channel | B12: Spend (ZAR) | C12: Impressions | D12: Reach (sum of daily) | E12: Avg Daily Frequency | F12: Link Clicks | G12: CTR (Link) | H12: CPC (Link) | I12: CPM | J12: Landing Page Views | K12: LPV Rate | L12: Test Drive Bookings | M12: CVR (Booking / LPV) | N12: CPL (Cost / Booking) | O12: Qualified Leads | P12: Qualified Rate | Q12: Cost per Qualified Lead | R12: View-Through Conv. | S12: Assisted Conv. | T12: Total Attributed Conv. | U12: Est. Revenue Pipeline (ZAR) | V12: % of Spend | W12: % of Bookings
A13: Meta (FB/IG) | B13: =SUMIFS(Raw_Data!$R$2:$R$2552,Raw_Data!$D$2:$D$2552,$A13) | C13: =SUMIFS(Raw_Data!$S$2:$S$2552,Raw_Data!$D$2:$D$2552,$A13) | D13: =SUMIFS(Raw_Data!$T$2:$T$2552,Raw_Data!$D$2:$D$2552,$A13) | E13: =IFERROR(C13/D13,"") | F13: =SUMIFS(Raw_Data!$W$2:$W$2552,Raw_Data!$D$2:$D$2552,$A13) | G13: =IFERROR(F13/C13,"") | H13: =IFERROR(B13/F13,"") | I13: =IFERROR(B13/C13*1000,"") | J13: =SUMIFS(Raw_Data!$AA$2:$AA$2552,Raw_Data!$D$2:$D$2552,$A13) | K13: =IFERROR(J13/F13,"") | L13: =SUMIFS(Raw_Data!$AL$2:$AL$2552,Raw_Data!$D$2:$D$2552,$A13) | M13: =IFERROR(L13/J13,"") | N13: =IFERROR(B13/L13,"") | O13: =SUMIFS(Raw_Data!$AO$2:$AO$2552,Raw_Data!$D$2:$D$2552,$A13) | P13: =IFERROR(O13/L13,"") | Q13: =IFERROR(B13/O13,"") | R13: =SUMIFS(Raw_Data!$AR$2:$AR$2552,Raw_Data!$D$2:$D$2552,$A13) | S13: =SUMIFS(Raw_Data!$AS$2:$AS$2552,Raw_Data!$D$2:$D$2552,$A13) | T13: =L13+R13 | U13: =SUMIFS(Raw_Data!$AU$2:$AU$2552,Raw_Data!$D$2:$D$2552,$A13) | V13: =IFERROR(B13/$B$17,"") | W13: =IFERROR(L13/$L$17,"")
A14: TikTok | B14: =SUMIFS(Raw_Data!$R$2:$R$2552,Raw_Data!$D$2:$D$2552,$A14) | C14: =SUMIFS(Raw_Data!$S$2:$S$2552,Raw_Data!$D$2:$D$2552,$A14) | D14: =SUMIFS(Raw_Data!$T$2:$T$2552,Raw_Data!$D$2:$D$2552,$A14) | E14: =IFERROR(C14/D14,"") | F14: =SUMIFS(Raw_Data!$W$2:$W$2552,Raw_Data!$D$2:$D$2552,$A14) | G14: =IFERROR(F14/C14,"") | H14: =IFERROR(B14/F14,"") | I14: =IFERROR(B14/C14*1000,"") | J14: =SUMIFS(Raw_Data!$AA$2:$AA$2552,Raw_Data!$D$2:$D$2552,$A14) | K14: =IFERROR(J14/F14,"") | L14: =SUMIFS(Raw_Data!$AL$2:$AL$2552,Raw_Data!$D$2:$D$2552,$A14) | M14: =IFERROR(L14/J14,"") | N14: =IFERROR(B14/L14,"") | O14: =SUMIFS(Raw_Data!$AO$2:$AO$2552,Raw_Data!$D$2:$D$2552,$A14) | P14: =IFERROR(O14/L14,"") | Q14: =IFERROR(B14/O14,"") | R14: =SUMIFS(Raw_Data!$AR$2:$AR$2552,Raw_Data!$D$2:$D$2552,$A14) | S14: =SUMIFS(Raw_Data!$AS$2:$AS$2552,Raw_Data!$D$2:$D$2552,$A14) | T14: =L14+R14 | U14: =SUMIFS(Raw_Data!$AU$2:$AU$2552,Raw_Data!$D$2:$D$2552,$A14) | V14: =IFERROR(B14/$B$17,"") | W14: =IFERROR(L14/$L$17,"")
A15: X | B15: =SUMIFS(Raw_Data!$R$2:$R$2552,Raw_Data!$D$2:$D$2552,$A15) | C15: =SUMIFS(Raw_Data!$S$2:$S$2552,Raw_Data!$D$2:$D$2552,$A15) | D15: =SUMIFS(Raw_Data!$T$2:$T$2552,Raw_Data!$D$2:$D$2552,$A15) | E15: =IFERROR(C15/D15,"") | F15: =SUMIFS(Raw_Data!$W$2:$W$2552,Raw_Data!$D$2:$D$2552,$A15) | G15: =IFERROR(F15/C15,"") | H15: =IFERROR(B15/F15,"") | I15: =IFERROR(B15/C15*1000,"") | J15: =SUMIFS(Raw_Data!$AA$2:$AA$2552,Raw_Data!$D$2:$D$2552,$A15) | K15: =IFERROR(J15/F15,"") | L15: =SUMIFS(Raw_Data!$AL$2:$AL$2552,Raw_Data!$D$2:$D$2552,$A15) | M15: =IFERROR(L15/J15,"") | N15: =IFERROR(B15/L15,"") | O15: =SUMIFS(Raw_Data!$AO$2:$AO$2552,Raw_Data!$D$2:$D$2552,$A15) | P15: =IFERROR(O15/L15,"") | Q15: =IFERROR(B15/O15,"") | R15: =SUMIFS(Raw_Data!$AR$2:$AR$2552,Raw_Data!$D$2:$D$2552,$A15) | S15: =SUMIFS(Raw_Data!$AS$2:$AS$2552,Raw_Data!$D$2:$D$2552,$A15) | T15: =L15+R15 | U15: =SUMIFS(Raw_Data!$AU$2:$AU$2552,Raw_Data!$D$2:$D$2552,$A15) | V15: =IFERROR(B15/$B$17,"") | W15: =IFERROR(L15/$L$17,"")
A16: Programmatic | B16: =SUMIFS(Raw_Data!$R$2:$R$2552,Raw_Data!$D$2:$D$2552,$A16) | C16: =SUMIFS(Raw_Data!$S$2:$S$2552,Raw_Data!$D$2:$D$2552,$A16) | D16: =SUMIFS(Raw_Data!$T$2:$T$2552,Raw_Data!$D$2:$D$2552,$A16) | E16: =IFERROR(C16/D16,"") | F16: =SUMIFS(Raw_Data!$W$2:$W$2552,Raw_Data!$D$2:$D$2552,$A16) | G16: =IFERROR(F16/C16,"") | H16: =IFERROR(B16/F16,"") | I16: =IFERROR(B16/C16*1000,"") | J16: =SUMIFS(Raw_Data!$AA$2:$AA$2552,Raw_Data!$D$2:$D$2552,$A16) | K16: =IFERROR(J16/F16,"") | L16: =SUMIFS(Raw_Data!$AL$2:$AL$2552,Raw_Data!$D$2:$D$2552,$A16) | M16: =IFERROR(L16/J16,"") | N16: =IFERROR(B16/L16,"") | O16: =SUMIFS(Raw_Data!$AO$2:$AO$2552,Raw_Data!$D$2:$D$2552,$A16) | P16: =IFERROR(O16/L16,"") | Q16: =IFERROR(B16/O16,"") | R16: =SUMIFS(Raw_Data!$AR$2:$AR$2552,Raw_Data!$D$2:$D$2552,$A16) | S16: =SUMIFS(Raw_Data!$AS$2:$AS$2552,Raw_Data!$D$2:$D$2552,$A16) | T16: =L16+R16 | U16: =SUMIFS(Raw_Data!$AU$2:$AU$2552,Raw_Data!$D$2:$D$2552,$A16) | V16: =IFERROR(B16/$B$17,"") | W16: =IFERROR(L16/$L$17,"")
A17: TOTAL / BLENDED | E17: =IFERROR(C17/D17,"") | G17: =IFERROR(F17/C17,"") | H17: =IFERROR(B17/F17,"") | I17: =IFERROR(B17/C17*1000,"") | K17: =IFERROR(J17/F17,"") | M17: =IFERROR(L17/J17,"") | N17: =IFERROR(B17/L17,"") | P17: =IFERROR(O17/L17,"") | Q17: =IFERROR(B17/O17,"") | T17: =L17+R17 | V17: =IFERROR(B17/$B$17,"") | W17: =IFERROR(L17/$L$17,"")
A19: PERFORMANCE BY MODEL
A20: Model | B20: Spend (ZAR) | C20: Impressions | D20: Reach (sum of daily) | E20: Avg Daily Frequency | F20: Link Clicks | G20: CTR (Link) | H20: CPC (Link) | I20: CPM | J20: Landing Page Views | K20: LPV Rate | L20: Test Drive Bookings | M20: CVR (Booking / LPV) | N20: CPL (Cost / Booking) | O20: Qualified Leads | P20: Qualified Rate | Q20: Cost per Qualified Lead | R20: View-Through Conv. | S20: Assisted Conv. | T20: Total Attributed Conv. | U20: Est. Revenue Pipeline (ZAR) | V20: % of Spend | W20: % of Bookings
A21: AMUR | B21: =SUMIFS(Raw_Data!$R$2:$R$2552,Raw_Data!$H$2:$H$2552,$A21) | C21: =SUMIFS(Raw_Data!$S$2:$S$2552,Raw_Data!$H$2:$H$2552,$A21) | D21: =SUMIFS(Raw_Data!$T$2:$T$2552,Raw_Data!$H$2:$H$2552,$A21) | E21: =IFERROR(C21/D21,"") | F21: =SUMIFS(Raw_Data!$W$2:$W$2552,Raw_Data!$H$2:$H$2552,$A21) | G21: =IFERROR(F21/C21,"") | H21: =IFERROR(B21/F21,"") | I21: =IFERROR(B21/C21*1000,"") | J21: =SUMIFS(Raw_Data!$AA$2:$AA$2552,Raw_Data!$H$2:$H$2552,$A21) | K21: =IFERROR(J21/F21,"") | L21: =SUMIFS(Raw_Data!$AL$2:$AL$2552,Raw_Data!$H$2:$H$2552,$A21) | M21: =IFERROR(L21/J21,"") | N21: =IFERROR(B21/L21,"") | O21: =SUMIFS(Raw_Data!$AO$2:$AO$2552,Raw_Data!$H$2:$H$2552,$A21) | P21: =IFERROR(O21/L21,"") | Q21: =IFERROR(B21/O21,"") | R21: =SUMIFS(Raw_Data!$AR$2:$AR$2552,Raw_Data!$H$2:$H$2552,$A21) | S21: =SUMIFS(Raw_Data!$AS$2:$AS$2552,Raw_Data!$H$2:$H$2552,$A21) | T21: =L21+R21 | U21: =SUMIFS(Raw_Data!$AU$2:$AU$2552,Raw_Data!$H$2:$H$2552,$A21) | V21: =IFERROR(B21/$B$17,"") | W21: =IFERROR(L21/$L$17,"")
A22: JAVAN | B22: =SUMIFS(Raw_Data!$R$2:$R$2552,Raw_Data!$H$2:$H$2552,$A22) | C22: =SUMIFS(Raw_Data!$S$2:$S$2552,Raw_Data!$H$2:$H$2552,$A22) | D22: =SUMIFS(Raw_Data!$T$2:$T$2552,Raw_Data!$H$2:$H$2552,$A22) | E22: =IFERROR(C22/D22,"") | F22: =SUMIFS(Raw_Data!$W$2:$W$2552,Raw_Data!$H$2:$H$2552,$A22) | G22: =IFERROR(F22/C22,"") | H22: =IFERROR(B22/F22,"") | I22: =IFERROR(B22/C22*1000,"") | J22: =SUMIFS(Raw_Data!$AA$2:$AA$2552,Raw_Data!$H$2:$H$2552,$A22) | K22: =IFERROR(J22/F22,"") | L22: =SUMIFS(Raw_Data!$AL$2:$AL$2552,Raw_Data!$H$2:$H$2552,$A22) | M22: =IFERROR(L22/J22,"") | N22: =IFERROR(B22/L22,"") | O22: =SUMIFS(Raw_Data!$AO$2:$AO$2552,Raw_Data!$H$2:$H$2552,$A22) | P22: =IFERROR(O22/L22,"") | Q22: =IFERROR(B22/O22,"") | R22: =SUMIFS(Raw_Data!$AR$2:$AR$2552,Raw_Data!$H$2:$H$2552,$A22) | S22: =SUMIFS(Raw_Data!$AS$2:$AS$2552,Raw_Data!$H$2:$H$2552,$A22) | T22: =L22+R22 | U22: =SUMIFS(Raw_Data!$AU$2:$AU$2552,Raw_Data!$H$2:$H$2552,$A22) | V22: =IFERROR(B22/$B$17,"") | W22: =IFERROR(L22/$L$17,"")
A23: PANTERA | B23: =SUMIFS(Raw_Data!$R$2:$R$2552,Raw_Data!$H$2:$H$2552,$A23) | C23: =SUMIFS(Raw_Data!$S$2:$S$2552,Raw_Data!$H$2:$H$2552,$A23) | D23: =SUMIFS(Raw_Data!$T$2:$T$2552,Raw_Data!$H$2:$H$2552,$A23) | E23: =IFERROR(C23/D23,"") | F23: =SUMIFS(Raw_Data!$W$2:$W$2552,Raw_Data!$H$2:$H$2552,$A23) | G23: =IFERROR(F23/C23,"") | H23: =IFERROR(B23/F23,"") | I23: =IFERROR(B23/C23*1000,"") | J23: =SUMIFS(Raw_Data!$AA$2:$AA$2552,Raw_Data!$H$2:$H$2552,$A23) | K23: =IFERROR(J23/F23,"") | L23: =SUMIFS(Raw_Data!$AL$2:$AL$2552,Raw_Data!$H$2:$H$2552,$A23) | M23: =IFERROR(L23/J23,"") | N23: =IFERROR(B23/L23,"") | O23: =SUMIFS(Raw_Data!$AO$2:$AO$2552,Raw_Data!$H$2:$H$2552,$A23) | P23: =IFERROR(O23/L23,"") | Q23: =IFERROR(B23/O23,"") | R23: =SUMIFS(Raw_Data!$AR$2:$AR$2552,Raw_Data!$H$2:$H$2552,$A23) | S23: =SUMIFS(Raw_Data!$AS$2:$AS$2552,Raw_Data!$H$2:$H$2552,$A23) | T23: =L23+R23 | U23: =SUMIFS(Raw_Data!$AU$2:$AU$2552,Raw_Data!$H$2:$H$2552,$A23) | V23: =IFERROR(B23/$B$17,"") | W23: =IFERROR(L23/$L$17,"")
A24: Range | B24: =SUMIFS(Raw_Data!$R$2:$R$2552,Raw_Data!$H$2:$H$2552,$A24) | C24: =SUMIFS(Raw_Data!$S$2:$S$2552,Raw_Data!$H$2:$H$2552,$A24) | D24: =SUMIFS(Raw_Data!$T$2:$T$2552,Raw_Data!$H$2:$H$2552,$A24) | E24: =IFERROR(C24/D24,"") | F24: =SUMIFS(Raw_Data!$W$2:$W$2552,Raw_Data!$H$2:$H$2552,$A24) | G24: =IFERROR(F24/C24,"") | H24: =IFERROR(B24/F24,"") | I24: =IFERROR(B24/C24*1000,"") | J24: =SUMIFS(Raw_Data!$AA$2:$AA$2552,Raw_Data!$H$2:$H$2552,$A24) | K24: =IFERROR(J24/F24,"") | L24: =SUMIFS(Raw_Data!$AL$2:$AL$2552,Raw_Data!$H$2:$H$2552,$A24) | M24: =IFERROR(L24/J24,"") | N24: =IFERROR(B24/L24,"") | O24: =SUMIFS(Raw_Data!$AO$2:$AO$2552,Raw_Data!$H$2:$H$2552,$A24) | P24: =IFERROR(O24/L24,"") | Q24: =IFERROR(B24/O24,"") | R24: =SUMIFS(Raw_Data!$AR$2:$AR$2552,Raw_Data!$H$2:$H$2552,$A24) | S24: =SUMIFS(Raw_Data!$AS$2:$AS$2552,Raw_Data!$H$2:$H$2552,$A24) | T24: =L24+R24 | U24: =SUMIFS(Raw_Data!$AU$2:$AU$2552,Raw_Data!$H$2:$H$2552,$A24) | V24: =IFERROR(B24/$B$17,"") | W24: =IFERROR(L24/$L$17,"")
A25: TOTAL | E25: =IFERROR(C25/D25,"") | G25: =IFERROR(F25/C25,"") | H25: =IFERROR(B25/F25,"") | I25: =IFERROR(B25/C25*1000,"") | K25: =IFERROR(J25/F25,"") | M25: =IFERROR(L25/J25,"") | N25: =IFERROR(B25/L25,"") | P25: =IFERROR(O25/L25,"") | Q25: =IFERROR(B25/O25,"") | T25: =L25+R25 | V25: =IFERROR(B25/$B$17,"") | W25: =IFERROR(L25/$L$17,"")
A27: PERFORMANCE BY AUDIENCE STRATEGY
A28: Audience Type | B28: Spend (ZAR) | C28: Impressions | D28: Reach (sum of daily) | E28: Avg Daily Frequency | F28: Link Clicks | G28: CTR (Link) | H28: CPC (Link) | I28: CPM | J28: Landing Page Views | K28: LPV Rate | L28: Test Drive Bookings | M28: CVR (Booking / LPV) | N28: CPL (Cost / Booking) | O28: Qualified Leads | P28: Qualified Rate | Q28: Cost per Qualified Lead | R28: View-Through Conv. | S28: Assisted Conv. | T28: Total Attributed Conv. | U28: Est. Revenue Pipeline (ZAR) | V28: % of Spend | W28: % of Bookings
A29: Contextual | B29: =SUMIFS(Raw_Data!$R$2:$R$2552,Raw_Data!$K$2:$K$2552,$A29) | C29: =SUMIFS(Raw_Data!$S$2:$S$2552,Raw_Data!$K$2:$K$2552,$A29) | D29: =SUMIFS(Raw_Data!$T$2:$T$2552,Raw_Data!$K$2:$K$2552,$A29) | E29: =IFERROR(C29/D29,"") | F29: =SUMIFS(Raw_Data!$W$2:$W$2552,Raw_Data!$K$2:$K$2552,$A29) | G29: =IFERROR(F29/C29,"") | H29: =IFERROR(B29/F29,"") | I29: =IFERROR(B29/C29*1000,"") | J29: =SUMIFS(Raw_Data!$AA$2:$AA$2552,Raw_Data!$K$2:$K$2552,$A29) | K29: =IFERROR(J29/F29,"") | L29: =SUMIFS(Raw_Data!$AL$2:$AL$2552,Raw_Data!$K$2:$K$2552,$A29) | M29: =IFERROR(L29/J29,"") | N29: =IFERROR(B29/L29,"") | O29: =SUMIFS(Raw_Data!$AO$2:$AO$2552,Raw_Data!$K$2:$K$2552,$A29) | P29: =IFERROR(O29/L29,"") | Q29: =IFERROR(B29/O29,"") | R29: =SUMIFS(Raw_Data!$AR$2:$AR$2552,Raw_Data!$K$2:$K$2552,$A29) | S29: =SUMIFS(Raw_Data!$AS$2:$AS$2552,Raw_Data!$K$2:$K$2552,$A29) | T29: =L29+R29 | U29: =SUMIFS(Raw_Data!$AU$2:$AU$2552,Raw_Data!$K$2:$K$2552,$A29) | V29: =IFERROR(B29/$B$17,"") | W29: =IFERROR(L29/$L$17,"")
A30: In-Market | B30: =SUMIFS(Raw_Data!$R$2:$R$2552,Raw_Data!$K$2:$K$2552,$A30) | C30: =SUMIFS(Raw_Data!$S$2:$S$2552,Raw_Data!$K$2:$K$2552,$A30) | D30: =SUMIFS(Raw_Data!$T$2:$T$2552,Raw_Data!$K$2:$K$2552,$A30) | E30: =IFERROR(C30/D30,"") | F30: =SUMIFS(Raw_Data!$W$2:$W$2552,Raw_Data!$K$2:$K$2552,$A30) | G30: =IFERROR(F30/C30,"") | H30: =IFERROR(B30/F30,"") | I30: =IFERROR(B30/C30*1000,"") | J30: =SUMIFS(Raw_Data!$AA$2:$AA$2552,Raw_Data!$K$2:$K$2552,$A30) | K30: =IFERROR(J30/F30,"") | L30: =SUMIFS(Raw_Data!$AL$2:$AL$2552,Raw_Data!$K$2:$K$2552,$A30) | M30: =IFERROR(L30/J30,"") | N30: =IFERROR(B30/L30,"") | O30: =SUMIFS(Raw_Data!$AO$2:$AO$2552,Raw_Data!$K$2:$K$2552,$A30) | P30: =IFERROR(O30/L30,"") | Q30: =IFERROR(B30/O30,"") | R30: =SUMIFS(Raw_Data!$AR$2:$AR$2552,Raw_Data!$K$2:$K$2552,$A30) | S30: =SUMIFS(Raw_Data!$AS$2:$AS$2552,Raw_Data!$K$2:$K$2552,$A30) | T30: =L30+R30 | U30: =SUMIFS(Raw_Data!$AU$2:$AU$2552,Raw_Data!$K$2:$K$2552,$A30) | V30: =IFERROR(B30/$B$17,"") | W30: =IFERROR(L30/$L$17,"")
A31: Interest | B31: =SUMIFS(Raw_Data!$R$2:$R$2552,Raw_Data!$K$2:$K$2552,$A31) | C31: =SUMIFS(Raw_Data!$S$2:$S$2552,Raw_Data!$K$2:$K$2552,$A31) | D31: =SUMIFS(Raw_Data!$T$2:$T$2552,Raw_Data!$K$2:$K$2552,$A31) | E31: =IFERROR(C31/D31,"") | F31: =SUMIFS(Raw_Data!$W$2:$W$2552,Raw_Data!$K$2:$K$2552,$A31) | G31: =IFERROR(F31/C31,"") | H31: =IFERROR(B31/F31,"") | I31: =IFERROR(B31/C31*1000,"") | J31: =SUMIFS(Raw_Data!$AA$2:$AA$2552,Raw_Data!$K$2:$K$2552,$A31) | K31: =IFERROR(J31/F31,"") | L31: =SUMIFS(Raw_Data!$AL$2:$AL$2552,Raw_Data!$K$2:$K$2552,$A31) | M31: =IFERROR(L31/J31,"") | N31: =IFERROR(B31/L31,"") | O31: =SUMIFS(Raw_Data!$AO$2:$AO$2552,Raw_Data!$K$2:$K$2552,$A31) | P31: =IFERROR(O31/L31,"") | Q31: =IFERROR(B31/O31,"") | R31: =SUMIFS(Raw_Data!$AR$2:$AR$2552,Raw_Data!$K$2:$K$2552,$A31) | S31: =SUMIFS(Raw_Data!$AS$2:$AS$2552,Raw_Data!$K$2:$K$2552,$A31) | T31: =L31+R31 | U31: =SUMIFS(Raw_Data!$AU$2:$AU$2552,Raw_Data!$K$2:$K$2552,$A31) | V31: =IFERROR(B31/$B$17,"") | W31: =IFERROR(L31/$L$17,"")
A32: Lookalike | B32: =SUMIFS(Raw_Data!$R$2:$R$2552,Raw_Data!$K$2:$K$2552,$A32) | C32: =SUMIFS(Raw_Data!$S$2:$S$2552,Raw_Data!$K$2:$K$2552,$A32) | D32: =SUMIFS(Raw_Data!$T$2:$T$2552,Raw_Data!$K$2:$K$2552,$A32) | E32: =IFERROR(C32/D32,"") | F32: =SUMIFS(Raw_Data!$W$2:$W$2552,Raw_Data!$K$2:$K$2552,$A32) | G32: =IFERROR(F32/C32,"") | H32: =IFERROR(B32/F32,"") | I32: =IFERROR(B32/C32*1000,"") | J32: =SUMIFS(Raw_Data!$AA$2:$AA$2552,Raw_Data!$K$2:$K$2552,$A32) | K32: =IFERROR(J32/F32,"") | L32: =SUMIFS(Raw_Data!$AL$2:$AL$2552,Raw_Data!$K$2:$K$2552,$A32) | M32: =IFERROR(L32/J32,"") | N32: =IFERROR(B32/L32,"") | O32: =SUMIFS(Raw_Data!$AO$2:$AO$2552,Raw_Data!$K$2:$K$2552,$A32) | P32: =IFERROR(O32/L32,"") | Q32: =IFERROR(B32/O32,"") | R32: =SUMIFS(Raw_Data!$AR$2:$AR$2552,Raw_Data!$K$2:$K$2552,$A32) | S32: =SUMIFS(Raw_Data!$AS$2:$AS$2552,Raw_Data!$K$2:$K$2552,$A32) | T32: =L32+R32 | U32: =SUMIFS(Raw_Data!$AU$2:$AU$2552,Raw_Data!$K$2:$K$2552,$A32) | V32: =IFERROR(B32/$B$17,"") | W32: =IFERROR(L32/$L$17,"")
A33: Prospecting | B33: =SUMIFS(Raw_Data!$R$2:$R$2552,Raw_Data!$K$2:$K$2552,$A33) | C33: =SUMIFS(Raw_Data!$S$2:$S$2552,Raw_Data!$K$2:$K$2552,$A33) | D33: =SUMIFS(Raw_Data!$T$2:$T$2552,Raw_Data!$K$2:$K$2552,$A33) | E33: =IFERROR(C33/D33,"") | F33: =SUMIFS(Raw_Data!$W$2:$W$2552,Raw_Data!$K$2:$K$2552,$A33) | G33: =IFERROR(F33/C33,"") | H33: =IFERROR(B33/F33,"") | I33: =IFERROR(B33/C33*1000,"") | J33: =SUMIFS(Raw_Data!$AA$2:$AA$2552,Raw_Data!$K$2:$K$2552,$A33) | K33: =IFERROR(J33/F33,"") | L33: =SUMIFS(Raw_Data!$AL$2:$AL$2552,Raw_Data!$K$2:$K$2552,$A33) | M33: =IFERROR(L33/J33,"") | N33: =IFERROR(B33/L33,"") | O33: =SUMIFS(Raw_Data!$AO$2:$AO$2552,Raw_Data!$K$2:$K$2552,$A33) | P33: =IFERROR(O33/L33,"") | Q33: =IFERROR(B33/O33,"") | R33: =SUMIFS(Raw_Data!$AR$2:$AR$2552,Raw_Data!$K$2:$K$2552,$A33) | S33: =SUMIFS(Raw_Data!$AS$2:$AS$2552,Raw_Data!$K$2:$K$2552,$A33) | T33: =L33+R33 | U33: =SUMIFS(Raw_Data!$AU$2:$AU$2552,Raw_Data!$K$2:$K$2552,$A33) | V33: =IFERROR(B33/$B$17,"") | W33: =IFERROR(L33/$L$17,"")
A34: Retargeting | B34: =SUMIFS(Raw_Data!$R$2:$R$2552,Raw_Data!$K$2:$K$2552,$A34) | C34: =SUMIFS(Raw_Data!$S$2:$S$2552,Raw_Data!$K$2:$K$2552,$A34) | D34: =SUMIFS(Raw_Data!$T$2:$T$2552,Raw_Data!$K$2:$K$2552,$A34) | E34: =IFERROR(C34/D34,"") | F34: =SUMIFS(Raw_Data!$W$2:$W$2552,Raw_Data!$K$2:$K$2552,$A34) | G34: =IFERROR(F34/C34,"") | H34: =IFERROR(B34/F34,"") | I34: =IFERROR(B34/C34*1000,"") | J34: =SUMIFS(Raw_Data!$AA$2:$AA$2552,Raw_Data!$K$2:$K$2552,$A34) | K34: =IFERROR(J34/F34,"") | L34: =SUMIFS(Raw_Data!$AL$2:$AL$2552,Raw_Data!$K$2:$K$2552,$A34) | M34: =IFERROR(L34/J34,"") | N34: =IFERROR(B34/L34,"") | O34: =SUMIFS(Raw_Data!$AO$2:$AO$2552,Raw_Data!$K$2:$K$2552,$A34) | P34: =IFERROR(O34/L34,"") | Q34: =IFERROR(B34/O34,"") | R34: =SUMIFS(Raw_Data!$AR$2:$AR$2552,Raw_Data!$K$2:$K$2552,$A34) | S34: =SUMIFS(Raw_Data!$AS$2:$AS$2552,Raw_Data!$K$2:$K$2552,$A34) | T34: =L34+R34 | U34: =SUMIFS(Raw_Data!$AU$2:$AU$2552,Raw_Data!$K$2:$K$2552,$A34) | V34: =IFERROR(B34/$B$17,"") | W34: =IFERROR(L34/$L$17,"")
A35: TOTAL | E35: =IFERROR(C35/D35,"") | G35: =IFERROR(F35/C35,"") | H35: =IFERROR(B35/F35,"") | I35: =IFERROR(B35/C35*1000,"") | K35: =IFERROR(J35/F35,"") | M35: =IFERROR(L35/J35,"") | N35: =IFERROR(B35/L35,"") | P35: =IFERROR(O35/L35,"") | Q35: =IFERROR(B35/O35,"") | T35: =L35+R35 | V35: =IFERROR(B35/$B$17,"") | W35: =IFERROR(L35/$L$17,"")
A37: PERFORMANCE BY WEEK
A38: ISO Week | B38: Spend (ZAR) | C38: Impressions | D38: Reach (sum of daily) | E38: Avg Daily Frequency | F38: Link Clicks | G38: CTR (Link) | H38: CPC (Link) | I38: CPM | J38: Landing Page Views | K38: LPV Rate | L38: Test Drive Bookings | M38: CVR (Booking / LPV) | N38: CPL (Cost / Booking) | O38: Qualified Leads | P38: Qualified Rate | Q38: Cost per Qualified Lead | R38: View-Through Conv. | S38: Assisted Conv. | T38: Total Attributed Conv. | U38: Est. Revenue Pipeline (ZAR) | V38: % of Spend | W38: % of Bookings
A39: Wk 31 | B39: =SUMIFS(Raw_Data!$R$2:$R$2552,Raw_Data!$B$2:$B$2552,$A39) | C39: =SUMIFS(Raw_Data!$S$2:$S$2552,Raw_Data!$B$2:$B$2552,$A39) | D39: =SUMIFS(Raw_Data!$T$2:$T$2552,Raw_Data!$B$2:$B$2552,$A39) | E39: =IFERROR(C39/D39,"") | F39: =SUMIFS(Raw_Data!$W$2:$W$2552,Raw_Data!$B$2:$B$2552,$A39) | G39: =IFERROR(F39/C39,"") | H39: =IFERROR(B39/F39,"") | I39: =IFERROR(B39/C39*1000,"") | J39: =SUMIFS(Raw_Data!$AA$2:$AA$2552,Raw_Data!$B$2:$B$2552,$A39) | K39: =IFERROR(J39/F39,"") | L39: =SUMIFS(Raw_Data!$AL$2:$AL$2552,Raw_Data!$B$2:$B$2552,$A39) | M39: =IFERROR(L39/J39,"") | N39: =IFERROR(B39/L39,"") | O39: =SUMIFS(Raw_Data!$AO$2:$AO$2552,Raw_Data!$B$2:$B$2552,$A39) | P39: =IFERROR(O39/L39,"") | Q39: =IFERROR(B39/O39,"") | R39: =SUMIFS(Raw_Data!$AR$2:$AR$2552,Raw_Data!$B$2:$B$2552,$A39) | S39: =SUMIFS(Raw_Data!$AS$2:$AS$2552,Raw_Data!$B$2:$B$2552,$A39) | T39: =L39+R39 | U39: =SUMIFS(Raw_Data!$AU$2:$AU$2552,Raw_Data!$B$2:$B$2552,$A39) | V39: =IFERROR(B39/$B$17,"") | W39: =IFERROR(L39/$L$17,"")
A40: Wk 32 | B40: =SUMIFS(Raw_Data!$R$2:$R$2552,Raw_Data!$B$2:$B$2552,$A40) | C40: =SUMIFS(Raw_Data!$S$2:$S$2552,Raw_Data!$B$2:$B$2552,$A40) | D40: =SUMIFS(Raw_Data!$T$2:$T$2552,Raw_Data!$B$2:$B$2552,$A40) | E40: =IFERROR(C40/D40,"") | F40: =SUMIFS(Raw_Data!$W$2:$W$2552,Raw_Data!$B$2:$B$2552,$A40) | G40: =IFERROR(F40/C40,"") | H40: =IFERROR(B40/F40,"") | I40: =IFERROR(B40/C40*1000,"") | J40: =SUMIFS(Raw_Data!$AA$2:$AA$2552,Raw_Data!$B$2:$B$2552,$A40) | K40: =IFERROR(J40/F40,"") | L40: =SUMIFS(Raw_Data!$AL$2:$AL$2552,Raw_Data!$B$2:$B$2552,$A40) | M40: =IFERROR(L40/J40,"") | N40: =IFERROR(B40/L40,"") | O40: =SUMIFS(Raw_Data!$AO$2:$AO$2552,Raw_Data!$B$2:$B$2552,$A40) | P40: =IFERROR(O40/L40,"") | Q40: =IFERROR(B40/O40,"") | R40: =SUMIFS(Raw_Data!$AR$2:$AR$2552,Raw_Data!$B$2:$B$2552,$A40) | S40: =SUMIFS(Raw_Data!$AS$2:$AS$2552,Raw_Data!$B$2:$B$2552,$A40) | T40: =L40+R40 | U40: =SUMIFS(Raw_Data!$AU$2:$AU$2552,Raw_Data!$B$2:$B$2552,$A40) | V40: =IFERROR(B40/$B$17,"") | W40: =IFERROR(L40/$L$17,"")
A41: Wk 33 | B41: =SUMIFS(Raw_Data!$R$2:$R$2552,Raw_Data!$B$2:$B$2552,$A41) | C41: =SUMIFS(Raw_Data!$S$2:$S$2552,Raw_Data!$B$2:$B$2552,$A41) | D41: =SUMIFS(Raw_Data!$T$2:$T$2552,Raw_Data!$B$2:$B$2552,$A41) | E41: =IFERROR(C41/D41,"") | F41: =SUMIFS(Raw_Data!$W$2:$W$2552,Raw_Data!$B$2:$B$2552,$A41) | G41: =IFERROR(F41/C41,"") | H41: =IFERROR(B41/F41,"") | I41: =IFERROR(B41/C41*1000,"") | J41: =SUMIFS(Raw_Data!$AA$2:$AA$2552,Raw_Data!$B$2:$B$2552,$A41) | K41: =IFERROR(J41/F41,"") | L41: =SUMIFS(Raw_Data!$AL$2:$AL$2552,Raw_Data!$B$2:$B$2552,$A41) | M41: =IFERROR(L41/J41,"") | N41: =IFERROR(B41/L41,"") | O41: =SUMIFS(Raw_Data!$AO$2:$AO$2552,Raw_Data!$B$2:$B$2552,$A41) | P41: =IFERROR(O41/L41,"") | Q41: =IFERROR(B41/O41,"") | R41: =SUMIFS(Raw_Data!$AR$2:$AR$2552,Raw_Data!$B$2:$B$2552,$A41) | S41: =SUMIFS(Raw_Data!$AS$2:$AS$2552,Raw_Data!$B$2:$B$2552,$A41) | T41: =L41+R41 | U41: =SUMIFS(Raw_Data!$AU$2:$AU$2552,Raw_Data!$B$2:$B$2552,$A41) | V41: =IFERROR(B41/$B$17,"") | W41: =IFERROR(L41/$L$17,"")
A42: Wk 34 | B42: =SUMIFS(Raw_Data!$R$2:$R$2552,Raw_Data!$B$2:$B$2552,$A42) | C42: =SUMIFS(Raw_Data!$S$2:$S$2552,Raw_Data!$B$2:$B$2552,$A42) | D42: =SUMIFS(Raw_Data!$T$2:$T$2552,Raw_Data!$B$2:$B$2552,$A42) | E42: =IFERROR(C42/D42,"") | F42: =SUMIFS(Raw_Data!$W$2:$W$2552,Raw_Data!$B$2:$B$2552,$A42) | G42: =IFERROR(F42/C42,"") | H42: =IFERROR(B42/F42,"") | I42: =IFERROR(B42/C42*1000,"") | J42: =SUMIFS(Raw_Data!$AA$2:$AA$2552,Raw_Data!$B$2:$B$2552,$A42) | K42: =IFERROR(J42/F42,"") | L42: =SUMIFS(Raw_Data!$AL$2:$AL$2552,Raw_Data!$B$2:$B$2552,$A42) | M42: =IFERROR(L42/J42,"") | N42: =IFERROR(B42/L42,"") | O42: =SUMIFS(Raw_Data!$AO$2:$AO$2552,Raw_Data!$B$2:$B$2552,$A42) | P42: =IFERROR(O42/L42,"") | Q42: =IFERROR(B42/O42,"") | R42: =SUMIFS(Raw_Data!$AR$2:$AR$2552,Raw_Data!$B$2:$B$2552,$A42) | S42: =SUMIFS(Raw_Data!$AS$2:$AS$2552,Raw_Data!$B$2:$B$2552,$A42) | T42: =L42+R42 | U42: =SUMIFS(Raw_Data!$AU$2:$AU$2552,Raw_Data!$B$2:$B$2552,$A42) | V42: =IFERROR(B42/$B$17,"") | W42: =IFERROR(L42/$L$17,"")
A43: Wk 35 | B43: =SUMIFS(Raw_Data!$R$2:$R$2552,Raw_Data!$B$2:$B$2552,$A43) | C43: =SUMIFS(Raw_Data!$S$2:$S$2552,Raw_Data!$B$2:$B$2552,$A43) | D43: =SUMIFS(Raw_Data!$T$2:$T$2552,Raw_Data!$B$2:$B$2552,$A43) | E43: =IFERROR(C43/D43,"") | F43: =SUMIFS(Raw_Data!$W$2:$W$2552,Raw_Data!$B$2:$B$2552,$A43) | G43: =IFERROR(F43/C43,"") | H43: =IFERROR(B43/F43,"") | I43: =IFERROR(B43/C43*1000,"") | J43: =SUMIFS(Raw_Data!$AA$2:$AA$2552,Raw_Data!$B$2:$B$2552,$A43) | K43: =IFERROR(J43/F43,"") | L43: =SUMIFS(Raw_Data!$AL$2:$AL$2552,Raw_Data!$B$2:$B$2552,$A43) | M43: =IFERROR(L43/J43,"") | N43: =IFERROR(B43/L43,"") | O43: =SUMIFS(Raw_Data!$AO$2:$AO$2552,Raw_Data!$B$2:$B$2552,$A43) | P43: =IFERROR(O43/L43,"") | Q43: =IFERROR(B43/O43,"") | R43: =SUMIFS(Raw_Data!$AR$2:$AR$2552,Raw_Data!$B$2:$B$2552,$A43) | S43: =SUMIFS(Raw_Data!$AS$2:$AS$2552,Raw_Data!$B$2:$B$2552,$A43) | T43: =L43+R43 | U43: =SUMIFS(Raw_Data!$AU$2:$AU$2552,Raw_Data!$B$2:$B$2552,$A43) | V43: =IFERROR(B43/$B$17,"") | W43: =IFERROR(L43/$L$17,"")
A44: Wk 36 | B44: =SUMIFS(Raw_Data!$R$2:$R$2552,Raw_Data!$B$2:$B$2552,$A44) | C44: =SUMIFS(Raw_Data!$S$2:$S$2552,Raw_Data!$B$2:$B$2552,$A44) | D44: =SUMIFS(Raw_Data!$T$2:$T$2552,Raw_Data!$B$2:$B$2552,$A44) | E44: =IFERROR(C44/D44,"") | F44: =SUMIFS(Raw_Data!$W$2:$W$2552,Raw_Data!$B$2:$B$2552,$A44) | G44: =IFERROR(F44/C44,"") | H44: =IFERROR(B44/F44,"") | I44: =IFERROR(B44/C44*1000,"") | J44: =SUMIFS(Raw_Data!$AA$2:$AA$2552,Raw_Data!$B$2:$B$2552,$A44) | K44: =IFERROR(J44/F44,"") | L44: =SUMIFS(Raw_Data!$AL$2:$AL$2552,Raw_Data!$B$2:$B$2552,$A44) | M44: =IFERROR(L44/J44,"") | N44: =IFERROR(B44/L44,"") | O44: =SUMIFS(Raw_Data!$AO$2:$AO$2552,Raw_Data!$B$2:$B$2552,$A44) | P44: =IFERROR(O44/L44,"") | Q44: =IFERROR(B44/O44,"") | R44: =SUMIFS(Raw_Data!$AR$2:$AR$2552,Raw_Data!$B$2:$B$2552,$A44) | S44: =SUMIFS(Raw_Data!$AS$2:$AS$2552,Raw_Data!$B$2:$B$2552,$A44) | T44: =L44+R44 | U44: =SUMIFS(Raw_Data!$AU$2:$AU$2552,Raw_Data!$B$2:$B$2552,$A44) | V44: =IFERROR(B44/$B$17,"") | W44: =IFERROR(L44/$L$17,"")
A45: TOTAL | E45: =IFERROR(C45/D45,"") | G45: =IFERROR(F45/C45,"") | H45: =IFERROR(B45/F45,"") | I45: =IFERROR(B45/C45*1000,"") | K45: =IFERROR(J45/F45,"") | M45: =IFERROR(L45/J45,"") | N45: =IFERROR(B45/L45,"") | P45: =IFERROR(O45/L45,"") | Q45: =IFERROR(B45/O45,"") | T45: =L45+R45 | V45: =IFERROR(B45/$B$17,"") | W45: =IFERROR(L45/$L$17,"")

Sheet Daily_Trend
A1: Daily Trend — 1 to 31 August 2026
A2: Total market delivery per day, cumulative pacing against the R400,000 plan, and per-channel spend / bookings / CPL for charting.
A4: Date | B4: Day | C4: Week | D4: Spend (ZAR) | E4: Impressions | F4: Reach (sum of daily) | G4: Avg Daily Frequency | H4: Link Clicks | I4: CTR (Link) | J4: CPC (Link) | K4: CPM | L4: Landing Page Views | M4: LPV Rate | N4: Test Drive Bookings | O4: CVR (Booking / LPV) | P4: CPL (Cost / Booking) | Q4: Qualified Leads | R4: Qualified Rate | S4: Cost per Qualified Lead | T4: View-Through Conv. | U4: Assisted Conv. | V4: Total Attributed Conv. | W4: Est. Revenue Pipeline (ZAR) | X4: % of Spend | Y4: % of Bookings | Z4: Cumulative Spend | AA4: Cumulative Bookings | AB4: Cumulative CPL | AC4: Budget Consumed | AD4: Month Elapsed | AE4: Pacing Index | AF4: Meta (FB/IG) Spend | AG4: Meta (FB/IG) Bookings | AH4: Meta (FB/IG) CPL | AI4: TikTok Spend | AJ4: TikTok Bookings | AK4: TikTok CPL | AL4: X Spend | AM4: X Bookings | AN4: X CPL | AO4: Programmatic Spend | AP4: Programmatic Bookings | AQ4: Programmatic CPL
A5: 46235 | B5: Sat | C5: Wk 31 | D5: =SUMIFS(Raw_Data!$R$2:$R$2552,Raw_Data!$A$2:$A$2552,$A5) | E5: =SUMIFS(Raw_Data!$S$2:$S$2552,Raw_Data!$A$2:$A$2552,$A5) | F5: =SUMIFS(Raw_Data!$T$2:$T$2552,Raw_Data!$A$2:$A$2552,$A5) | G5: =IFERROR(E5/F5,"") | H5: =SUMIFS(Raw_Data!$W$2:$W$2552,Raw_Data!$A$2:$A$2552,$A5) | I5: =IFERROR(H5/E5,"") | J5: =IFERROR(D5/H5,"") | K5: =IFERROR(D5/E5*1000,"") | L5: =SUMIFS(Raw_Data!$AA$2:$AA$2552,Raw_Data!$A$2:$A$2552,$A5) | M5: =IFERROR(L5/H5,"") | N5: =SUMIFS(Raw_Data!$AL$2:$AL$2552,Raw_Data!$A$2:$A$2552,$A5) | O5: =IFERROR(N5/L5,"") | P5: =IFERROR(D5/N5,"") | Q5: =SUMIFS(Raw_Data!$AO$2:$AO$2552,Raw_Data!$A$2:$A$2552,$A5) | R5: =IFERROR(Q5/N5,"") | S5: =IFERROR(D5/Q5,"") | T5: =SUMIFS(Raw_Data!$AR$2:$AR$2552,Raw_Data!$A$2:$A$2552,$A5) | U5: =SUMIFS(Raw_Data!$AS$2:$AS$2552,Raw_Data!$A$2:$A$2552,$A5) | V5: =N5+T5 | W5: =SUMIFS(Raw_Data!$AU$2:$AU$2552,Raw_Data!$A$2:$A$2552,$A5) | X5: =IFERROR(D5/$D$36,"") | Y5: =IFERROR(N5/$N$36,"") | Z5: =SUM($D$5:D5) | AA5: =SUM($N$5:N5) | AB5: =IFERROR(Z5/AA5,"") | AC5: =IFERROR(Z5/Assumptions!$C$10,"") | AD5: =1/31 | AE5: =IFERROR(AC5/AD5,"") | AF5: =SUMIFS(Raw_Data!$R$2:$R$2552,Raw_Data!$A$2:$A$2552,$A5,Raw_Data!$D$2:$D$2552,"Meta (FB/IG)") | AG5: =SUMIFS(Raw_Data!$AL$2:$AL$2552,Raw_Data!$A$2:$A$2552,$A5,Raw_Data!$D$2:$D$2552,"Meta (FB/IG)") | AH5: =IFERROR(AF5/AG5,"") | AI5: =SUMIFS(Raw_Data!$R$2:$R$2552,Raw_Data!$A$2:$A$2552,$A5,Raw_Data!$D$2:$D$2552,"TikTok") | AJ5: =SUMIFS(Raw_Data!$AL$2:$AL$2552,Raw_Data!$A$2:$A$2552,$A5,Raw_Data!$D$2:$D$2552,"TikTok") | AK5: =IFERROR(AI5/AJ5,"") | AL5: =SUMIFS(Raw_Data!$R$2:$R$2552,Raw_Data!$A$2:$A$2552,$A5,Raw_Data!$D$2:$D$2552,"X") | AM5: =SUMIFS(Raw_Data!$AL$2:$AL$2552,Raw_Data!$A$2:$A$2552,$A5,Raw_Data!$D$2:$D$2552,"X") | AN5: =IFERROR(AL5/AM5,"") | AO5: =SUMIFS(Raw_Data!$R$2:$R$2552,Raw_Data!$A$2:$A$2552,$A5,Raw_Data!$D$2:$D$2552,"Programmatic") | AP5: =SUMIFS(Raw_Data!$AL$2:$AL$2552,Raw_Data!$A$2:$A$2552,$A5,Raw_Data!$D$2:$D$2552,"Programmatic") | AQ5: =IFERROR(AO5/AP5,"")
A6: 46236 | B6: Sun | C6: Wk 31 | D6: =SUMIFS(Raw_Data!$R$2:$R$2552,Raw_Data!$A$2:$A$2552,$A6) | E6: =SUMIFS(Raw_Data!$S$2:$S$2552,Raw_Data!$A$2:$A$2552,$A6) | F6: =SUMIFS(Raw_Data!$T$2:$T$2552,Raw_Data!$A$2:$A$2552,$A6) | G6: =IFERROR(E6/F6,"") | H6: =SUMIFS(Raw_Data!$W$2:$W$2552,Raw_Data!$A$2:$A$2552,$A6) | I6: =IFERROR(H6/E6,"") | J6: =IFERROR(D6/H6,"") | K6: =IFERROR(D6/E6*1000,"") | L6: =SUMIFS(Raw_Data!$AA$2:$AA$2552,Raw_Data!$A$2:$A$2552,$A6) | M6: =IFERROR(L6/H6,"") | N6: =SUMIFS(Raw_Data!$AL$2:$AL$2552,Raw_Data!$A$2:$A$2552,$A6) | O6: =IFERROR(N6/L6,"") | P6: =IFERROR(D6/N6,"") | Q6: =SUMIFS(Raw_Data!$AO$2:$AO$2552,Raw_Data!$A$2:$A$2552,$A6) | R6: =IFERROR(Q6/N6,"") | S6: =IFERROR(D6/Q6,"") | T6: =SUMIFS(Raw_Data!$AR$2:$AR$2552,Raw_Data!$A$2:$A$2552,$A6) | U6: =SUMIFS(Raw_Data!$AS$2:$AS$2552,Raw_Data!$A$2:$A$2552,$A6) | V6: =N6+T6 | W6: =SUMIFS(Raw_Data!$AU$2:$AU$2552,Raw_Data!$A$2:$A$2552,$A6) | X6: =IFERROR(D6/$D$36,"") | Y6: =IFERROR(N6/$N$36,"") | Z6: =SUM($D$5:D6) | AA6: =SUM($N$5:N6) | AB6: =IFERROR(Z6/AA6,"") | AC6: =IFERROR(Z6/Assumptions!$C$10,"") | AD6: =2/31 | AE6: =IFERROR(AC6/AD6,"") | AF6: =SUMIFS(Raw_Data!$R$2:$R$2552,Raw_Data!$A$2:$A$2552,$A6,Raw_Data!$D$2:$D$2552,"Meta (FB/IG)") | AG6: =SUMIFS(Raw_Data!$AL$2:$AL$2552,Raw_Data!$A$2:$A$2552,$A6,Raw_Data!$D$2:$D$2552,"Meta (FB/IG)") | AH6: =IFERROR(AF6/AG6,"") | AI6: =SUMIFS(Raw_Data!$R$2:$R$2552,Raw_Data!$A$2:$A$2552,$A6,Raw_Data!$D$2:$D$2552,"TikTok") | AJ6: =SUMIFS(Raw_Data!$AL$2:$AL$2552,Raw_Data!$A$2:$A$2552,$A6,Raw_Data!$D$2:$D$2552,"TikTok") | AK6: =IFERROR(AI6/AJ6,"") | AL6: =SUMIFS(Raw_Data!$R$2:$R$2552,Raw_Data!$A$2:$A$2552,$A6,Raw_Data!$D$2:$D$2552,"X") | AM6: =SUMIFS(Raw_Data!$AL$2:$AL$2552,Raw_Data!$A$2:$A$2552,$A6,Raw_Data!$D$2:$D$2552,"X") | AN6: =IFERROR(AL6/AM6,"") | AO6: =SUMIFS(Raw_Data!$R$2:$R$2552,Raw_Data!$A$2:$A$2552,$A6,Raw_Data!$D$2:$D$2552,"Programmatic") | AP6: =SUMIFS(Raw_Data!$AL$2:$AL$2552,Raw_Data!$A$2:$A$2552,$A6,Raw_Data!$D$2:$D$2552,"Programmatic") | AQ6: =IFERROR(AO6/AP6,"")
A7: 46237 | B7: Mon | C7: Wk 32 | D7: =SUMIFS(Raw_Data!$R$2:$R$2552,Raw_Data!$A$2:$A$2552,$A7) | E7: =SUMIFS(Raw_Data!$S$2:$S$2552,Raw_Data!$A$2:$A$2552,$A7) | F7: =SUMIFS(Raw_Data!$T$2:$T$2552,Raw_Data!$A$2:$A$2552,$A7) | G7: =IFERROR(E7/F7,"") | H7: =SUMIFS(Raw_Data!$W$2:$W$2552,Raw_Data!$A$2:$A$2552,$A7) | I7: =IFERROR(H7/E7,"") | J7: =IFERROR(D7/H7,"") | K7: =IFERROR(D7/E7*1000,"") | L7: =SUMIFS(Raw_Data!$AA$2:$AA$2552,Raw_Data!$A$2:$A$2552,$A7) | M7: =IFERROR(L7/H7,"") | N7: =SUMIFS(Raw_Data!$AL$2:$AL$2552,Raw_Data!$A$2:$A$2552,$A7) | O7: =IFERROR(N7/L7,"") | P7: =IFERROR(D7/N7,"") | Q7: =SUMIFS(Raw_Data!$AO$2:$AO$2552,Raw_Data!$A$2:$A$2552,$A7) | R7: =IFERROR(Q7/N7,"") | S7: =IFERROR(D7/Q7,"") | T7: =SUMIFS(Raw_Data!$AR$2:$AR$2552,Raw_Data!$A$2:$A$2552,$A7) | U7: =SUMIFS(Raw_Data!$AS$2:$AS$2552,Raw_Data!$A$2:$A$2552,$A7) | V7: =N7+T7 | W7: =SUMIFS(Raw_Data!$AU$2:$AU$2552,Raw_Data!$A$2:$A$2552,$A7) | X7: =IFERROR(D7/$D$36,"") | Y7: =IFERROR(N7/$N$36,"") | Z7: =SUM($D$5:D7) | AA7: =SUM($N$5:N7) | AB7: =IFERROR(Z7/AA7,"") | AC7: =IFERROR(Z7/Assumptions!$C$10,"") | AD7: =3/31 | AE7: =IFERROR(AC7/AD7,"") | AF7: =SUMIFS(Raw_Data!$R$2:$R$2552,Raw_Data!$A$2:$A$2552,$A7,Raw_Data!$D$2:$D$2552,"Meta (FB/IG)") | AG7: =SUMIFS(Raw_Data!$AL$2:$AL$2552,Raw_Data!$A$2:$A$2552,$A7,Raw_Data!$D$2:$D$2552,"Meta (FB/IG)") | AH7: =IFERROR(AF7/AG7,"") | AI7: =SUMIFS(Raw_Data!$R$2:$R$2552,Raw_Data!$A$2:$A$2552,$A7,Raw_Data!$D$2:$D$2552,"TikTok") | AJ7: =SUMIFS(Raw_Data!$AL$2:$AL$2552,Raw_Data!$A$2:$A$2552,$A7,Raw_Data!$D$2:$D$2552,"TikTok") | AK7: =IFERROR(AI7/AJ7,"") | AL7: =SUMIFS(Raw_Data!$R$2:$R$2552,Raw_Data!$A$2:$A$2552,$A7,Raw_Data!$D$2:$D$2552,"X") | AM7: =SUMIFS(Raw_Data!$AL$2:$AL$2552,Raw_Data!$A$2:$A$2552,$A7,Raw_Data!$D$2:$D$2552,"X") | AN7: =IFERROR(AL7/AM7,"") | AO7: =SUMIFS(Raw_Data!$R$2:$R$2552,Raw_Data!$A$2:$A$2552,$A7,Raw_Data!$D$2:$D$2552,"Programmatic") | AP7: =SUMIFS(Raw_Data!$AL$2:$AL$2552,Raw_Data!$A$2:$A$2552,$A7,Raw_Data!$D$2:$D$2552,"Programmatic") | AQ7: =IFERROR(AO7/AP7,"")
A8: 46238 | B8: Tue | C8: Wk 32 | D8: =SUMIFS(Raw_Data!$R$2:$R$2552,Raw_Data!$A$2:$A$2552,$A8) | E8: =SUMIFS(Raw_Data!$S$2:$S$2552,Raw_Data!$A$2:$A$2552,$A8) | F8: =SUMIFS(Raw_Data!$T$2:$T$2552,Raw_Data!$A$2:$A$2552,$A8) | G8: =IFERROR(E8/F8,"") | H8: =SUMIFS(Raw_Data!$W$2:$W$2552,Raw_Data!$A$2:$A$2552,$A8) | I8: =IFERROR(H8/E8,"") | J8: =IFERROR(D8/H8,"") | K8: =IFERROR(D8/E8*1000,"") | L8: =SUMIFS(Raw_Data!$AA$2:$AA$2552,Raw_Data!$A$2:$A$2552,$A8) | M8: =IFERROR(L8/H8,"") | N8: =SUMIFS(Raw_Data!$AL$2:$AL$2552,Raw_Data!$A$2:$A$2552,$A8) | O8: =IFERROR(N8/L8,"") | P8: =IFERROR(D8/N8,"") | Q8: =SUMIFS(Raw_Data!$AO$2:$AO$2552,Raw_Data!$A$2:$A$2552,$A8) | R8: =IFERROR(Q8/N8,"") | S8: =IFERROR(D8/Q8,"") | T8: =SUMIFS(Raw_Data!$AR$2:$AR$2552,Raw_Data!$A$2:$A$2552,$A8) | U8: =SUMIFS(Raw_Data!$AS$2:$AS$2552,Raw_Data!$A$2:$A$2552,$A8) | V8: =N8+T8 | W8: =SUMIFS(Raw_Data!$AU$2:$AU$2552,Raw_Data!$A$2:$A$2552,$A8) | X8: =IFERROR(D8/$D$36,"") | Y8: =IFERROR(N8/$N$36,"") | Z8: =SUM($D$5:D8) | AA8: =SUM($N$5:N8) | AB8: =IFERROR(Z8/AA8,"") | AC8: =IFERROR(Z8/Assumptions!$C$10,"") | AD8: =4/31 | AE8: =IFERROR(AC8/AD8,"") | AF8: =SUMIFS(Raw_Data!$R$2:$R$2552,Raw_Data!$A$2:$A$2552,$A8,Raw_Data!$D$2:$D$2552,"Meta (FB/IG)") | AG8: =SUMIFS(Raw_Data!$AL$2:$AL$2552,Raw_Data!$A$2:$A$2552,$A8,Raw_Data!$D$2:$D$2552,"Meta (FB/IG)") | AH8: =IFERROR(AF8/AG8,"") | AI8: =SUMIFS(Raw_Data!$R$2:$R$2552,Raw_Data!$A$2:$A$2552,$A8,Raw_Data!$D$2:$D$2552,"TikTok") | AJ8: =SUMIFS(Raw_Data!$AL$2:$AL$2552,Raw_Data!$A$2:$A$2552,$A8,Raw_Data!$D$2:$D$2552,"TikTok") | AK8: =IFERROR(AI8/AJ8,"") | AL8: =SUMIFS(Raw_Data!$R$2:$R$2552,Raw_Data!$A$2:$A$2552,$A8,Raw_Data!$D$2:$D$2552,"X") | AM8: =SUMIFS(Raw_Data!$AL$2:$AL$2552,Raw_Data!$A$2:$A$2552,$A8,Raw_Data!$D$2:$D$2552,"X") | AN8: =IFERROR(AL8/AM8,"") | AO8: =SUMIFS(Raw_Data!$R$2:$R$2552,Raw_Data!$A$2:$A$2552,$A8,Raw_Data!$D$2:$D$2552,"Programmatic") | AP8: =SUMIFS(Raw_Data!$AL$2:$AL$2552,Raw_Data!$A$2:$A$2552,$A8,Raw_Data!$D$2:$D$2552,"Programmatic") | AQ8: =IFERROR(AO8/AP8,"")
A9: 46239 | B9: Wed | C9: Wk 32 | D9: =SUMIFS(Raw_Data!$R$2:$R$2552,Raw_Data!$A$2:$A$2552,$A9) | E9: =SUMIFS(Raw_Data!$S$2:$S$2552,Raw_Data!$A$2:$A$2552,$A9) | F9: =SUMIFS(Raw_Data!$T$2:$T$2552,Raw_Data!$A$2:$A$2552,$A9) | G9: =IFERROR(E9/F9,"") | H9: =SUMIFS(Raw_Data!$W$2:$W$2552,Raw_Data!$A$2:$A$2552,$A9) | I9: =IFERROR(H9/E9,"") | J9: =IFERROR(D9/H9,"") | K9: =IFERROR(D9/E9*1000,"") | L9: =SUMIFS(Raw_Data!$AA$2:$AA$2552,Raw_Data!$A$2:$A$2552,$A9) | M9: =IFERROR(L9/H9,"") | N9: =SUMIFS(Raw_Data!$AL$2:$AL$2552,Raw_Data!$A$2:$A$2552,$A9) | O9: =IFERROR(N9/L9,"") | P9: =IFERROR(D9/N9,"") | Q9: =SUMIFS(Raw_Data!$AO$2:$AO$2552,Raw_Data!$A$2:$A$2552,$A9) | R9: =IFERROR(Q9/N9,"") | S9: =IFERROR(D9/Q9,"") | T9: =SUMIFS(Raw_Data!$AR$2:$AR$2552,Raw_Data!$A$2:$A$2552,$A9) | U9: =SUMIFS(Raw_Data!$AS$2:$AS$2552,Raw_Data!$A$2:$A$2552,$A9) | V9: =N9+T9 | W9: =SUMIFS(Raw_Data!$AU$2:$AU$2552,Raw_Data!$A$2:$A$2552,$A9) | X9: =IFERROR(D9/$D$36,"") | Y9: =IFERROR(N9/$N$36,"") | Z9: =SUM($D$5:D9) | AA9: =SUM($N$5:N9) | AB9: =IFERROR(Z9/AA9,"") | AC9: =IFERROR(Z9/Assumptions!$C$10,"") | AD9: =5/31 | AE9: =IFERROR(AC9/AD9,"") | AF9: =SUMIFS(Raw_Data!$R$2:$R$2552,Raw_Data!$A$2:$A$2552,$A9,Raw_Data!$D$2:$D$2552,"Meta (FB/IG)") | AG9: =SUMIFS(Raw_Data!$AL$2:$AL$2552,Raw_Data!$A$2:$A$2552,$A9,Raw_Data!$D$2:$D$2552,"Meta (FB/IG)") | AH9: =IFERROR(AF9/AG9,"") | AI9: =SUMIFS(Raw_Data!$R$2:$R$2552,Raw_Data!$A$2:$A$2552,$A9,Raw_Data!$D$2:$D$2552,"TikTok") | AJ9: =SUMIFS(Raw_Data!$AL$2:$AL$2552,Raw_Data!$A$2:$A$2552,$A9,Raw_Data!$D$2:$D$2552,"TikTok") | AK9: =IFERROR(AI9/AJ9,"") | AL9: =SUMIFS(Raw_Data!$R$2:$R$2552,Raw_Data!$A$2:$A$2552,$A9,Raw_Data!$D$2:$D$2552,"X") | AM9: =SUMIFS(Raw_Data!$AL$2:$AL$2552,Raw_Data!$A$2:$A$2552,$A9,Raw_Data!$D$2:$D$2552,"X") | AN9: =IFERROR(AL9/AM9,"") | AO9: =SUMIFS(Raw_Data!$R$2:$R$2552,Raw_Data!$A$2:$A$2552,$A9,Raw_Data!$D$2:$D$2552,"Programmatic") | AP9: =SUMIFS(Raw_Data!$AL$2:$AL$2552,Raw_Data!$A$2:$A$2552,$A9,Raw_Data!$D$2:$D$2552,"Programmatic") | AQ9: =IFERROR(AO9/AP9,"")
A10: 46240 | B10: Thu | C10: Wk 32 | D10: =SUMIFS(Raw_Data!$R$2:$R$2552,Raw_Data!$A$2:$A$2552,$A10) | E10: =SUMIFS(Raw_Data!$S$2:$S$2552,Raw_Data!$A$2:$A$2552,$A10) | F10: =SUMIFS(Raw_Data!$T$2:$T$2552,Raw_Data!$A$2:$A$2552,$A10) | G10: =IFERROR(E10/F10,"") | H10: =SUMIFS(Raw_Data!$W$2:$W$2552,Raw_Data!$A$2:$A$2552,$A10) | I10: =IFERROR(H10/E10,"") | J10: =IFERROR(D10/H10,"") | K10: =IFERROR(D10/E10*1000,"") | L10: =SUMIFS(Raw_Data!$AA$2:$AA$2552,Raw_Data!$A$2:$A$2552,$A10) | M10: =IFERROR(L10/H10,"") | N10: =SUMIFS(Raw_Data!$AL$2:$AL$2552,Raw_Data!$A$2:$A$2552,$A10) | O10: =IFERROR(N10/L10,"") | P10: =IFERROR(D10/N10,"") | Q10: =SUMIFS(Raw_Data!$AO$2:$AO$2552,Raw_Data!$A$2:$A$2552,$A10) | R10: =IFERROR(Q10/N10,"") | S10: =IFERROR(D10/Q10,"") | T10: =SUMIFS(Raw_Data!$AR$2:$AR$2552,Raw_Data!$A$2:$A$2552,$A10) | U10: =SUMIFS(Raw_Data!$AS$2:$AS$2552,Raw_Data!$A$2:$A$2552,$A10) | V10: =N10+T10 | W10: =SUMIFS(Raw_Data!$AU$2:$AU$2552,Raw_Data!$A$2:$A$2552,$A10) | X10: =IFERROR(D10/$D$36,"") | Y10: =IFERROR(N10/$N$36,"") | Z10: =SUM($D$5:D10) | AA10: =SUM($N$5:N10) | AB10: =IFERROR(Z10/AA10,"") | AC10: =IFERROR(Z10/Assumptions!$C$10,"") | AD10: =6/31 | AE10: =IFERROR(AC10/AD10,"") | AF10: =SUMIFS(Raw_Data!$R$2:$R$2552,Raw_Data!$A$2:$A$2552,$A10,Raw_Data!$D$2:$D$2552,"Meta (FB/IG)") | AG10: =SUMIFS(Raw_Data!$AL$2:$AL$2552,Raw_Data!$A$2:$A$2552,$A10,Raw_Data!$D$2:$D$2552,"Meta (FB/IG)") | AH10: =IFERROR(AF10/AG10,"") | AI10: =SUMIFS(Raw_Data!$R$2:$R$2552,Raw_Data!$A$2:$A$2552,$A10,Raw_Data!$D$2:$D$2552,"TikTok") | AJ10: =SUMIFS(Raw_Data!$AL$2:$AL$2552,Raw_Data!$A$2:$A$2552,$A10,Raw_Data!$D$2:$D$2552,"TikTok") | AK10: =IFERROR(AI10/AJ10,"") | AL10: =SUMIFS(Raw_Data!$R$2:$R$2552,Raw_Data!$A$2:$A$2552,$A10,Raw_Data!$D$2:$D$2552,"X") | AM10: =SUMIFS(Raw_Data!$AL$2:$AL$2552,Raw_Data!$A$2:$A$2552,$A10,Raw_Data!$D$2:$D$2552,"X") | AN10: =IFERROR(AL10/AM10,"") | AO10: =SUMIFS(Raw_Data!$R$2:$R$2552,Raw_Data!$A$2:$A$2552,$A10,Raw_Data!$D$2:$D$2552,"Programmatic") | AP10: =SUMIFS(Raw_Data!$AL$2:$AL$2552,Raw_Data!$A$2:$A$2552,$A10,Raw_Data!$D$2:$D$2552,"Programmatic") | AQ10: =IFERROR(AO10/AP10,"")
A11: 46241 | B11: Fri | C11: Wk 32 | D11: =SUMIFS(Raw_Data!$R$2:$R$2552,Raw_Data!$A$2:$A$2552,$A11) | E11: =SUMIFS(Raw_Data!$S$2:$S$2552,Raw_Data!$A$2:$A$2552,$A11) | F11: =SUMIFS(Raw_Data!$T$2:$T$2552,Raw_Data!$A$2:$A$2552,$A11) | G11: =IFERROR(E11/F11,"") | H11: =SUMIFS(Raw_Data!$W$2:$W$2552,Raw_Data!$A$2:$A$2552,$A11) | I11: =IFERROR(H11/E11,"") | J11: =IFERROR(D11/H11,"") | K11: =IFERROR(D11/E11*1000,"") | L11: =SUMIFS(Raw_Data!$AA$2:$AA$2552,Raw_Data!$A$2:$A$2552,$A11) | M11: =IFERROR(L11/H11,"") | N11: =SUMIFS(Raw_Data!$AL$2:$AL$2552,Raw_Data!$A$2:$A$2552,$A11) | O11: =IFERROR(N11/L11,"") | P11: =IFERROR(D11/N11,"") | Q11: =SUMIFS(Raw_Data!$AO$2:$AO$2552,Raw_Data!$A$2:$A$2552,$A11) | R11: =IFERROR(Q11/N11,"") | S11: =IFERROR(D11/Q11,"") | T11: =SUMIFS(Raw_Data!$AR$2:$AR$2552,Raw_Data!$A$2:$A$2552,$A11) | U11: =SUMIFS(Raw_Data!$AS$2:$AS$2552,Raw_Data!$A$2:$A$2552,$A11) | V11: =N11+T11 | W11: =SUMIFS(Raw_Data!$AU$2:$AU$2552,Raw_Data!$A$2:$A$2552,$A11) | X11: =IFERROR(D11/$D$36,"") | Y11: =IFERROR(N11/$N$36,"") | Z11: =SUM($D$5:D11) | AA11: =SUM($N$5:N11) | AB11: =IFERROR(Z11/AA11,"") | AC11: =IFERROR(Z11/Assumptions!$C$10,"") | AD11: =7/31 | AE11: =IFERROR(AC11/AD11,"") | AF11: =SUMIFS(Raw_Data!$R$2:$R$2552,Raw_Data!$A$2:$A$2552,$A11,Raw_Data!$D$2:$D$2552,"Meta (FB/IG)") | AG11: =SUMIFS(Raw_Data!$AL$2:$AL$2552,Raw_Data!$A$2:$A$2552,$A11,Raw_Data!$D$2:$D$2552,"Meta (FB/IG)") | AH11: =IFERROR(AF11/AG11,"") | AI11: =SUMIFS(Raw_Data!$R$2:$R$2552,Raw_Data!$A$2:$A$2552,$A11,Raw_Data!$D$2:$D$2552,"TikTok") | AJ11: =SUMIFS(Raw_Data!$AL$2:$AL$2552,Raw_Data!$A$2:$A$2552,$A11,Raw_Data!$D$2:$D$2552,"TikTok") | AK11: =IFERROR(AI11/AJ11,"") | AL11: =SUMIFS(Raw_Data!$R$2:$R$2552,Raw_Data!$A$2:$A$2552,$A11,Raw_Data!$D$2:$D$2552,"X") | AM11: =SUMIFS(Raw_Data!$AL$2:$AL$2552,Raw_Data!$A$2:$A$2552,$A11,Raw_Data!$D$2:$D$2552,"X") | AN11: =IFERROR(AL11/AM11,"") | AO11: =SUMIFS(Raw_Data!$R$2:$R$2552,Raw_Data!$A$2:$A$2552,$A11,Raw_Data!$D$2:$D$2552,"Programmatic") | AP11: =SUMIFS(Raw_Data!$AL$2:$AL$2552,Raw_Data!$A$2:$A$2552,$A11,Raw_Data!$D$2:$D$2552,"Programmatic") | AQ11: =IFERROR(AO11/AP11,"")
A12: 46242 | B12: Sat | C12: Wk 32 | D12: =SUMIFS(Raw_Data!$R$2:$R$2552,Raw_Data!$A$2:$A$2552,$A12) | E12: =SUMIFS(Raw_Data!$S$2:$S$2552,Raw_Data!$A$2:$A$2552,$A12) | F12: =SUMIFS(Raw_Data!$T$2:$T$2552,Raw_Data!$A$2:$A$2552,$A12) | G12: =IFERROR(E12/F12,"") | H12: =SUMIFS(Raw_Data!$W$2:$W$2552,Raw_Data!$A$2:$A$2552,$A12) | I12: =IFERROR(H12/E12,"") | J12: =IFERROR(D12/H12,"") | K12: =IFERROR(D12/E12*1000,"") | L12: =SUMIFS(Raw_Data!$AA$2:$AA$2552,Raw_Data!$A$2:$A$2552,$A12) | M12: =IFERROR(L12/H12,"") | N12: =SUMIFS(Raw_Data!$AL$2:$AL$2552,Raw_Data!$A$2:$A$2552,$A12) | O12: =IFERROR(N12/L12,"") | P12: =IFERROR(D12/N12,"") | Q12: =SUMIFS(Raw_Data!$AO$2:$AO$2552,Raw_Data!$A$2:$A$2552,$A12) | R12: =IFERROR(Q12/N12,"") | S12: =IFERROR(D12/Q12,"") | T12: =SUMIFS(Raw_Data!$AR$2:$AR$2552,Raw_Data!$A$2:$A$2552,$A12) | U12: =SUMIFS(Raw_Data!$AS$2:$AS$2552,Raw_Data!$A$2:$A$2552,$A12) | V12: =N12+T12 | W12: =SUMIFS(Raw_Data!$AU$2:$AU$2552,Raw_Data!$A$2:$A$2552,$A12) | X12: =IFERROR(D12/$D$36,"") | Y12: =IFERROR(N12/$N$36,"") | Z12: =SUM($D$5:D12) | AA12: =SUM($N$5:N12) | AB12: =IFERROR(Z12/AA12,"") | AC12: =IFERROR(Z12/Assumptions!$C$10,"") | AD12: =8/31 | AE12: =IFERROR(AC12/AD12,"") | AF12: =SUMIFS(Raw_Data!$R$2:$R$2552,Raw_Data!$A$2:$A$2552,$A12,Raw_Data!$D$2:$D$2552,"Meta (FB/IG)") | AG12: =SUMIFS(Raw_Data!$AL$2:$AL$2552,Raw_Data!$A$2:$A$2552,$A12,Raw_Data!$D$2:$D$2552,"Meta (FB/IG)") | AH12: =IFERROR(AF12/AG12,"") | AI12: =SUMIFS(Raw_Data!$R$2:$R$2552,Raw_Data!$A$2:$A$2552,$A12,Raw_Data!$D$2:$D$2552,"TikTok") | AJ12: =SUMIFS(Raw_Data!$AL$2:$AL$2552,Raw_Data!$A$2:$A$2552,$A12,Raw_Data!$D$2:$D$2552,"TikTok") | AK12: =IFERROR(AI12/AJ12,"") | AL12: =SUMIFS(Raw_Data!$R$2:$R$2552,Raw_Data!$A$2:$A$2552,$A12,Raw_Data!$D$2:$D$2552,"X") | AM12: =SUMIFS(Raw_Data!$AL$2:$AL$2552,Raw_Data!$A$2:$A$2552,$A12,Raw_Data!$D$2:$D$2552,"X") | AN12: =IFERROR(AL12/AM12,"") | AO12: =SUMIFS(Raw_Data!$R$2:$R$2552,Raw_Data!$A$2:$A$2552,$A12,Raw_Data!$D$2:$D$2552,"Programmatic") | AP12: =SUMIFS(Raw_Data!$AL$2:$AL$2552,Raw_Data!$A$2:$A$2552,$A12,Raw_Data!$D$2:$D$2552,"Programmatic") | AQ12: =IFERROR(AO12/AP12,"")
A13: 46243 | B13: Sun | C13: Wk 32 | D13: =SUMIFS(Raw_Data!$R$2:$R$2552,Raw_Data!$A$2:$A$2552,$A13) | E13: =SUMIFS(Raw_Data!$S$2:$S$2552,Raw_Data!$A$2:$A$2552,$A13) | F13: =SUMIFS(Raw_Data!$T$2:$T$2552,Raw_Data!$A$2:$A$2552,$A13) | G13: =IFERROR(E13/F13,"") | H13: =SUMIFS(Raw_Data!$W$2:$W$2552,Raw_Data!$A$2:$A$2552,$A13) | I13: =IFERROR(H13/E13,"") | J13: =IFERROR(D13/H13,"") | K13: =IFERROR(D13/E13*1000,"") | L13: =SUMIFS(Raw_Data!$AA$2:$AA$2552,Raw_Data!$A$2:$A$2552,$A13) | M13: =IFERROR(L13/H13,"") | N13: =SUMIFS(Raw_Data!$AL$2:$AL$2552,Raw_Data!$A$2:$A$2552,$A13) | O13: =IFERROR(N13/L13,"") | P13: =IFERROR(D13/N13,"") | Q13: =SUMIFS(Raw_Data!$AO$2:$AO$2552,Raw_Data!$A$2:$A$2552,$A13) | R13: =IFERROR(Q13/N13,"") | S13: =IFERROR(D13/Q13,"") | T13: =SUMIFS(Raw_Data!$AR$2:$AR$2552,Raw_Data!$A$2:$A$2552,$A13) | U13: =SUMIFS(Raw_Data!$AS$2:$AS$2552,Raw_Data!$A$2:$A$2552,$A13) | V13: =N13+T13 | W13: =SUMIFS(Raw_Data!$AU$2:$AU$2552,Raw_Data!$A$2:$A$2552,$A13) | X13: =IFERROR(D13/$D$36,"") | Y13: =IFERROR(N13/$N$36,"") | Z13: =SUM($D$5:D13) | AA13: =SUM($N$5:N13) | AB13: =IFERROR(Z13/AA13,"") | AC13: =IFERROR(Z13/Assumptions!$C$10,"") | AD13: =9/31 | AE13: =IFERROR(AC13/AD13,"") | AF13: =SUMIFS(Raw_Data!$R$2:$R$2552,Raw_Data!$A$2:$A$2552,$A13,Raw_Data!$D$2:$D$2552,"Meta (FB/IG)") | AG13: =SUMIFS(Raw_Data!$AL$2:$AL$2552,Raw_Data!$A$2:$A$2552,$A13,Raw_Data!$D$2:$D$2552,"Meta (FB/IG)") | AH13: =IFERROR(AF13/AG13,"") | AI13: =SUMIFS(Raw_Data!$R$2:$R$2552,Raw_Data!$A$2:$A$2552,$A13,Raw_Data!$D$2:$D$2552,"TikTok") | AJ13: =SUMIFS(Raw_Data!$AL$2:$AL$2552,Raw_Data!$A$2:$A$2552,$A13,Raw_Data!$D$2:$D$2552,"TikTok") | AK13: =IFERROR(AI13/AJ13,"") | AL13: =SUMIFS(Raw_Data!$R$2:$R$2552,Raw_Data!$A$2:$A$2552,$A13,Raw_Data!$D$2:$D$2552,"X") | AM13: =SUMIFS(Raw_Data!$AL$2:$AL$2552,Raw_Data!$A$2:$A$2552,$A13,Raw_Data!$D$2:$D$2552,"X") | AN13: =IFERROR(AL13/AM13,"") | AO13: =SUMIFS(Raw_Data!$R$2:$R$2552,Raw_Data!$A$2:$A$2552,$A13,Raw_Data!$D$2:$D$2552,"Programmatic") | AP13: =SUMIFS(Raw_Data!$AL$2:$AL$2552,Raw_Data!$A$2:$A$2552,$A13,Raw_Data!$D$2:$D$2552,"Programmatic") | AQ13: =IFERROR(AO13/AP13,"")
A14: 46244 | B14: Mon | C14: Wk 33 | D14: =SUMIFS(Raw_Data!$R$2:$R$2552,Raw_Data!$A$2:$A$2552,$A14) | E14: =SUMIFS(Raw_Data!$S$2:$S$2552,Raw_Data!$A$2:$A$2552,$A14) | F14: =SUMIFS(Raw_Data!$T$2:$T$2552,Raw_Data!$A$2:$A$2552,$A14) | G14: =IFERROR(E14/F14,"") | H14: =SUMIFS(Raw_Data!$W$2:$W$2552,Raw_Data!$A$2:$A$2552,$A14) | I14: =IFERROR(H14/E14,"") | J14: =IFERROR(D14/H14,"") | K14: =IFERROR(D14/E14*1000,"") | L14: =SUMIFS(Raw_Data!$AA$2:$AA$2552,Raw_Data!$A$2:$A$2552,$A14) | M14: =IFERROR(L14/H14,"") | N14: =SUMIFS(Raw_Data!$AL$2:$AL$2552,Raw_Data!$A$2:$A$2552,$A14) | O14: =IFERROR(N14/L14,"") | P14: =IFERROR(D14/N14,"") | Q14: =SUMIFS(Raw_Data!$AO$2:$AO$2552,Raw_Data!$A$2:$A$2552,$A14) | R14: =IFERROR(Q14/N14,"") | S14: =IFERROR(D14/Q14,"") | T14: =SUMIFS(Raw_Data!$AR$2:$AR$2552,Raw_Data!$A$2:$A$2552,$A14) | U14: =SUMIFS(Raw_Data!$AS$2:$AS$2552,Raw_Data!$A$2:$A$2552,$A14) | V14: =N14+T14 | W14: =SUMIFS(Raw_Data!$AU$2:$AU$2552,Raw_Data!$A$2:$A$2552,$A14) | X14: =IFERROR(D14/$D$36,"") | Y14: =IFERROR(N14/$N$36,"") | Z14: =SUM($D$5:D14) | AA14: =SUM($N$5:N14) | AB14: =IFERROR(Z14/AA14,"") | AC14: =IFERROR(Z14/Assumptions!$C$10,"") | AD14: =10/31 | AE14: =IFERROR(AC14/AD14,"") | AF14: =SUMIFS(Raw_Data!$R$2:$R$2552,Raw_Data!$A$2:$A$2552,$A14,Raw_Data!$D$2:$D$2552,"Meta (FB/IG)") | AG14: =SUMIFS(Raw_Data!$AL$2:$AL$2552,Raw_Data!$A$2:$A$2552,$A14,Raw_Data!$D$2:$D$2552,"Meta (FB/IG)") | AH14: =IFERROR(AF14/AG14,"") | AI14: =SUMIFS(Raw_Data!$R$2:$R$2552,Raw_Data!$A$2:$A$2552,$A14,Raw_Data!$D$2:$D$2552,"TikTok") | AJ14: =SUMIFS(Raw_Data!$AL$2:$AL$2552,Raw_Data!$A$2:$A$2552,$A14,Raw_Data!$D$2:$D$2552,"TikTok") | AK14: =IFERROR(AI14/AJ14,"") | AL14: =SUMIFS(Raw_Data!$R$2:$R$2552,Raw_Data!$A$2:$A$2552,$A14,Raw_Data!$D$2:$D$2552,"X") | AM14: =SUMIFS(Raw_Data!$AL$2:$AL$2552,Raw_Data!$A$2:$A$2552,$A14,Raw_Data!$D$2:$D$2552,"X") | AN14: =IFERROR(AL14/AM14,"") | AO14: =SUMIFS(Raw_Data!$R$2:$R$2552,Raw_Data!$A$2:$A$2552,$A14,Raw_Data!$D$2:$D$2552,"Programmatic") | AP14: =SUMIFS(Raw_Data!$AL$2:$AL$2552,Raw_Data!$A$2:$A$2552,$A14,Raw_Data!$D$2:$D$2552,"Programmatic") | AQ14: =IFERROR(AO14/AP14,"")
A15: 46245 | B15: Tue | C15: Wk 33 | D15: =SUMIFS(Raw_Data!$R$2:$R$2552,Raw_Data!$A$2:$A$2552,$A15) | E15: =SUMIFS(Raw_Data!$S$2:$S$2552,Raw_Data!$A$2:$A$2552,$A15) | F15: =SUMIFS(Raw_Data!$T$2:$T$2552,Raw_Data!$A$2:$A$2552,$A15) | G15: =IFERROR(E15/F15,"") | H15: =SUMIFS(Raw_Data!$W$2:$W$2552,Raw_Data!$A$2:$A$2552,$A15) | I15: =IFERROR(H15/E15,"") | J15: =IFERROR(D15/H15,"") | K15: =IFERROR(D15/E15*1000,"") | L15: =SUMIFS(Raw_Data!$AA$2:$AA$2552,Raw_Data!$A$2:$A$2552,$A15) | M15: =IFERROR(L15/H15,"") | N15: =SUMIFS(Raw_Data!$AL$2:$AL$2552,Raw_Data!$A$2:$A$2552,$A15) | O15: =IFERROR(N15/L15,"") | P15: =IFERROR(D15/N15,"") | Q15: =SUMIFS(Raw_Data!$AO$2:$AO$2552,Raw_Data!$A$2:$A$2552,$A15) | R15: =IFERROR(Q15/N15,"") | S15: =IFERROR(D15/Q15,"") | T15: =SUMIFS(Raw_Data!$AR$2:$AR$2552,Raw_Data!$A$2:$A$2552,$A15) | U15: =SUMIFS(Raw_Data!$AS$2:$AS$2552,Raw_Data!$A$2:$A$2552,$A15) | V15: =N15+T15 | W15: =SUMIFS(Raw_Data!$AU$2:$AU$2552,Raw_Data!$A$2:$A$2552,$A15) | X15: =IFERROR(D15/$D$36,"") | Y15: =IFERROR(N15/$N$36,"") | Z15: =SUM($D$5:D15) | AA15: =SUM($N$5:N15) | AB15: =IFERROR(Z15/AA15,"") | AC15: =IFERROR(Z15/Assumptions!$C$10,"") | AD15: =11/31 | AE15: =IFERROR(AC15/AD15,"") | AF15: =SUMIFS(Raw_Data!$R$2:$R$2552,Raw_Data!$A$2:$A$2552,$A15,Raw_Data!$D$2:$D$2552,"Meta (FB/IG)") | AG15: =SUMIFS(Raw_Data!$AL$2:$AL$2552,Raw_Data!$A$2:$A$2552,$A15,Raw_Data!$D$2:$D$2552,"Meta (FB/IG)") | AH15: =IFERROR(AF15/AG15,"") | AI15: =SUMIFS(Raw_Data!$R$2:$R$2552,Raw_Data!$A$2:$A$2552,$A15,Raw_Data!$D$2:$D$2552,"TikTok") | AJ15: =SUMIFS(Raw_Data!$AL$2:$AL$2552,Raw_Data!$A$2:$A$2552,$A15,Raw_Data!$D$2:$D$2552,"TikTok") | AK15: =IFERROR(AI15/AJ15,"") | AL15: =SUMIFS(Raw_Data!$R$2:$R$2552,Raw_Data!$A$2:$A$2552,$A15,Raw_Data!$D$2:$D$2552,"X") | AM15: =SUMIFS(Raw_Data!$AL$2:$AL$2552,Raw_Data!$A$2:$A$2552,$A15,Raw_Data!$D$2:$D$2552,"X") | AN15: =IFERROR(AL15/AM15,"") | AO15: =SUMIFS(Raw_Data!$R$2:$R$2552,Raw_Data!$A$2:$A$2552,$A15,Raw_Data!$D$2:$D$2552,"Programmatic") | AP15: =SUMIFS(Raw_Data!$AL$2:$AL$2552,Raw_Data!$A$2:$A$2552,$A15,Raw_Data!$D$2:$D$2552,"Programmatic") | AQ15: =IFERROR(AO15/AP15,"")
A16: 46246 | B16: Wed | C16: Wk 33 | D16: =SUMIFS(Raw_Data!$R$2:$R$2552,Raw_Data!$A$2:$A$2552,$A16) | E16: =SUMIFS(Raw_Data!$S$2:$S$2552,Raw_Data!$A$2:$A$2552,$A16) | F16: =SUMIFS(Raw_Data!$T$2:$T$2552,Raw_Data!$A$2:$A$2552,$A16) | G16: =IFERROR(E16/F16,"") | H16: =SUMIFS(Raw_Data!$W$2:$W$2552,Raw_Data!$A$2:$A$2552,$A16) | I16: =IFERROR(H16/E16,"") | J16: =IFERROR(D16/H16,"") | K16: =IFERROR(D16/E16*1000,"") | L16: =SUMIFS(Raw_Data!$AA$2:$AA$2552,Raw_Data!$A$2:$A$2552,$A16) | M16: =IFERROR(L16/H16,"") | N16: =SUMIFS(Raw_Data!$AL$2:$AL$2552,Raw_Data!$A$2:$A$2552,$A16) | O16: =IFERROR(N16/L16,"") | P16: =IFERROR(D16/N16,"") | Q16: =SUMIFS(Raw_Data!$AO$2:$AO$2552,Raw_Data!$A$2:$A$2552,$A16) | R16: =IFERROR(Q16/N16,"") | S16: =IFERROR(D16/Q16,"") | T16: =SUMIFS(Raw_Data!$AR$2:$AR$2552,Raw_Data!$A$2:$A$2552,$A16) | U16: =SUMIFS(Raw_Data!$AS$2:$AS$2552,Raw_Data!$A$2:$A$2552,$A16) | V16: =N16+T16 | W16: =SUMIFS(Raw_Data!$AU$2:$AU$2552,Raw_Data!$A$2:$A$2552,$A16) | X16: =IFERROR(D16/$D$36,"") | Y16: =IFERROR(N16/$N$36,"") | Z16: =SUM($D$5:D16) | AA16: =SUM($N$5:N16) | AB16: =IFERROR(Z16/AA16,"") | AC16: =IFERROR(Z16/Assumptions!$C$10,"") | AD16: =12/31 | AE16: =IFERROR(AC16/AD16,"") | AF16: =SUMIFS(Raw_Data!$R$2:$R$2552,Raw_Data!$A$2:$A$2552,$A16,Raw_Data!$D$2:$D$2552,"Meta (FB/IG)") | AG16: =SUMIFS(Raw_Data!$AL$2:$AL$2552,Raw_Data!$A$2:$A$2552,$A16,Raw_Data!$D$2:$D$2552,"Meta (FB/IG)") | AH16: =IFERROR(AF16/AG16,"") | AI16: =SUMIFS(Raw_Data!$R$2:$R$2552,Raw_Data!$A$2:$A$2552,$A16,Raw_Data!$D$2:$D$2552,"TikTok") | AJ16: =SUMIFS(Raw_Data!$AL$2:$AL$2552,Raw_Data!$A$2:$A$2552,$A16,Raw_Data!$D$2:$D$2552,"TikTok") | AK16: =IFERROR(AI16/AJ16,"") | AL16: =SUMIFS(Raw_Data!$R$2:$R$2552,Raw_Data!$A$2:$A$2552,$A16,Raw_Data!$D$2:$D$2552,"X") | AM16: =SUMIFS(Raw_Data!$AL$2:$AL$2552,Raw_Data!$A$2:$A$2552,$A16,Raw_Data!$D$2:$D$2552,"X") | AN16: =IFERROR(AL16/AM16,"") | AO16: =SUMIFS(Raw_Data!$R$2:$R$2552,Raw_Data!$A$2:$A$2552,$A16,Raw_Data!$D$2:$D$2552,"Programmatic") | AP16: =SUMIFS(Raw_Data!$AL$2:$AL$2552,Raw_Data!$A$2:$A$2552,$A16,Raw_Data!$D$2:$D$2552,"Programmatic") | AQ16: =IFERROR(AO16/AP16,"")
A17: 46247 | B17: Thu | C17: Wk 33 | D17: =SUMIFS(Raw_Data!$R$2:$R$2552,Raw_Data!$A$2:$A$2552,$A17) | E17: =SUMIFS(Raw_Data!$S$2:$S$2552,Raw_Data!$A$2:$A$2552,$A17) | F17: =SUMIFS(Raw_Data!$T$2:$T$2552,Raw_Data!$A$2:$A$2552,$A17) | G17: =IFERROR(E17/F17,"") | H17: =SUMIFS(Raw_Data!$W$2:$W$2552,Raw_Data!$A$2:$A$2552,$A17) | I17: =IFERROR(H17/E17,"") | J17: =IFERROR(D17/H17,"") | K17: =IFERROR(D17/E17*1000,"") | L17: =SUMIFS(Raw_Data!$AA$2:$AA$2552,Raw_Data!$A$2:$A$2552,$A17) | M17: =IFERROR(L17/H17,"") | N17: =SUMIFS(Raw_Data!$AL$2:$AL$2552,Raw_Data!$A$2:$A$2552,$A17) | O17: =IFERROR(N17/L17,"") | P17: =IFERROR(D17/N17,"") | Q17: =SUMIFS(Raw_Data!$AO$2:$AO$2552,Raw_Data!$A$2:$A$2552,$A17) | R17: =IFERROR(Q17/N17,"") | S17: =IFERROR(D17/Q17,"") | T17: =SUMIFS(Raw_Data!$AR$2:$AR$2552,Raw_Data!$A$2:$A$2552,$A17) | U17: =SUMIFS(Raw_Data!$AS$2:$AS$2552,Raw_Data!$A$2:$A$2552,$A17) | V17: =N17+T17 | W17: =SUMIFS(Raw_Data!$AU$2:$AU$2552,Raw_Data!$A$2:$A$2552,$A17) | X17: =IFERROR(D17/$D$36,"") | Y17: =IFERROR(N17/$N$36,"") | Z17: =SUM($D$5:D17) | AA17: =SUM($N$5:N17) | AB17: =IFERROR(Z17/AA17,"") | AC17: =IFERROR(Z17/Assumptions!$C$10,"") | AD17: =13/31 | AE17: =IFERROR(AC17/AD17,"") | AF17: =SUMIFS(Raw_Data!$R$2:$R$2552,Raw_Data!$A$2:$A$2552,$A17,Raw_Data!$D$2:$D$2552,"Meta (FB/IG)") | AG17: =SUMIFS(Raw_Data!$AL$2:$AL$2552,Raw_Data!$A$2:$A$2552,$A17,Raw_Data!$D$2:$D$2552,"Meta (FB/IG)") | AH17: =IFERROR(AF17/AG17,"") | AI17: =SUMIFS(Raw_Data!$R$2:$R$2552,Raw_Data!$A$2:$A$2552,$A17,Raw_Data!$D$2:$D$2552,"TikTok") | AJ17: =SUMIFS(Raw_Data!$AL$2:$AL$2552,Raw_Data!$A$2:$A$2552,$A17,Raw_Data!$D$2:$D$2552,"TikTok") | AK17: =IFERROR(AI17/AJ17,"") | AL17: =SUMIFS(Raw_Data!$R$2:$R$2552,Raw_Data!$A$2:$A$2552,$A17,Raw_Data!$D$2:$D$2552,"X") | AM17: =SUMIFS(Raw_Data!$AL$2:$AL$2552,Raw_Data!$A$2:$A$2552,$A17,Raw_Data!$D$2:$D$2552,"X") | AN17: =IFERROR(AL17/AM17,"") | AO17: =SUMIFS(Raw_Data!$R$2:$R$2552,Raw_Data!$A$2:$A$2552,$A17,Raw_Data!$D$2:$D$2552,"Programmatic") | AP17: =SUMIFS(Raw_Data!$AL$2:$AL$2552,Raw_Data!$A$2:$A$2552,$A17,Raw_Data!$D$2:$D$2552,"Programmatic") | AQ17: =IFERROR(AO17/AP17,"")
A18: 46248 | B18: Fri | C18: Wk 33 | D18: =SUMIFS(Raw_Data!$R$2:$R$2552,Raw_Data!$A$2:$A$2552,$A18) | E18: =SUMIFS(Raw_Data!$S$2:$S$2552,Raw_Data!$A$2:$A$2552,$A18) | F18: =SUMIFS(Raw_Data!$T$2:$T$2552,Raw_Data!$A$2:$A$2552,$A18) | G18: =IFERROR(E18/F18,"") | H18: =SUMIFS(Raw_Data!$W$2:$W$2552,Raw_Data!$A$2:$A$2552,$A18) | I18: =IFERROR(H18/E18,"") | J18: =IFERROR(D18/H18,"") | K18: =IFERROR(D18/E18*1000,"") | L18: =SUMIFS(Raw_Data!$AA$2:$AA$2552,Raw_Data!$A$2:$A$2552,$A18) | M18: =IFERROR(L18/H18,"") | N18: =SUMIFS(Raw_Data!$AL$2:$AL$2552,Raw_Data!$A$2:$A$2552,$A18) | O18: =IFERROR(N18/L18,"") | P18: =IFERROR(D18/N18,"") | Q18: =SUMIFS(Raw_Data!$AO$2:$AO$2552,Raw_Data!$A$2:$A$2552,$A18) | R18: =IFERROR(Q18/N18,"") | S18: =IFERROR(D18/Q18,"") | T18: =SUMIFS(Raw_Data!$AR$2:$AR$2552,Raw_Data!$A$2:$A$2552,$A18) | U18: =SUMIFS(Raw_Data!$AS$2:$AS$2552,Raw_Data!$A$2:$A$2552,$A18) | V18: =N18+T18 | W18: =SUMIFS(Raw_Data!$AU$2:$AU$2552,Raw_Data!$A$2:$A$2552,$A18) | X18: =IFERROR(D18/$D$36,"") | Y18: =IFERROR(N18/$N$36,"") | Z18: =SUM($D$5:D18) | AA18: =SUM($N$5:N18) | AB18: =IFERROR(Z18/AA18,"") | AC18: =IFERROR(Z18/Assumptions!$C$10,"") | AD18: =14/31 | AE18: =IFERROR(AC18/AD18,"") | AF18: =SUMIFS(Raw_Data!$R$2:$R$2552,Raw_Data!$A$2:$A$2552,$A18,Raw_Data!$D$2:$D$2552,"Meta (FB/IG)") | AG18: =SUMIFS(Raw_Data!$AL$2:$AL$2552,Raw_Data!$A$2:$A$2552,$A18,Raw_Data!$D$2:$D$2552,"Meta (FB/IG)") | AH18: =IFERROR(AF18/AG18,"") | AI18: =SUMIFS(Raw_Data!$R$2:$R$2552,Raw_Data!$A$2:$A$2552,$A18,Raw_Data!$D$2:$D$2552,"TikTok") | AJ18: =SUMIFS(Raw_Data!$AL$2:$AL$2552,Raw_Data!$A$2:$A$2552,$A18,Raw_Data!$D$2:$D$2552,"TikTok") | AK18: =IFERROR(AI18/AJ18,"") | AL18: =SUMIFS(Raw_Data!$R$2:$R$2552,Raw_Data!$A$2:$A$2552,$A18,Raw_Data!$D$2:$D$2552,"X") | AM18: =SUMIFS(Raw_Data!$AL$2:$AL$2552,Raw_Data!$A$2:$A$2552,$A18,Raw_Data!$D$2:$D$2552,"X") | AN18: =IFERROR(AL18/AM18,"") | AO18: =SUMIFS(Raw_Data!$R$2:$R$2552,Raw_Data!$A$2:$A$2552,$A18,Raw_Data!$D$2:$D$2552,"Programmatic") | AP18: =SUMIFS(Raw_Data!$AL$2:$AL$2552,Raw_Data!$A$2:$A$2552,$A18,Raw_Data!$D$2:$D$2552,"Programmatic") | AQ18: =IFERROR(AO18/AP18,"")
A19: 46249 | B19: Sat | C19: Wk 33 | D19: =SUMIFS(Raw_Data!$R$2:$R$2552,Raw_Data!$A$2:$A$2552,$A19) | E19: =SUMIFS(Raw_Data!$S$2:$S$2552,Raw_Data!$A$2:$A$2552,$A19) | F19: =SUMIFS(Raw_Data!$T$2:$T$2552,Raw_Data!$A$2:$A$2552,$A19) | G19: =IFERROR(E19/F19,"") | H19: =SUMIFS(Raw_Data!$W$2:$W$2552,Raw_Data!$A$2:$A$2552,$A19) | I19: =IFERROR(H19/E19,"") | J19: =IFERROR(D19/H19,"") | K19: =IFERROR(D19/E19*1000,"") | L19: =SUMIFS(Raw_Data!$AA$2:$AA$2552,Raw_Data!$A$2:$A$2552,$A19) | M19: =IFERROR(L19/H19,"") | N19: =SUMIFS(Raw_Data!$AL$2:$AL$2552,Raw_Data!$A$2:$A$2552,$A19) | O19: =IFERROR(N19/L19,"") | P19: =IFERROR(D19/N19,"") | Q19: =SUMIFS(Raw_Data!$AO$2:$AO$2552,Raw_Data!$A$2:$A$2552,$A19) | R19: =IFERROR(Q19/N19,"") | S19: =IFERROR(D19/Q19,"") | T19: =SUMIFS(Raw_Data!$AR$2:$AR$2552,Raw_Data!$A$2:$A$2552,$A19) | U19: =SUMIFS(Raw_Data!$AS$2:$AS$2552,Raw_Data!$A$2:$A$2552,$A19) | V19: =N19+T19 | W19: =SUMIFS(Raw_Data!$AU$2:$AU$2552,Raw_Data!$A$2:$A$2552,$A19) | X19: =IFERROR(D19/$D$36,"") | Y19: =IFERROR(N19/$N$36,"") | Z19: =SUM($D$5:D19) | AA19: =SUM($N$5:N19) | AB19: =IFERROR(Z19/AA19,"") | AC19: =IFERROR(Z19/Assumptions!$C$10,"") | AD19: =15/31 | AE19: =IFERROR(AC19/AD19,"") | AF19: =SUMIFS(Raw_Data!$R$2:$R$2552,Raw_Data!$A$2:$A$2552,$A19,Raw_Data!$D$2:$D$2552,"Meta (FB/IG)") | AG19: =SUMIFS(Raw_Data!$AL$2:$AL$2552,Raw_Data!$A$2:$A$2552,$A19,Raw_Data!$D$2:$D$2552,"Meta (FB/IG)") | AH19: =IFERROR(AF19/AG19,"") | AI19: =SUMIFS(Raw_Data!$R$2:$R$2552,Raw_Data!$A$2:$A$2552,$A19,Raw_Data!$D$2:$D$2552,"TikTok") | AJ19: =SUMIFS(Raw_Data!$AL$2:$AL$2552,Raw_Data!$A$2:$A$2552,$A19,Raw_Data!$D$2:$D$2552,"TikTok") | AK19: =IFERROR(AI19/AJ19,"") | AL19: =SUMIFS(Raw_Data!$R$2:$R$2552,Raw_Data!$A$2:$A$2552,$A19,Raw_Data!$D$2:$D$2552,"X") | AM19: =SUMIFS(Raw_Data!$AL$2:$AL$2552,Raw_Data!$A$2:$A$2552,$A19,Raw_Data!$D$2:$D$2552,"X") | AN19: =IFERROR(AL19/AM19,"") | AO19: =SUMIFS(Raw_Data!$R$2:$R$2552,Raw_Data!$A$2:$A$2552,$A19,Raw_Data!$D$2:$D$2552,"Programmatic") | AP19: =SUMIFS(Raw_Data!$AL$2:$AL$2552,Raw_Data!$A$2:$A$2552,$A19,Raw_Data!$D$2:$D$2552,"Programmatic") | AQ19: =IFERROR(AO19/AP19,"")
A20: 46250 | B20: Sun | C20: Wk 33 | D20: =SUMIFS(Raw_Data!$R$2:$R$2552,Raw_Data!$A$2:$A$2552,$A20) | E20: =SUMIFS(Raw_Data!$S$2:$S$2552,Raw_Data!$A$2:$A$2552,$A20) | F20: =SUMIFS(Raw_Data!$T$2:$T$2552,Raw_Data!$A$2:$A$2552,$A20) | G20: =IFERROR(E20/F20,"") | H20: =SUMIFS(Raw_Data!$W$2:$W$2552,Raw_Data!$A$2:$A$2552,$A20) | I20: =IFERROR(H20/E20,"") | J20: =IFERROR(D20/H20,"") | K20: =IFERROR(D20/E20*1000,"") | L20: =SUMIFS(Raw_Data!$AA$2:$AA$2552,Raw_Data!$A$2:$A$2552,$A20) | M20: =IFERROR(L20/H20,"") | N20: =SUMIFS(Raw_Data!$AL$2:$AL$2552,Raw_Data!$A$2:$A$2552,$A20) | O20: =IFERROR(N20/L20,"") | P20: =IFERROR(D20/N20,"") | Q20: =SUMIFS(Raw_Data!$AO$2:$AO$2552,Raw_Data!$A$2:$A$2552,$A20) | R20: =IFERROR(Q20/N20,"") | S20: =IFERROR(D20/Q20,"") | T20: =SUMIFS(Raw_Data!$AR$2:$AR$2552,Raw_Data!$A$2:$A$2552,$A20) | U20: =SUMIFS(Raw_Data!$AS$2:$AS$2552,Raw_Data!$A$2:$A$2552,$A20) | V20: =N20+T20 | W20: =SUMIFS(Raw_Data!$AU$2:$AU$2552,Raw_Data!$A$2:$A$2552,$A20) | X20: =IFERROR(D20/$D$36,"") | Y20: =IFERROR(N20/$N$36,"") | Z20: =SUM($D$5:D20) | AA20: =SUM($N$5:N20) | AB20: =IFERROR(Z20/AA20,"") | AC20: =IFERROR(Z20/Assumptions!$C$10,"") | AD20: =16/31 | AE20: =IFERROR(AC20/AD20,"") | AF20: =SUMIFS(Raw_Data!$R$2:$R$2552,Raw_Data!$A$2:$A$2552,$A20,Raw_Data!$D$2:$D$2552,"Meta (FB/IG)") | AG20: =SUMIFS(Raw_Data!$AL$2:$AL$2552,Raw_Data!$A$2:$A$2552,$A20,Raw_Data!$D$2:$D$2552,"Meta (FB/IG)") | AH20: =IFERROR(AF20/AG20,"") | AI20: =SUMIFS(Raw_Data!$R$2:$R$2552,Raw_Data!$A$2:$A$2552,$A20,Raw_Data!$D$2:$D$2552,"TikTok") | AJ20: =SUMIFS(Raw_Data!$AL$2:$AL$2552,Raw_Data!$A$2:$A$2552,$A20,Raw_Data!$D$2:$D$2552,"TikTok") | AK20: =IFERROR(AI20/AJ20,"") | AL20: =SUMIFS(Raw_Data!$R$2:$R$2552,Raw_Data!$A$2:$A$2552,$A20,Raw_Data!$D$2:$D$2552,"X") | AM20: =SUMIFS(Raw_Data!$AL$2:$AL$2552,Raw_Data!$A$2:$A$2552,$A20,Raw_Data!$D$2:$D$2552,"X") | AN20: =IFERROR(AL20/AM20,"") | AO20: =SUMIFS(Raw_Data!$R$2:$R$2552,Raw_Data!$A$2:$A$2552,$A20,Raw_Data!$D$2:$D$2552,"Programmatic") | AP20: =SUMIFS(Raw_Data!$AL$2:$AL$2552,Raw_Data!$A$2:$A$2552,$A20,Raw_Data!$D$2:$D$2552,"Programmatic") | AQ20: =IFERROR(AO20/AP20,"")
A21: 46251 | B21: Mon | C21: Wk 34 | D21: =SUMIFS(Raw_Data!$R$2:$R$2552,Raw_Data!$A$2:$A$2552,$A21) | E21: =SUMIFS(Raw_Data!$S$2:$S$2552,Raw_Data!$A$2:$A$2552,$A21) | F21: =SUMIFS(Raw_Data!$T$2:$T$2552,Raw_Data!$A$2:$A$2552,$A21) | G21: =IFERROR(E21/F21,"") | H21: =SUMIFS(Raw_Data!$W$2:$W$2552,Raw_Data!$A$2:$A$2552,$A21) | I21: =IFERROR(H21/E21,"") | J21: =IFERROR(D21/H21,"") | K21: =IFERROR(D21/E21*1000,"") | L21: =SUMIFS(Raw_Data!$AA$2:$AA$2552,Raw_Data!$A$2:$A$2552,$A21) | M21: =IFERROR(L21/H21,"") | N21: =SUMIFS(Raw_Data!$AL$2:$AL$2552,Raw_Data!$A$2:$A$2552,$A21) | O21: =IFERROR(N21/L21,"") | P21: =IFERROR(D21/N21,"") | Q21: =SUMIFS(Raw_Data!$AO$2:$AO$2552,Raw_Data!$A$2:$A$2552,$A21) | R21: =IFERROR(Q21/N21,"") | S21: =IFERROR(D21/Q21,"") | T21: =SUMIFS(Raw_Data!$AR$2:$AR$2552,Raw_Data!$A$2:$A$2552,$A21) | U21: =SUMIFS(Raw_Data!$AS$2:$AS$2552,Raw_Data!$A$2:$A$2552,$A21) | V21: =N21+T21 | W21: =SUMIFS(Raw_Data!$AU$2:$AU$2552,Raw_Data!$A$2:$A$2552,$A21) | X21: =IFERROR(D21/$D$36,"") | Y21: =IFERROR(N21/$N$36,"") | Z21: =SUM($D$5:D21) | AA21: =SUM($N$5:N21) | AB21: =IFERROR(Z21/AA21,"") | AC21: =IFERROR(Z21/Assumptions!$C$10,"") | AD21: =17/31 | AE21: =IFERROR(AC21/AD21,"") | AF21: =SUMIFS(Raw_Data!$R$2:$R$2552,Raw_Data!$A$2:$A$2552,$A21,Raw_Data!$D$2:$D$2552,"Meta (FB/IG)") | AG21: =SUMIFS(Raw_Data!$AL$2:$AL$2552,Raw_Data!$A$2:$A$2552,$A21,Raw_Data!$D$2:$D$2552,"Meta (FB/IG)") | AH21: =IFERROR(AF21/AG21,"") | AI21: =SUMIFS(Raw_Data!$R$2:$R$2552,Raw_Data!$A$2:$A$2552,$A21,Raw_Data!$D$2:$D$2552,"TikTok") | AJ21: =SUMIFS(Raw_Data!$AL$2:$AL$2552,Raw_Data!$A$2:$A$2552,$A21,Raw_Data!$D$2:$D$2552,"TikTok") | AK21: =IFERROR(AI21/AJ21,"") | AL21: =SUMIFS(Raw_Data!$R$2:$R$2552,Raw_Data!$A$2:$A$2552,$A21,Raw_Data!$D$2:$D$2552,"X") | AM21: =SUMIFS(Raw_Data!$AL$2:$AL$2552,Raw_Data!$A$2:$A$2552,$A21,Raw_Data!$D$2:$D$2552,"X") | AN21: =IFERROR(AL21/AM21,"") | AO21: =SUMIFS(Raw_Data!$R$2:$R$2552,Raw_Data!$A$2:$A$2552,$A21,Raw_Data!$D$2:$D$2552,"Programmatic") | AP21: =SUMIFS(Raw_Data!$AL$2:$AL$2552,Raw_Data!$A$2:$A$2552,$A21,Raw_Data!$D$2:$D$2552,"Programmatic") | AQ21: =IFERROR(AO21/AP21,"")
A22: 46252 | B22: Tue | C22: Wk 34 | D22: =SUMIFS(Raw_Data!$R$2:$R$2552,Raw_Data!$A$2:$A$2552,$A22) | E22: =SUMIFS(Raw_Data!$S$2:$S$2552,Raw_Data!$A$2:$A$2552,$A22) | F22: =SUMIFS(Raw_Data!$T$2:$T$2552,Raw_Data!$A$2:$A$2552,$A22) | G22: =IFERROR(E22/F22,"") | H22: =SUMIFS(Raw_Data!$W$2:$W$2552,Raw_Data!$A$2:$A$2552,$A22) | I22: =IFERROR(H22/E22,"") | J22: =IFERROR(D22/H22,"") | K22: =IFERROR(D22/E22*1000,"") | L22: =SUMIFS(Raw_Data!$AA$2:$AA$2552,Raw_Data!$A$2:$A$2552,$A22) | M22: =IFERROR(L22/H22,"") | N22: =SUMIFS(Raw_Data!$AL$2:$AL$2552,Raw_Data!$A$2:$A$2552,$A22) | O22: =IFERROR(N22/L22,"") | P22: =IFERROR(D22/N22,"") | Q22: =SUMIFS(Raw_Data!$AO$2:$AO$2552,Raw_Data!$A$2:$A$2552,$A22) | R22: =IFERROR(Q22/N22,"") | S22: =IFERROR(D22/Q22,"") | T22: =SUMIFS(Raw_Data!$AR$2:$AR$2552,Raw_Data!$A$2:$A$2552,$A22) | U22: =SUMIFS(Raw_Data!$AS$2:$AS$2552,Raw_Data!$A$2:$A$2552,$A22) | V22: =N22+T22 | W22: =SUMIFS(Raw_Data!$AU$2:$AU$2552,Raw_Data!$A$2:$A$2552,$A22) | X22: =IFERROR(D22/$D$36,"") | Y22: =IFERROR(N22/$N$36,"") | Z22: =SUM($D$5:D22) | AA22: =SUM($N$5:N22) | AB22: =IFERROR(Z22/AA22,"") | AC22: =IFERROR(Z22/Assumptions!$C$10,"") | AD22: =18/31 | AE22: =IFERROR(AC22/AD22,"") | AF22: =SUMIFS(Raw_Data!$R$2:$R$2552,Raw_Data!$A$2:$A$2552,$A22,Raw_Data!$D$2:$D$2552,"Meta (FB/IG)") | AG22: =SUMIFS(Raw_Data!$AL$2:$AL$2552,Raw_Data!$A$2:$A$2552,$A22,Raw_Data!$D$2:$D$2552,"Meta (FB/IG)") | AH22: =IFERROR(AF22/AG22,"") | AI22: =SUMIFS(Raw_Data!$R$2:$R$2552,Raw_Data!$A$2:$A$2552,$A22,Raw_Data!$D$2:$D$2552,"TikTok") | AJ22: =SUMIFS(Raw_Data!$AL$2:$AL$2552,Raw_Data!$A$2:$A$2552,$A22,Raw_Data!$D$2:$D$2552,"TikTok") | AK22: =IFERROR(AI22/AJ22,"") | AL22: =SUMIFS(Raw_Data!$R$2:$R$2552,Raw_Data!$A$2:$A$2552,$A22,Raw_Data!$D$2:$D$2552,"X") | AM22: =SUMIFS(Raw_Data!$AL$2:$AL$2552,Raw_Data!$A$2:$A$2552,$A22,Raw_Data!$D$2:$D$2552,"X") | AN22: =IFERROR(AL22/AM22,"") | AO22: =SUMIFS(Raw_Data!$R$2:$R$2552,Raw_Data!$A$2:$A$2552,$A22,Raw_Data!$D$2:$D$2552,"Programmatic") | AP22: =SUMIFS(Raw_Data!$AL$2:$AL$2552,Raw_Data!$A$2:$A$2552,$A22,Raw_Data!$D$2:$D$2552,"Programmatic") | AQ22: =IFERROR(AO22/AP22,"")
A23: 46253 | B23: Wed | C23: Wk 34 | D23: =SUMIFS(Raw_Data!$R$2:$R$2552,Raw_Data!$A$2:$A$2552,$A23) | E23: =SUMIFS(Raw_Data!$S$2:$S$2552,Raw_Data!$A$2:$A$2552,$A23) | F23: =SUMIFS(Raw_Data!$T$2:$T$2552,Raw_Data!$A$2:$A$2552,$A23) | G23: =IFERROR(E23/F23,"") | H23: =SUMIFS(Raw_Data!$W$2:$W$2552,Raw_Data!$A$2:$A$2552,$A23) | I23: =IFERROR(H23/E23,"") | J23: =IFERROR(D23/H23,"") | K23: =IFERROR(D23/E23*1000,"") | L23: =SUMIFS(Raw_Data!$AA$2:$AA$2552,Raw_Data!$A$2:$A$2552,$A23) | M23: =IFERROR(L23/H23,"") | N23: =SUMIFS(Raw_Data!$AL$2:$AL$2552,Raw_Data!$A$2:$A$2552,$A23) | O23: =IFERROR(N23/L23,"") | P23: =IFERROR(D23/N23,"") | Q23: =SUMIFS(Raw_Data!$AO$2:$AO$2552,Raw_Data!$A$2:$A$2552,$A23) | R23: =IFERROR(Q23/N23,"") | S23: =IFERROR(D23/Q23,"") | T23: =SUMIFS(Raw_Data!$AR$2:$AR$2552,Raw_Data!$A$2:$A$2552,$A23) | U23: =SUMIFS(Raw_Data!$AS$2:$AS$2552,Raw_Data!$A$2:$A$2552,$A23) | V23: =N23+T23 | W23: =SUMIFS(Raw_Data!$AU$2:$AU$2552,Raw_Data!$A$2:$A$2552,$A23) | X23: =IFERROR(D23/$D$36,"") | Y23: =IFERROR(N23/$N$36,"") | Z23: =SUM($D$5:D23) | AA23: =SUM($N$5:N23) | AB23: =IFERROR(Z23/AA23,"") | AC23: =IFERROR(Z23/Assumptions!$C$10,"") | AD23: =19/31 | AE23: =IFERROR(AC23/AD23,"") | AF23: =SUMIFS(Raw_Data!$R$2:$R$2552,Raw_Data!$A$2:$A$2552,$A23,Raw_Data!$D$2:$D$2552,"Meta (FB/IG)") | AG23: =SUMIFS(Raw_Data!$AL$2:$AL$2552,Raw_Data!$A$2:$A$2552,$A23,Raw_Data!$D$2:$D$2552,"Meta (FB/IG)") | AH23: =IFERROR(AF23/AG23,"") | AI23: =SUMIFS(Raw_Data!$R$2:$R$2552,Raw_Data!$A$2:$A$2552,$A23,Raw_Data!$D$2:$D$2552,"TikTok") | AJ23: =SUMIFS(Raw_Data!$AL$2:$AL$2552,Raw_Data!$A$2:$A$2552,$A23,Raw_Data!$D$2:$D$2552,"TikTok") | AK23: =IFERROR(AI23/AJ23,"") | AL23: =SUMIFS(Raw_Data!$R$2:$R$2552,Raw_Data!$A$2:$A$2552,$A23,Raw_Data!$D$2:$D$2552,"X") | AM23: =SUMIFS(Raw_Data!$AL$2:$AL$2552,Raw_Data!$A$2:$A$2552,$A23,Raw_Data!$D$2:$D$2552,"X") | AN23: =IFERROR(AL23/AM23,"") | AO23: =SUMIFS(Raw_Data!$R$2:$R$2552,Raw_Data!$A$2:$A$2552,$A23,Raw_Data!$D$2:$D$2552,"Programmatic") | AP23: =SUMIFS(Raw_Data!$AL$2:$AL$2552,Raw_Data!$A$2:$A$2552,$A23,Raw_Data!$D$2:$D$2552,"Programmatic") | AQ23: =IFERROR(AO23/AP23,"")
A24: 46254 | B24: Thu | C24: Wk 34 | D24: =SUMIFS(Raw_Data!$R$2:$R$2552,Raw_Data!$A$2:$A$2552,$A24) | E24: =SUMIFS(Raw_Data!$S$2:$S$2552,Raw_Data!$A$2:$A$2552,$A24) | F24: =SUMIFS(Raw_Data!$T$2:$T$2552,Raw_Data!$A$2:$A$2552,$A24) | G24: =IFERROR(E24/F24,"") | H24: =SUMIFS(Raw_Data!$W$2:$W$2552,Raw_Data!$A$2:$A$2552,$A24) | I24: =IFERROR(H24/E24,"") | J24: =IFERROR(D24/H24,"") | K24: =IFERROR(D24/E24*1000,"") | L24: =SUMIFS(Raw_Data!$AA$2:$AA$2552,Raw_Data!$A$2:$A$2552,$A24) | M24: =IFERROR(L24/H24,"") | N24: =SUMIFS(Raw_Data!$AL$2:$AL$2552,Raw_Data!$A$2:$A$2552,$A24) | O24: =IFERROR(N24/L24,"") | P24: =IFERROR(D24/N24,"") | Q24: =SUMIFS(Raw_Data!$AO$2:$AO$2552,Raw_Data!$A$2:$A$2552,$A24) | R24: =IFERROR(Q24/N24,"") | S24: =IFERROR(D24/Q24,"") | T24: =SUMIFS(Raw_Data!$AR$2:$AR$2552,Raw_Data!$A$2:$A$2552,$A24) | U24: =SUMIFS(Raw_Data!$AS$2:$AS$2552,Raw_Data!$A$2:$A$2552,$A24) | V24: =N24+T24 | W24: =SUMIFS(Raw_Data!$AU$2:$AU$2552,Raw_Data!$A$2:$A$2552,$A24) | X24: =IFERROR(D24/$D$36,"") | Y24: =IFERROR(N24/$N$36,"") | Z24: =SUM($D$5:D24) | AA24: =SUM($N$5:N24) | AB24: =IFERROR(Z24/AA24,"") | AC24: =IFERROR(Z24/Assumptions!$C$10,"") | AD24: =20/31 | AE24: =IFERROR(AC24/AD24,"") | AF24: =SUMIFS(Raw_Data!$R$2:$R$2552,Raw_Data!$A$2:$A$2552,$A24,Raw_Data!$D$2:$D$2552,"Meta (FB/IG)") | AG24: =SUMIFS(Raw_Data!$AL$2:$AL$2552,Raw_Data!$A$2:$A$2552,$A24,Raw_Data!$D$2:$D$2552,"Meta (FB/IG)") | AH24: =IFERROR(AF24/AG24,"") | AI24: =SUMIFS(Raw_Data!$R$2:$R$2552,Raw_Data!$A$2:$A$2552,$A24,Raw_Data!$D$2:$D$2552,"TikTok") | AJ24: =SUMIFS(Raw_Data!$AL$2:$AL$2552,Raw_Data!$A$2:$A$2552,$A24,Raw_Data!$D$2:$D$2552,"TikTok") | AK24: =IFERROR(AI24/AJ24,"") | AL24: =SUMIFS(Raw_Data!$R$2:$R$2552,Raw_Data!$A$2:$A$2552,$A24,Raw_Data!$D$2:$D$2552,"X") | AM24: =SUMIFS(Raw_Data!$AL$2:$AL$2552,Raw_Data!$A$2:$A$2552,$A24,Raw_Data!$D$2:$D$2552,"X") | AN24: =IFERROR(AL24/AM24,"") | AO24: =SUMIFS(Raw_Data!$R$2:$R$2552,Raw_Data!$A$2:$A$2552,$A24,Raw_Data!$D$2:$D$2552,"Programmatic") | AP24: =SUMIFS(Raw_Data!$AL$2:$AL$2552,Raw_Data!$A$2:$A$2552,$A24,Raw_Data!$D$2:$D$2552,"Programmatic") | AQ24: =IFERROR(AO24/AP24,"")
A25: 46255 | B25: Fri | C25: Wk 34 | D25: =SUMIFS(Raw_Data!$R$2:$R$2552,Raw_Data!$A$2:$A$2552,$A25) | E25: =SUMIFS(Raw_Data!$S$2:$S$2552,Raw_Data!$A$2:$A$2552,$A25) | F25: =SUMIFS(Raw_Data!$T$2:$T$2552,Raw_Data!$A$2:$A$2552,$A25) | G25: =IFERROR(E25/F25,"") | H25: =SUMIFS(Raw_Data!$W$2:$W$2552,Raw_Data!$A$2:$A$2552,$A25) | I25: =IFERROR(H25/E25,"") | J25: =IFERROR(D25/H25,"") | K25: =IFERROR(D25/E25*1000,"") | L25: =SUMIFS(Raw_Data!$AA$2:$AA$2552,Raw_Data!$A$2:$A$2552,$A25) | M25: =IFERROR(L25/H25,"") | N25: =SUMIFS(Raw_Data!$AL$2:$AL$2552,Raw_Data!$A$2:$A$2552,$A25) | O25: =IFERROR(N25/L25,"") | P25: =IFERROR(D25/N25,"") | Q25: =SUMIFS(Raw_Data!$AO$2:$AO$2552,Raw_Data!$A$2:$A$2552,$A25) | R25: =IFERROR(Q25/N25,"") | S25: =IFERROR(D25/Q25,"") | T25: =SUMIFS(Raw_Data!$AR$2:$AR$2552,Raw_Data!$A$2:$A$2552,$A25) | U25: =SUMIFS(Raw_Data!$AS$2:$AS$2552,Raw_Data!$A$2:$A$2552,$A25) | V25: =N25+T25 | W25: =SUMIFS(Raw_Data!$AU$2:$AU$2552,Raw_Data!$A$2:$A$2552,$A25) | X25: =IFERROR(D25/$D$36,"") | Y25: =IFERROR(N25/$N$36,"") | Z25: =SUM($D$5:D25) | AA25: =SUM($N$5:N25) | AB25: =IFERROR(Z25/AA25,"") | AC25: =IFERROR(Z25/Assumptions!$C$10,"") | AD25: =21/31 | AE25: =IFERROR(AC25/AD25,"") | AF25: =SUMIFS(Raw_Data!$R$2:$R$2552,Raw_Data!$A$2:$A$2552,$A25,Raw_Data!$D$2:$D$2552,"Meta (FB/IG)") | AG25: =SUMIFS(Raw_Data!$AL$2:$AL$2552,Raw_Data!$A$2:$A$2552,$A25,Raw_Data!$D$2:$D$2552,"Meta (FB/IG)") | AH25: =IFERROR(AF25/AG25,"") | AI25: =SUMIFS(Raw_Data!$R$2:$R$2552,Raw_Data!$A$2:$A$2552,$A25,Raw_Data!$D$2:$D$2552,"TikTok") | AJ25: =SUMIFS(Raw_Data!$AL$2:$AL$2552,Raw_Data!$A$2:$A$2552,$A25,Raw_Data!$D$2:$D$2552,"TikTok") | AK25: =IFERROR(AI25/AJ25,"") | AL25: =SUMIFS(Raw_Data!$R$2:$R$2552,Raw_Data!$A$2:$A$2552,$A25,Raw_Data!$D$2:$D$2552,"X") | AM25: =SUMIFS(Raw_Data!$AL$2:$AL$2552,Raw_Data!$A$2:$A$2552,$A25,Raw_Data!$D$2:$D$2552,"X") | AN25: =IFERROR(AL25/AM25,"") | AO25: =SUMIFS(Raw_Data!$R$2:$R$2552,Raw_Data!$A$2:$A$2552,$A25,Raw_Data!$D$2:$D$2552,"Programmatic") | AP25: =SUMIFS(Raw_Data!$AL$2:$AL$2552,Raw_Data!$A$2:$A$2552,$A25,Raw_Data!$D$2:$D$2552,"Programmatic") | AQ25: =IFERROR(AO25/AP25,"")
A26: 46256 | B26: Sat | C26: Wk 34 | D26: =SUMIFS(Raw_Data!$R$2:$R$2552,Raw_Data!$A$2:$A$2552,$A26) | E26: =SUMIFS(Raw_Data!$S$2:$S$2552,Raw_Data!$A$2:$A$2552,$A26) | F26: =SUMIFS(Raw_Data!$T$2:$T$2552,Raw_Data!$A$2:$A$2552,$A26) | G26: =IFERROR(E26/F26,"") | H26: =SUMIFS(Raw_Data!$W$2:$W$2552,Raw_Data!$A$2:$A$2552,$A26) | I26: =IFERROR(H26/E26,"") | J26: =IFERROR(D26/H26,"") | K26: =IFERROR(D26/E26*1000,"") | L26: =SUMIFS(Raw_Data!$AA$2:$AA$2552,Raw_Data!$A$2:$A$2552,$A26) | M26: =IFERROR(L26/H26,"") | N26: =SUMIFS(Raw_Data!$AL$2:$AL$2552,Raw_Data!$A$2:$A$2552,$A26) | O26: =IFERROR(N26/L26,"") | P26: =IFERROR(D26/N26,"") | Q26: =SUMIFS(Raw_Data!$AO$2:$AO$2552,Raw_Data!$A$2:$A$2552,$A26) | R26: =IFERROR(Q26/N26,"") | S26: =IFERROR(D26/Q26,"") | T26: =SUMIFS(Raw_Data!$AR$2:$AR$2552,Raw_Data!$A$2:$A$2552,$A26) | U26: =SUMIFS(Raw_Data!$AS$2:$AS$2552,Raw_Data!$A$2:$A$2552,$A26) | V26: =N26+T26 | W26: =SUMIFS(Raw_Data!$AU$2:$AU$2552,Raw_Data!$A$2:$A$2552,$A26) | X26: =IFERROR(D26/$D$36,"") | Y26: =IFERROR(N26/$N$36,"") | Z26: =SUM($D$5:D26) | AA26: =SUM($N$5:N26) | AB26: =IFERROR(Z26/AA26,"") | AC26: =IFERROR(Z26/Assumptions!$C$10,"") | AD26: =22/31 | AE26: =IFERROR(AC26/AD26,"") | AF26: =SUMIFS(Raw_Data!$R$2:$R$2552,Raw_Data!$A$2:$A$2552,$A26,Raw_Data!$D$2:$D$2552,"Meta (FB/IG)") | AG26: =SUMIFS(Raw_Data!$AL$2:$AL$2552,Raw_Data!$A$2:$A$2552,$A26,Raw_Data!$D$2:$D$2552,"Meta (FB/IG)") | AH26: =IFERROR(AF26/AG26,"") | AI26: =SUMIFS(Raw_Data!$R$2:$R$2552,Raw_Data!$A$2:$A$2552,$A26,Raw_Data!$D$2:$D$2552,"TikTok") | AJ26: =SUMIFS(Raw_Data!$AL$2:$AL$2552,Raw_Data!$A$2:$A$2552,$A26,Raw_Data!$D$2:$D$2552,"TikTok") | AK26: =IFERROR(AI26/AJ26,"") | AL26: =SUMIFS(Raw_Data!$R$2:$R$2552,Raw_Data!$A$2:$A$2552,$A26,Raw_Data!$D$2:$D$2552,"X") | AM26: =SUMIFS(Raw_Data!$AL$2:$AL$2552,Raw_Data!$A$2:$A$2552,$A26,Raw_Data!$D$2:$D$2552,"X") | AN26: =IFERROR(AL26/AM26,"") | AO26: =SUMIFS(Raw_Data!$R$2:$R$2552,Raw_Data!$A$2:$A$2552,$A26,Raw_Data!$D$2:$D$2552,"Programmatic") | AP26: =SUMIFS(Raw_Data!$AL$2:$AL$2552,Raw_Data!$A$2:$A$2552,$A26,Raw_Data!$D$2:$D$2552,"Programmatic") | AQ26: =IFERROR(AO26/AP26,"")
A27: 46257 | B27: Sun | C27: Wk 34 | D27: =SUMIFS(Raw_Data!$R$2:$R$2552,Raw_Data!$A$2:$A$2552,$A27) | E27: =SUMIFS(Raw_Data!$S$2:$S$2552,Raw_Data!$A$2:$A$2552,$A27) | F27: =SUMIFS(Raw_Data!$T$2:$T$2552,Raw_Data!$A$2:$A$2552,$A27) | G27: =IFERROR(E27/F27,"") | H27: =SUMIFS(Raw_Data!$W$2:$W$2552,Raw_Data!$A$2:$A$2552,$A27) | I27: =IFERROR(H27/E27,"") | J27: =IFERROR(D27/H27,"") | K27: =IFERROR(D27/E27*1000,"") | L27: =SUMIFS(Raw_Data!$AA$2:$AA$2552,Raw_Data!$A$2:$A$2552,$A27) | M27: =IFERROR(L27/H27,"") | N27: =SUMIFS(Raw_Data!$AL$2:$AL$2552,Raw_Data!$A$2:$A$2552,$A27) | O27: =IFERROR(N27/L27,"") | P27: =IFERROR(D27/N27,"") | Q27: =SUMIFS(Raw_Data!$AO$2:$AO$2552,Raw_Data!$A$2:$A$2552,$A27) | R27: =IFERROR(Q27/N27,"") | S27: =IFERROR(D27/Q27,"") | T27: =SUMIFS(Raw_Data!$AR$2:$AR$2552,Raw_Data!$A$2:$A$2552,$A27) | U27: =SUMIFS(Raw_Data!$AS$2:$AS$2552,Raw_Data!$A$2:$A$2552,$A27) | V27: =N27+T27 | W27: =SUMIFS(Raw_Data!$AU$2:$AU$2552,Raw_Data!$A$2:$A$2552,$A27) | X27: =IFERROR(D27/$D$36,"") | Y27: =IFERROR(N27/$N$36,"") | Z27: =SUM($D$5:D27) | AA27: =SUM($N$5:N27) | AB27: =IFERROR(Z27/AA27,"") | AC27: =IFERROR(Z27/Assumptions!$C$10,"") | AD27: =23/31 | AE27: =IFERROR(AC27/AD27,"") | AF27: =SUMIFS(Raw_Data!$R$2:$R$2552,Raw_Data!$A$2:$A$2552,$A27,Raw_Data!$D$2:$D$2552,"Meta (FB/IG)") | AG27: =SUMIFS(Raw_Data!$AL$2:$AL$2552,Raw_Data!$A$2:$A$2552,$A27,Raw_Data!$D$2:$D$2552,"Meta (FB/IG)") | AH27: =IFERROR(AF27/AG27,"") | AI27: =SUMIFS(Raw_Data!$R$2:$R$2552,Raw_Data!$A$2:$A$2552,$A27,Raw_Data!$D$2:$D$2552,"TikTok") | AJ27: =SUMIFS(Raw_Data!$AL$2:$AL$2552,Raw_Data!$A$2:$A$2552,$A27,Raw_Data!$D$2:$D$2552,"TikTok") | AK27: =IFERROR(AI27/AJ27,"") | AL27: =SUMIFS(Raw_Data!$R$2:$R$2552,Raw_Data!$A$2:$A$2552,$A27,Raw_Data!$D$2:$D$2552,"X") | AM27: =SUMIFS(Raw_Data!$AL$2:$AL$2552,Raw_Data!$A$2:$A$2552,$A27,Raw_Data!$D$2:$D$2552,"X") | AN27: =IFERROR(AL27/AM27,"") | AO27: =SUMIFS(Raw_Data!$R$2:$R$2552,Raw_Data!$A$2:$A$2552,$A27,Raw_Data!$D$2:$D$2552,"Programmatic") | AP27: =SUMIFS(Raw_Data!$AL$2:$AL$2552,Raw_Data!$A$2:$A$2552,$A27,Raw_Data!$D$2:$D$2552,"Programmatic") | AQ27: =IFERROR(AO27/AP27,"")
A28: 46258 | B28: Mon | C28: Wk 35 | D28: =SUMIFS(Raw_Data!$R$2:$R$2552,Raw_Data!$A$2:$A$2552,$A28) | E28: =SUMIFS(Raw_Data!$S$2:$S$2552,Raw_Data!$A$2:$A$2552,$A28) | F28: =SUMIFS(Raw_Data!$T$2:$T$2552,Raw_Data!$A$2:$A$2552,$A28) | G28: =IFERROR(E28/F28,"") | H28: =SUMIFS(Raw_Data!$W$2:$W$2552,Raw_Data!$A$2:$A$2552,$A28) | I28: =IFERROR(H28/E28,"") | J28: =IFERROR(D28/H28,"") | K28: =IFERROR(D28/E28*1000,"") | L28: =SUMIFS(Raw_Data!$AA$2:$AA$2552,Raw_Data!$A$2:$A$2552,$A28) | M28: =IFERROR(L28/H28,"") | N28: =SUMIFS(Raw_Data!$AL$2:$AL$2552,Raw_Data!$A$2:$A$2552,$A28) | O28: =IFERROR(N28/L28,"") | P28: =IFERROR(D28/N28,"") | Q28: =SUMIFS(Raw_Data!$AO$2:$AO$2552,Raw_Data!$A$2:$A$2552,$A28) | R28: =IFERROR(Q28/N28,"") | S28: =IFERROR(D28/Q28,"") | T28: =SUMIFS(Raw_Data!$AR$2:$AR$2552,Raw_Data!$A$2:$A$2552,$A28) | U28: =SUMIFS(Raw_Data!$AS$2:$AS$2552,Raw_Data!$A$2:$A$2552,$A28) | V28: =N28+T28 | W28: =SUMIFS(Raw_Data!$AU$2:$AU$2552,Raw_Data!$A$2:$A$2552,$A28) | X28: =IFERROR(D28/$D$36,"") | Y28: =IFERROR(N28/$N$36,"") | Z28: =SUM($D$5:D28) | AA28: =SUM($N$5:N28) | AB28: =IFERROR(Z28/AA28,"") | AC28: =IFERROR(Z28/Assumptions!$C$10,"") | AD28: =24/31 | AE28: =IFERROR(AC28/AD28,"") | AF28: =SUMIFS(Raw_Data!$R$2:$R$2552,Raw_Data!$A$2:$A$2552,$A28,Raw_Data!$D$2:$D$2552,"Meta (FB/IG)") | AG28: =SUMIFS(Raw_Data!$AL$2:$AL$2552,Raw_Data!$A$2:$A$2552,$A28,Raw_Data!$D$2:$D$2552,"Meta (FB/IG)") | AH28: =IFERROR(AF28/AG28,"") | AI28: =SUMIFS(Raw_Data!$R$2:$R$2552,Raw_Data!$A$2:$A$2552,$A28,Raw_Data!$D$2:$D$2552,"TikTok") | AJ28: =SUMIFS(Raw_Data!$AL$2:$AL$2552,Raw_Data!$A$2:$A$2552,$A28,Raw_Data!$D$2:$D$2552,"TikTok") | AK28: =IFERROR(AI28/AJ28,"") | AL28: =SUMIFS(Raw_Data!$R$2:$R$2552,Raw_Data!$A$2:$A$2552,$A28,Raw_Data!$D$2:$D$2552,"X") | AM28: =SUMIFS(Raw_Data!$AL$2:$AL$2552,Raw_Data!$A$2:$A$2552,$A28,Raw_Data!$D$2:$D$2552,"X") | AN28: =IFERROR(AL28/AM28,"") | AO28: =SUMIFS(Raw_Data!$R$2:$R$2552,Raw_Data!$A$2:$A$2552,$A28,Raw_Data!$D$2:$D$2552,"Programmatic") | AP28: =SUMIFS(Raw_Data!$AL$2:$AL$2552,Raw_Data!$A$2:$A$2552,$A28,Raw_Data!$D$2:$D$2552,"Programmatic") | AQ28: =IFERROR(AO28/AP28,"")
A29: 46259 | B29: Tue | C29: Wk 35 | D29: =SUMIFS(Raw_Data!$R$2:$R$2552,Raw_Data!$A$2:$A$2552,$A29) | E29: =SUMIFS(Raw_Data!$S$2:$S$2552,Raw_Data!$A$2:$A$2552,$A29) | F29: =SUMIFS(Raw_Data!$T$2:$T$2552,Raw_Data!$A$2:$A$2552,$A29) | G29: =IFERROR(E29/F29,"") | H29: =SUMIFS(Raw_Data!$W$2:$W$2552,Raw_Data!$A$2:$A$2552,$A29) | I29: =IFERROR(H29/E29,"") | J29: =IFERROR(D29/H29,"") | K29: =IFERROR(D29/E29*1000,"") | L29: =SUMIFS(Raw_Data!$AA$2:$AA$2552,Raw_Data!$A$2:$A$2552,$A29) | M29: =IFERROR(L29/H29,"") | N29: =SUMIFS(Raw_Data!$AL$2:$AL$2552,Raw_Data!$A$2:$A$2552,$A29) | O29: =IFERROR(N29/L29,"") | P29: =IFERROR(D29/N29,"") | Q29: =SUMIFS(Raw_Data!$AO$2:$AO$2552,Raw_Data!$A$2:$A$2552,$A29) | R29: =IFERROR(Q29/N29,"") | S29: =IFERROR(D29/Q29,"") | T29: =SUMIFS(Raw_Data!$AR$2:$AR$2552,Raw_Data!$A$2:$A$2552,$A29) | U29: =SUMIFS(Raw_Data!$AS$2:$AS$2552,Raw_Data!$A$2:$A$2552,$A29) | V29: =N29+T29 | W29: =SUMIFS(Raw_Data!$AU$2:$AU$2552,Raw_Data!$A$2:$A$2552,$A29) | X29: =IFERROR(D29/$D$36,"") | Y29: =IFERROR(N29/$N$36,"") | Z29: =SUM($D$5:D29) | AA29: =SUM($N$5:N29) | AB29: =IFERROR(Z29/AA29,"") | AC29: =IFERROR(Z29/Assumptions!$C$10,"") | AD29: =25/31 | AE29: =IFERROR(AC29/AD29,"") | AF29: =SUMIFS(Raw_Data!$R$2:$R$2552,Raw_Data!$A$2:$A$2552,$A29,Raw_Data!$D$2:$D$2552,"Meta (FB/IG)") | AG29: =SUMIFS(Raw_Data!$AL$2:$AL$2552,Raw_Data!$A$2:$A$2552,$A29,Raw_Data!$D$2:$D$2552,"Meta (FB/IG)") | AH29: =IFERROR(AF29/AG29,"") | AI29: =SUMIFS(Raw_Data!$R$2:$R$2552,Raw_Data!$A$2:$A$2552,$A29,Raw_Data!$D$2:$D$2552,"TikTok") | AJ29: =SUMIFS(Raw_Data!$AL$2:$AL$2552,Raw_Data!$A$2:$A$2552,$A29,Raw_Data!$D$2:$D$2552,"TikTok") | AK29: =IFERROR(AI29/AJ29,"") | AL29: =SUMIFS(Raw_Data!$R$2:$R$2552,Raw_Data!$A$2:$A$2552,$A29,Raw_Data!$D$2:$D$2552,"X") | AM29: =SUMIFS(Raw_Data!$AL$2:$AL$2552,Raw_Data!$A$2:$A$2552,$A29,Raw_Data!$D$2:$D$2552,"X") | AN29: =IFERROR(AL29/AM29,"") | AO29: =SUMIFS(Raw_Data!$R$2:$R$2552,Raw_Data!$A$2:$A$2552,$A29,Raw_Data!$D$2:$D$2552,"Programmatic") | AP29: =SUMIFS(Raw_Data!$AL$2:$AL$2552,Raw_Data!$A$2:$A$2552,$A29,Raw_Data!$D$2:$D$2552,"Programmatic") | AQ29: =IFERROR(AO29/AP29,"")
A30: 46260 | B30: Wed | C30: Wk 35 | D30: =SUMIFS(Raw_Data!$R$2:$R$2552,Raw_Data!$A$2:$A$2552,$A30) | E30: =SUMIFS(Raw_Data!$S$2:$S$2552,Raw_Data!$A$2:$A$2552,$A30) | F30: =SUMIFS(Raw_Data!$T$2:$T$2552,Raw_Data!$A$2:$A$2552,$A30) | G30: =IFERROR(E30/F30,"") | H30: =SUMIFS(Raw_Data!$W$2:$W$2552,Raw_Data!$A$2:$A$2552,$A30) | I30: =IFERROR(H30/E30,"") | J30: =IFERROR(D30/H30,"") | K30: =IFERROR(D30/E30*1000,"") | L30: =SUMIFS(Raw_Data!$AA$2:$AA$2552,Raw_Data!$A$2:$A$2552,$A30) | M30: =IFERROR(L30/H30,"") | N30: =SUMIFS(Raw_Data!$AL$2:$AL$2552,Raw_Data!$A$2:$A$2552,$A30) | O30: =IFERROR(N30/L30,"") | P30: =IFERROR(D30/N30,"") | Q30: =SUMIFS(Raw_Data!$AO$2:$AO$2552,Raw_Data!$A$2:$A$2552,$A30) | R30: =IFERROR(Q30/N30,"") | S30: =IFERROR(D30/Q30,"") | T30: =SUMIFS(Raw_Data!$AR$2:$AR$2552,Raw_Data!$A$2:$A$2552,$A30) | U30: =SUMIFS(Raw_Data!$AS$2:$AS$2552,Raw_Data!$A$2:$A$2552,$A30) | V30: =N30+T30 | W30: =SUMIFS(Raw_Data!$AU$2:$AU$2552,Raw_Data!$A$2:$A$2552,$A30) | X30: =IFERROR(D30/$D$36,"") | Y30: =IFERROR(N30/$N$36,"") | Z30: =SUM($D$5:D30) | AA30: =SUM($N$5:N30) | AB30: =IFERROR(Z30/AA30,"") | AC30: =IFERROR(Z30/Assumptions!$C$10,"") | AD30: =26/31 | AE30: =IFERROR(AC30/AD30,"") | AF30: =SUMIFS(Raw_Data!$R$2:$R$2552,Raw_Data!$A$2:$A$2552,$A30,Raw_Data!$D$2:$D$2552,"Meta (FB/IG)") | AG30: =SUMIFS(Raw_Data!$AL$2:$AL$2552,Raw_Data!$A$2:$A$2552,$A30,Raw_Data!$D$2:$D$2552,"Meta (FB/IG)") | AH30: =IFERROR(AF30/AG30,"") | AI30: =SUMIFS(Raw_Data!$R$2:$R$2552,Raw_Data!$A$2:$A$2552,$A30,Raw_Data!$D$2:$D$2552,"TikTok") | AJ30: =SUMIFS(Raw_Data!$AL$2:$AL$2552,Raw_Data!$A$2:$A$2552,$A30,Raw_Data!$D$2:$D$2552,"TikTok") | AK30: =IFERROR(AI30/AJ30,"") | AL30: =SUMIFS(Raw_Data!$R$2:$R$2552,Raw_Data!$A$2:$A$2552,$A30,Raw_Data!$D$2:$D$2552,"X") | AM30: =SUMIFS(Raw_Data!$AL$2:$AL$2552,Raw_Data!$A$2:$A$2552,$A30,Raw_Data!$D$2:$D$2552,"X") | AN30: =IFERROR(AL30/AM30,"") | AO30: =SUMIFS(Raw_Data!$R$2:$R$2552,Raw_Data!$A$2:$A$2552,$A30,Raw_Data!$D$2:$D$2552,"Programmatic") | AP30: =SUMIFS(Raw_Data!$AL$2:$AL$2552,Raw_Data!$A$2:$A$2552,$A30,Raw_Data!$D$2:$D$2552,"Programmatic") | AQ30: =IFERROR(AO30/AP30,"")
A31: 46261 | B31: Thu | C31: Wk 35 | D31: =SUMIFS(Raw_Data!$R$2:$R$2552,Raw_Data!$A$2:$A$2552,$A31) | E31: =SUMIFS(Raw_Data!$S$2:$S$2552,Raw_Data!$A$2:$A$2552,$A31) | F31: =SUMIFS(Raw_Data!$T$2:$T$2552,Raw_Data!$A$2:$A$2552,$A31) | G31: =IFERROR(E31/F31,"") | H31: =SUMIFS(Raw_Data!$W$2:$W$2552,Raw_Data!$A$2:$A$2552,$A31) | I31: =IFERROR(H31/E31,"") | J31: =IFERROR(D31/H31,"") | K31: =IFERROR(D31/E31*1000,"") | L31: =SUMIFS(Raw_Data!$AA$2:$AA$2552,Raw_Data!$A$2:$A$2552,$A31) | M31: =IFERROR(L31/H31,"") | N31: =SUMIFS(Raw_Data!$AL$2:$AL$2552,Raw_Data!$A$2:$A$2552,$A31) | O31: =IFERROR(N31/L31,"") | P31: =IFERROR(D31/N31,"") | Q31: =SUMIFS(Raw_Data!$AO$2:$AO$2552,Raw_Data!$A$2:$A$2552,$A31) | R31: =IFERROR(Q31/N31,"") | S31: =IFERROR(D31/Q31,"") | T31: =SUMIFS(Raw_Data!$AR$2:$AR$2552,Raw_Data!$A$2:$A$2552,$A31) | U31: =SUMIFS(Raw_Data!$AS$2:$AS$2552,Raw_Data!$A$2:$A$2552,$A31) | V31: =N31+T31 | W31: =SUMIFS(Raw_Data!$AU$2:$AU$2552,Raw_Data!$A$2:$A$2552,$A31) | X31: =IFERROR(D31/$D$36,"") | Y31: =IFERROR(N31/$N$36,"") | Z31: =SUM($D$5:D31) | AA31: =SUM($N$5:N31) | AB31: =IFERROR(Z31/AA31,"") | AC31: =IFERROR(Z31/Assumptions!$C$10,"") | AD31: =27/31 | AE31: =IFERROR(AC31/AD31,"") | AF31: =SUMIFS(Raw_Data!$R$2:$R$2552,Raw_Data!$A$2:$A$2552,$A31,Raw_Data!$D$2:$D$2552,"Meta (FB/IG)") | AG31: =SUMIFS(Raw_Data!$AL$2:$AL$2552,Raw_Data!$A$2:$A$2552,$A31,Raw_Data!$D$2:$D$2552,"Meta (FB/IG)") | AH31: =IFERROR(AF31/AG31,"") | AI31: =SUMIFS(Raw_Data!$R$2:$R$2552,Raw_Data!$A$2:$A$2552,$A31,Raw_Data!$D$2:$D$2552,"TikTok") | AJ31: =SUMIFS(Raw_Data!$AL$2:$AL$2552,Raw_Data!$A$2:$A$2552,$A31,Raw_Data!$D$2:$D$2552,"TikTok") | AK31: =IFERROR(AI31/AJ31,"") | AL31: =SUMIFS(Raw_Data!$R$2:$R$2552,Raw_Data!$A$2:$A$2552,$A31,Raw_Data!$D$2:$D$2552,"X") | AM31: =SUMIFS(Raw_Data!$AL$2:$AL$2552,Raw_Data!$A$2:$A$2552,$A31,Raw_Data!$D$2:$D$2552,"X") | AN31: =IFERROR(AL31/AM31,"") | AO31: =SUMIFS(Raw_Data!$R$2:$R$2552,Raw_Data!$A$2:$A$2552,$A31,Raw_Data!$D$2:$D$2552,"Programmatic") | AP31: =SUMIFS(Raw_Data!$AL$2:$AL$2552,Raw_Data!$A$2:$A$2552,$A31,Raw_Data!$D$2:$D$2552,"Programmatic") | AQ31: =IFERROR(AO31/AP31,"")
A32: 46262 | B32: Fri | C32: Wk 35 | D32: =SUMIFS(Raw_Data!$R$2:$R$2552,Raw_Data!$A$2:$A$2552,$A32) | E32: =SUMIFS(Raw_Data!$S$2:$S$2552,Raw_Data!$A$2:$A$2552,$A32) | F32: =SUMIFS(Raw_Data!$T$2:$T$2552,Raw_Data!$A$2:$A$2552,$A32) | G32: =IFERROR(E32/F32,"") | H32: =SUMIFS(Raw_Data!$W$2:$W$2552,Raw_Data!$A$2:$A$2552,$A32) | I32: =IFERROR(H32/E32,"") | J32: =IFERROR(D32/H32,"") | K32: =IFERROR(D32/E32*1000,"") | L32: =SUMIFS(Raw_Data!$AA$2:$AA$2552,Raw_Data!$A$2:$A$2552,$A32) | M32: =IFERROR(L32/H32,"") | N32: =SUMIFS(Raw_Data!$AL$2:$AL$2552,Raw_Data!$A$2:$A$2552,$A32) | O32: =IFERROR(N32/L32,"") | P32: =IFERROR(D32/N32,"") | Q32: =SUMIFS(Raw_Data!$AO$2:$AO$2552,Raw_Data!$A$2:$A$2552,$A32) | R32: =IFERROR(Q32/N32,"") | S32: =IFERROR(D32/Q32,"") | T32: =SUMIFS(Raw_Data!$AR$2:$AR$2552,Raw_Data!$A$2:$A$2552,$A32) | U32: =SUMIFS(Raw_Data!$AS$2:$AS$2552,Raw_Data!$A$2:$A$2552,$A32) | V32: =N32+T32 | W32: =SUMIFS(Raw_Data!$AU$2:$AU$2552,Raw_Data!$A$2:$A$2552,$A32) | X32: =IFERROR(D32/$D$36,"") | Y32: =IFERROR(N32/$N$36,"") | Z32: =SUM($D$5:D32) | AA32: =SUM($N$5:N32) | AB32: =IFERROR(Z32/AA32,"") | AC32: =IFERROR(Z32/Assumptions!$C$10,"") | AD32: =28/31 | AE32: =IFERROR(AC32/AD32,"") | AF32: =SUMIFS(Raw_Data!$R$2:$R$2552,Raw_Data!$A$2:$A$2552,$A32,Raw_Data!$D$2:$D$2552,"Meta (FB/IG)") | AG32: =SUMIFS(Raw_Data!$AL$2:$AL$2552,Raw_Data!$A$2:$A$2552,$A32,Raw_Data!$D$2:$D$2552,"Meta (FB/IG)") | AH32: =IFERROR(AF32/AG32,"") | AI32: =SUMIFS(Raw_Data!$R$2:$R$2552,Raw_Data!$A$2:$A$2552,$A32,Raw_Data!$D$2:$D$2552,"TikTok") | AJ32: =SUMIFS(Raw_Data!$AL$2:$AL$2552,Raw_Data!$A$2:$A$2552,$A32,Raw_Data!$D$2:$D$2552,"TikTok") | AK32: =IFERROR(AI32/AJ32,"") | AL32: =SUMIFS(Raw_Data!$R$2:$R$2552,Raw_Data!$A$2:$A$2552,$A32,Raw_Data!$D$2:$D$2552,"X") | AM32: =SUMIFS(Raw_Data!$AL$2:$AL$2552,Raw_Data!$A$2:$A$2552,$A32,Raw_Data!$D$2:$D$2552,"X") | AN32: =IFERROR(AL32/AM32,"") | AO32: =SUMIFS(Raw_Data!$R$2:$R$2552,Raw_Data!$A$2:$A$2552,$A32,Raw_Data!$D$2:$D$2552,"Programmatic") | AP32: =SUMIFS(Raw_Data!$AL$2:$AL$2552,Raw_Data!$A$2:$A$2552,$A32,Raw_Data!$D$2:$D$2552,"Programmatic") | AQ32: =IFERROR(AO32/AP32,"")
A33: 46263 | B33: Sat | C33: Wk 35 | D33: =SUMIFS(Raw_Data!$R$2:$R$2552,Raw_Data!$A$2:$A$2552,$A33) | E33: =SUMIFS(Raw_Data!$S$2:$S$2552,Raw_Data!$A$2:$A$2552,$A33) | F33: =SUMIFS(Raw_Data!$T$2:$T$2552,Raw_Data!$A$2:$A$2552,$A33) | G33: =IFERROR(E33/F33,"") | H33: =SUMIFS(Raw_Data!$W$2:$W$2552,Raw_Data!$A$2:$A$2552,$A33) | I33: =IFERROR(H33/E33,"") | J33: =IFERROR(D33/H33,"") | K33: =IFERROR(D33/E33*1000,"") | L33: =SUMIFS(Raw_Data!$AA$2:$AA$2552,Raw_Data!$A$2:$A$2552,$A33) | M33: =IFERROR(L33/H33,"") | N33: =SUMIFS(Raw_Data!$AL$2:$AL$2552,Raw_Data!$A$2:$A$2552,$A33) | O33: =IFERROR(N33/L33,"") | P33: =IFERROR(D33/N33,"") | Q33: =SUMIFS(Raw_Data!$AO$2:$AO$2552,Raw_Data!$A$2:$A$2552,$A33) | R33: =IFERROR(Q33/N33,"") | S33: =IFERROR(D33/Q33,"") | T33: =SUMIFS(Raw_Data!$AR$2:$AR$2552,Raw_Data!$A$2:$A$2552,$A33) | U33: =SUMIFS(Raw_Data!$AS$2:$AS$2552,Raw_Data!$A$2:$A$2552,$A33) | V33: =N33+T33 | W33: =SUMIFS(Raw_Data!$AU$2:$AU$2552,Raw_Data!$A$2:$A$2552,$A33) | X33: =IFERROR(D33/$D$36,"") | Y33: =IFERROR(N33/$N$36,"") | Z33: =SUM($D$5:D33) | AA33: =SUM($N$5:N33) | AB33: =IFERROR(Z33/AA33,"") | AC33: =IFERROR(Z33/Assumptions!$C$10,"") | AD33: =29/31 | AE33: =IFERROR(AC33/AD33,"") | AF33: =SUMIFS(Raw_Data!$R$2:$R$2552,Raw_Data!$A$2:$A$2552,$A33,Raw_Data!$D$2:$D$2552,"Meta (FB/IG)") | AG33: =SUMIFS(Raw_Data!$AL$2:$AL$2552,Raw_Data!$A$2:$A$2552,$A33,Raw_Data!$D$2:$D$2552,"Meta (FB/IG)") | AH33: =IFERROR(AF33/AG33,"") | AI33: =SUMIFS(Raw_Data!$R$2:$R$2552,Raw_Data!$A$2:$A$2552,$A33,Raw_Data!$D$2:$D$2552,"TikTok") | AJ33: =SUMIFS(Raw_Data!$AL$2:$AL$2552,Raw_Data!$A$2:$A$2552,$A33,Raw_Data!$D$2:$D$2552,"TikTok") | AK33: =IFERROR(AI33/AJ33,"") | AL33: =SUMIFS(Raw_Data!$R$2:$R$2552,Raw_Data!$A$2:$A$2552,$A33,Raw_Data!$D$2:$D$2552,"X") | AM33: =SUMIFS(Raw_Data!$AL$2:$AL$2552,Raw_Data!$A$2:$A$2552,$A33,Raw_Data!$D$2:$D$2552,"X") | AN33: =IFERROR(AL33/AM33,"") | AO33: =SUMIFS(Raw_Data!$R$2:$R$2552,Raw_Data!$A$2:$A$2552,$A33,Raw_Data!$D$2:$D$2552,"Programmatic") | AP33: =SUMIFS(Raw_Data!$AL$2:$AL$2552,Raw_Data!$A$2:$A$2552,$A33,Raw_Data!$D$2:$D$2552,"Programmatic") | AQ33: =IFERROR(AO33/AP33,"")
A34: 46264 | B34: Sun | C34: Wk 35 | D34: =SUMIFS(Raw_Data!$R$2:$R$2552,Raw_Data!$A$2:$A$2552,$A34) | E34: =SUMIFS(Raw_Data!$S$2:$S$2552,Raw_Data!$A$2:$A$2552,$A34) | F34: =SUMIFS(Raw_Data!$T$2:$T$2552,Raw_Data!$A$2:$A$2552,$A34) | G34: =IFERROR(E34/F34,"") | H34: =SUMIFS(Raw_Data!$W$2:$W$2552,Raw_Data!$A$2:$A$2552,$A34) | I34: =IFERROR(H34/E34,"") | J34: =IFERROR(D34/H34,"") | K34: =IFERROR(D34/E34*1000,"") | L34: =SUMIFS(Raw_Data!$AA$2:$AA$2552,Raw_Data!$A$2:$A$2552,$A34) | M34: =IFERROR(L34/H34,"") | N34: =SUMIFS(Raw_Data!$AL$2:$AL$2552,Raw_Data!$A$2:$A$2552,$A34) | O34: =IFERROR(N34/L34,"") | P34: =IFERROR(D34/N34,"") | Q34: =SUMIFS(Raw_Data!$AO$2:$AO$2552,Raw_Data!$A$2:$A$2552,$A34) | R34: =IFERROR(Q34/N34,"") | S34: =IFERROR(D34/Q34,"") | T34: =SUMIFS(Raw_Data!$AR$2:$AR$2552,Raw_Data!$A$2:$A$2552,$A34) | U34: =SUMIFS(Raw_Data!$AS$2:$AS$2552,Raw_Data!$A$2:$A$2552,$A34) | V34: =N34+T34 | W34: =SUMIFS(Raw_Data!$AU$2:$AU$2552,Raw_Data!$A$2:$A$2552,$A34) | X34: =IFERROR(D34/$D$36,"") | Y34: =IFERROR(N34/$N$36,"") | Z34: =SUM($D$5:D34) | AA34: =SUM($N$5:N34) | AB34: =IFERROR(Z34/AA34,"") | AC34: =IFERROR(Z34/Assumptions!$C$10,"") | AD34: =30/31 | AE34: =IFERROR(AC34/AD34,"") | AF34: =SUMIFS(Raw_Data!$R$2:$R$2552,Raw_Data!$A$2:$A$2552,$A34,Raw_Data!$D$2:$D$2552,"Meta (FB/IG)") | AG34: =SUMIFS(Raw_Data!$AL$2:$AL$2552,Raw_Data!$A$2:$A$2552,$A34,Raw_Data!$D$2:$D$2552,"Meta (FB/IG)") | AH34: =IFERROR(AF34/AG34,"") | AI34: =SUMIFS(Raw_Data!$R$2:$R$2552,Raw_Data!$A$2:$A$2552,$A34,Raw_Data!$D$2:$D$2552,"TikTok") | AJ34: =SUMIFS(Raw_Data!$AL$2:$AL$2552,Raw_Data!$A$2:$A$2552,$A34,Raw_Data!$D$2:$D$2552,"TikTok") | AK34: =IFERROR(AI34/AJ34,"") | AL34: =SUMIFS(Raw_Data!$R$2:$R$2552,Raw_Data!$A$2:$A$2552,$A34,Raw_Data!$D$2:$D$2552,"X") | AM34: =SUMIFS(Raw_Data!$AL$2:$AL$2552,Raw_Data!$A$2:$A$2552,$A34,Raw_Data!$D$2:$D$2552,"X") | AN34: =IFERROR(AL34/AM34,"") | AO34: =SUMIFS(Raw_Data!$R$2:$R$2552,Raw_Data!$A$2:$A$2552,$A34,Raw_Data!$D$2:$D$2552,"Programmatic") | AP34: =SUMIFS(Raw_Data!$AL$2:$AL$2552,Raw_Data!$A$2:$A$2552,$A34,Raw_Data!$D$2:$D$2552,"Programmatic") | AQ34: =IFERROR(AO34/AP34,"")
A35: 46265 | B35: Mon | C35: Wk 36 | D35: =SUMIFS(Raw_Data!$R$2:$R$2552,Raw_Data!$A$2:$A$2552,$A35) | E35: =SUMIFS(Raw_Data!$S$2:$S$2552,Raw_Data!$A$2:$A$2552,$A35) | F35: =SUMIFS(Raw_Data!$T$2:$T$2552,Raw_Data!$A$2:$A$2552,$A35) | G35: =IFERROR(E35/F35,"") | H35: =SUMIFS(Raw_Data!$W$2:$W$2552,Raw_Data!$A$2:$A$2552,$A35) | I35: =IFERROR(H35/E35,"") | J35: =IFERROR(D35/H35,"") | K35: =IFERROR(D35/E35*1000,"") | L35: =SUMIFS(Raw_Data!$AA$2:$AA$2552,Raw_Data!$A$2:$A$2552,$A35) | M35: =IFERROR(L35/H35,"") | N35: =SUMIFS(Raw_Data!$AL$2:$AL$2552,Raw_Data!$A$2:$A$2552,$A35) | O35: =IFERROR(N35/L35,"") | P35: =IFERROR(D35/N35,"") | Q35: =SUMIFS(Raw_Data!$AO$2:$AO$2552,Raw_Data!$A$2:$A$2552,$A35) | R35: =IFERROR(Q35/N35,"") | S35: =IFERROR(D35/Q35,"") | T35: =SUMIFS(Raw_Data!$AR$2:$AR$2552,Raw_Data!$A$2:$A$2552,$A35) | U35: =SUMIFS(Raw_Data!$AS$2:$AS$2552,Raw_Data!$A$2:$A$2552,$A35) | V35: =N35+T35 | W35: =SUMIFS(Raw_Data!$AU$2:$AU$2552,Raw_Data!$A$2:$A$2552,$A35) | X35: =IFERROR(D35/$D$36,"") | Y35: =IFERROR(N35/$N$36,"") | Z35: =SUM($D$5:D35) | AA35: =SUM($N$5:N35) | AB35: =IFERROR(Z35/AA35,"") | AC35: =IFERROR(Z35/Assumptions!$C$10,"") | AD35: =31/31 | AE35: =IFERROR(AC35/AD35,"") | AF35: =SUMIFS(Raw_Data!$R$2:$R$2552,Raw_Data!$A$2:$A$2552,$A35,Raw_Data!$D$2:$D$2552,"Meta (FB/IG)") | AG35: =SUMIFS(Raw_Data!$AL$2:$AL$2552,Raw_Data!$A$2:$A$2552,$A35,Raw_Data!$D$2:$D$2552,"Meta (FB/IG)") | AH35: =IFERROR(AF35/AG35,"") | AI35: =SUMIFS(Raw_Data!$R$2:$R$2552,Raw_Data!$A$2:$A$2552,$A35,Raw_Data!$D$2:$D$2552,"TikTok") | AJ35: =SUMIFS(Raw_Data!$AL$2:$AL$2552,Raw_Data!$A$2:$A$2552,$A35,Raw_Data!$D$2:$D$2552,"TikTok") | AK35: =IFERROR(AI35/AJ35,"") | AL35: =SUMIFS(Raw_Data!$R$2:$R$2552,Raw_Data!$A$2:$A$2552,$A35,Raw_Data!$D$2:$D$2552,"X") | AM35: =SUMIFS(Raw_Data!$AL$2:$AL$2552,Raw_Data!$A$2:$A$2552,$A35,Raw_Data!$D$2:$D$2552,"X") | AN35: =IFERROR(AL35/AM35,"") | AO35: =SUMIFS(Raw_Data!$R$2:$R$2552,Raw_Data!$A$2:$A$2552,$A35,Raw_Data!$D$2:$D$2552,"Programmatic") | AP35: =SUMIFS(Raw_Data!$AL$2:$AL$2552,Raw_Data!$A$2:$A$2552,$A35,Raw_Data!$D$2:$D$2552,"Programmatic") | AQ35: =IFERROR(AO35/AP35,"")
A36: TOTAL | G36: =IFERROR(E36/F36,"") | I36: =IFERROR(H36/E36,"") | J36: =IFERROR(D36/H36,"") | K36: =IFERROR(D36/E36*1000,"") | M36: =IFERROR(L36/H36,"") | O36: =IFERROR(N36/L36,"") | P36: =IFERROR(D36/N36,"") | R36: =IFERROR(Q36/N36,"") | S36: =IFERROR(D36/Q36,"") | V36: =N36+T36 | X36: =IFERROR(D36/$D$36,"") | Y36: =IFERROR(N36/$N$36,"") | AF36: =SUM(AF5:AF35) | AG36: =SUM(AG5:AG35) | AH36: =IFERROR(AF36/AG36,"") | AI36: =SUM(AI5:AI35) | AJ36: =SUM(AJ5:AJ35) | AK36: =IFERROR(AI36/AJ36,"") | AL36: =SUM(AL5:AL35) | AM36: =SUM(AM5:AM35) | AN36: =IFERROR(AL36/AM36,"") | AO36: =SUM(AO5:AO35) | AP36: =SUM(AP5:AP35) | AQ36: =IFERROR(AO36/AP36,"")

Sheet Budget_Forecast
A1: Scope | B1: Planned Monthly Budget (ZAR) | C1: Planned Daily Spend | D1: Actual Spend | E1: Actual Daily Spend | F1: Spend Variance | G1: Required Run-Rate to Target | H1: Actual Bookings | I1: Actual CPL | J1: Actual Qualified Leads | K1: Qualified Rate | L1: Forecast Bookings | M1: Forecast CPL | N1: Forecast Qualified Leads | O1: Reallocation Recommendation | P1: Recommended Next-Month Budget
A2: Meta | B2: 168000 | C2: 5419.3548 | D2: 168000 | E2: 5419.3548 | F2: -5.8207661e-11 | G2: 0 | H2: 608 | I2: 276.31579 | J2: 397 | K2: 0.65296053 | L2: 832.38095 | M2: 276.31579 | N2: 543.5119 | O2: Increase: efficient conversion path | P2: 230000
A3: TikTok | B3: 84000 | C3: 2709.6774 | D3: 84000 | E3: 2709.6774 | F3: 0 | G3: 0 | H3: 174 | I3: 482.75862 | J3: 95 | K3: 0.54597701 | L3: 174 | M3: 482.75862 | N3: 95 | O3: Hold: monitor quality before scaling | P3: 84000
A4: Programmatic | B4: 65305.33 | C4: 2106.6235 | D4: 65305.33 | E4: 2106.6235 | F4: 4.3655746e-11 | G4: 0 | H4: 93 | I4: 702.20785 | J4: 48 | K4: 0.51612903 | L4: 69.779909 | M4: 702.20785 | N4: 36.015437 | O4: Reduce/reframe: weaker CPL or unmapped role | P4: 49000
A5: YouTube | B5: 34694.67 | C5: 1119.1829 | D5: 34694.67 | E5: 1119.1829 | F5: 2.1827873e-11 | G5: 0 | H5: 41 | I5: 846.21146 | J5: 23 | K5: 0.56097561 | L5: 27.179967 | M5: 846.21146 | N5: 15.247299 | O5: Reduce/reframe: weaker CPL or unmapped role | P5: 23000
A6: X | B6: 48000 | C6: 1548.3871 | D6: 48000 | E6: 1548.3871 | F6: -7.2759576e-12 | G6: 0 | H6: 71 | I6: 676.05634 | J6: 47 | K6: 0.66197183 | L6: 20.708333 | M6: 676.05634 | N6: 13.708333 | O6: Reduce/reframe: weaker CPL or unmapped role | P6: 14000
A7: Total | B7: 400000 | C7: 12903.226 | D7: 400000 | E7: 12903.226 | F7: 0 | G7: 0 | H7: 987 | I7: 405.26849 | J7: 610 | K7: 0.61803445 | L7: 1124.0492 | M7: 355.85632 | N7: 703.48297 | O7: Portfolio total | P7: 400000

Sheet Channel_Detail
A1: Channel Detail
A2: Each channel cut by week, model and audience strategy. Every row is a live SUMIFS over Raw_Data.
A4: CHANNEL x WEEK
A5: Channel | B5: ISO Week | C5: Spend (ZAR) | D5: Impressions | E5: Reach (sum of daily) | F5: Avg Daily Frequency | G5: Link Clicks | H5: CTR (Link) | I5: CPC (Link) | J5: CPM | K5: Landing Page Views | L5: LPV Rate | M5: Test Drive Bookings | N5: CVR (Booking / LPV) | O5: CPL (Cost / Booking) | P5: Qualified Leads | Q5: Qualified Rate | R5: Cost per Qualified Lead | S5: View-Through Conv. | T5: Assisted Conv. | U5: Total Attributed Conv. | V5: Est. Revenue Pipeline (ZAR) | W5: % of Spend | X5: % of Bookings
A6: Meta (FB/IG) | B6: Wk 31 | C6: =SUMIFS(Raw_Data!$R$2:$R$2552,Raw_Data!$D$2:$D$2552,$A6,Raw_Data!$B$2:$B$2552,$B6) | D6: =SUMIFS(Raw_Data!$S$2:$S$2552,Raw_Data!$D$2:$D$2552,$A6,Raw_Data!$B$2:$B$2552,$B6) | E6: =SUMIFS(Raw_Data!$T$2:$T$2552,Raw_Data!$D$2:$D$2552,$A6,Raw_Data!$B$2:$B$2552,$B6) | F6: =IFERROR(D6/E6,"") | G6: =SUMIFS(Raw_Data!$W$2:$W$2552,Raw_Data!$D$2:$D$2552,$A6,Raw_Data!$B$2:$B$2552,$B6) | H6: =IFERROR(G6/D6,"") | I6: =IFERROR(C6/G6,"") | J6: =IFERROR(C6/D6*1000,"") | K6: =SUMIFS(Raw_Data!$AA$2:$AA$2552,Raw_Data!$D$2:$D$2552,$A6,Raw_Data!$B$2:$B$2552,$B6) | L6: =IFERROR(K6/G6,"") | M6: =SUMIFS(Raw_Data!$AL$2:$AL$2552,Raw_Data!$D$2:$D$2552,$A6,Raw_Data!$B$2:$B$2552,$B6) | N6: =IFERROR(M6/K6,"") | O6: =IFERROR(C6/M6,"") | P6: =SUMIFS(Raw_Data!$AO$2:$AO$2552,Raw_Data!$D$2:$D$2552,$A6,Raw_Data!$B$2:$B$2552,$B6) | Q6: =IFERROR(P6/M6,"") | R6: =IFERROR(C6/P6,"") | S6: =SUMIFS(Raw_Data!$AR$2:$AR$2552,Raw_Data!$D$2:$D$2552,$A6,Raw_Data!$B$2:$B$2552,$B6) | T6: =SUMIFS(Raw_Data!$AS$2:$AS$2552,Raw_Data!$D$2:$D$2552,$A6,Raw_Data!$B$2:$B$2552,$B6) | U6: =M6+S6 | V6: =SUMIFS(Raw_Data!$AU$2:$AU$2552,Raw_Data!$D$2:$D$2552,$A6,Raw_Data!$B$2:$B$2552,$B6) | W6: =IFERROR(C6/Summary!$B$17,"") | X6: =IFERROR(M6/Summary!$L$17,"")
A7: Meta (FB/IG) | B7: Wk 32 | C7: =SUMIFS(Raw_Data!$R$2:$R$2552,Raw_Data!$D$2:$D$2552,$A7,Raw_Data!$B$2:$B$2552,$B7) | D7: =SUMIFS(Raw_Data!$S$2:$S$2552,Raw_Data!$D$2:$D$2552,$A7,Raw_Data!$B$2:$B$2552,$B7) | E7: =SUMIFS(Raw_Data!$T$2:$T$2552,Raw_Data!$D$2:$D$2552,$A7,Raw_Data!$B$2:$B$2552,$B7) | F7: =IFERROR(D7/E7,"") | G7: =SUMIFS(Raw_Data!$W$2:$W$2552,Raw_Data!$D$2:$D$2552,$A7,Raw_Data!$B$2:$B$2552,$B7) | H7: =IFERROR(G7/D7,"") | I7: =IFERROR(C7/G7,"") | J7: =IFERROR(C7/D7*1000,"") | K7: =SUMIFS(Raw_Data!$AA$2:$AA$2552,Raw_Data!$D$2:$D$2552,$A7,Raw_Data!$B$2:$B$2552,$B7) | L7: =IFERROR(K7/G7,"") | M7: =SUMIFS(Raw_Data!$AL$2:$AL$2552,Raw_Data!$D$2:$D$2552,$A7,Raw_Data!$B$2:$B$2552,$B7) | N7: =IFERROR(M7/K7,"") | O7: =IFERROR(C7/M7,"") | P7: =SUMIFS(Raw_Data!$AO$2:$AO$2552,Raw_Data!$D$2:$D$2552,$A7,Raw_Data!$B$2:$B$2552,$B7) | Q7: =IFERROR(P7/M7,"") | R7: =IFERROR(C7/P7,"") | S7: =SUMIFS(Raw_Data!$AR$2:$AR$2552,Raw_Data!$D$2:$D$2552,$A7,Raw_Data!$B$2:$B$2552,$B7) | T7: =SUMIFS(Raw_Data!$AS$2:$AS$2552,Raw_Data!$D$2:$D$2552,$A7,Raw_Data!$B$2:$B$2552,$B7) | U7: =M7+S7 | V7: =SUMIFS(Raw_Data!$AU$2:$AU$2552,Raw_Data!$D$2:$D$2552,$A7,Raw_Data!$B$2:$B$2552,$B7) | W7: =IFERROR(C7/Summary!$B$17,"") | X7: =IFERROR(M7/Summary!$L$17,"")
A8: Meta (FB/IG) | B8: Wk 33 | C8: =SUMIFS(Raw_Data!$R$2:$R$2552,Raw_Data!$D$2:$D$2552,$A8,Raw_Data!$B$2:$B$2552,$B8) | D8: =SUMIFS(Raw_Data!$S$2:$S$2552,Raw_Data!$D$2:$D$2552,$A8,Raw_Data!$B$2:$B$2552,$B8) | E8: =SUMIFS(Raw_Data!$T$2:$T$2552,Raw_Data!$D$2:$D$2552,$A8,Raw_Data!$B$2:$B$2552,$B8) | F8: =IFERROR(D8/E8,"") | G8: =SUMIFS(Raw_Data!$W$2:$W$2552,Raw_Data!$D$2:$D$2552,$A8,Raw_Data!$B$2:$B$2552,$B8) | H8: =IFERROR(G8/D8,"") | I8: =IFERROR(C8/G8,"") | J8: =IFERROR(C8/D8*1000,"") | K8: =SUMIFS(Raw_Data!$AA$2:$AA$2552,Raw_Data!$D$2:$D$2552,$A8,Raw_Data!$B$2:$B$2552,$B8) | L8: =IFERROR(K8/G8,"") | M8: =SUMIFS(Raw_Data!$AL$2:$AL$2552,Raw_Data!$D$2:$D$2552,$A8,Raw_Data!$B$2:$B$2552,$B8) | N8: =IFERROR(M8/K8,"") | O8: =IFERROR(C8/M8,"") | P8: =SUMIFS(Raw_Data!$AO$2:$AO$2552,Raw_Data!$D$2:$D$2552,$A8,Raw_Data!$B$2:$B$2552,$B8) | Q8: =IFERROR(P8/M8,"") | R8: =IFERROR(C8/P8,"") | S8: =SUMIFS(Raw_Data!$AR$2:$AR$2552,Raw_Data!$D$2:$D$2552,$A8,Raw_Data!$B$2:$B$2552,$B8) | T8: =SUMIFS(Raw_Data!$AS$2:$AS$2552,Raw_Data!$D$2:$D$2552,$A8,Raw_Data!$B$2:$B$2552,$B8) | U8: =M8+S8 | V8: =SUMIFS(Raw_Data!$AU$2:$AU$2552,Raw_Data!$D$2:$D$2552,$A8,Raw_Data!$B$2:$B$2552,$B8) | W8: =IFERROR(C8/Summary!$B$17,"") | X8: =IFERROR(M8/Summary!$L$17,"")
A9: Meta (FB/IG) | B9: Wk 34 | C9: =SUMIFS(Raw_Data!$R$2:$R$2552,Raw_Data!$D$2:$D$2552,$A9,Raw_Data!$B$2:$B$2552,$B9) | D9: =SUMIFS(Raw_Data!$S$2:$S$2552,Raw_Data!$D$2:$D$2552,$A9,Raw_Data!$B$2:$B$2552,$B9) | E9: =SUMIFS(Raw_Data!$T$2:$T$2552,Raw_Data!$D$2:$D$2552,$A9,Raw_Data!$B$2:$B$2552,$B9) | F9: =IFERROR(D9/E9,"") | G9: =SUMIFS(Raw_Data!$W$2:$W$2552,Raw_Data!$D$2:$D$2552,$A9,Raw_Data!$B$2:$B$2552,$B9) | H9: =IFERROR(G9/D9,"") | I9: =IFERROR(C9/G9,"") | J9: =IFERROR(C9/D9*1000,"") | K9: =SUMIFS(Raw_Data!$AA$2:$AA$2552,Raw_Data!$D$2:$D$2552,$A9,Raw_Data!$B$2:$B$2552,$B9) | L9: =IFERROR(K9/G9,"") | M9: =SUMIFS(Raw_Data!$AL$2:$AL$2552,Raw_Data!$D$2:$D$2552,$A9,Raw_Data!$B$2:$B$2552,$B9) | N9: =IFERROR(M9/K9,"") | O9: =IFERROR(C9/M9,"") | P9: =SUMIFS(Raw_Data!$AO$2:$AO$2552,Raw_Data!$D$2:$D$2552,$A9,Raw_Data!$B$2:$B$2552,$B9) | Q9: =IFERROR(P9/M9,"") | R9: =IFERROR(C9/P9,"") | S9: =SUMIFS(Raw_Data!$AR$2:$AR$2552,Raw_Data!$D$2:$D$2552,$A9,Raw_Data!$B$2:$B$2552,$B9) | T9: =SUMIFS(Raw_Data!$AS$2:$AS$2552,Raw_Data!$D$2:$D$2552,$A9,Raw_Data!$B$2:$B$2552,$B9) | U9: =M9+S9 | V9: =SUMIFS(Raw_Data!$AU$2:$AU$2552,Raw_Data!$D$2:$D$2552,$A9,Raw_Data!$B$2:$B$2552,$B9) | W9: =IFERROR(C9/Summary!$B$17,"") | X9: =IFERROR(M9/Summary!$L$17,"")
A10: Meta (FB/IG) | B10: Wk 35 | C10: =SUMIFS(Raw_Data!$R$2:$R$2552,Raw_Data!$D$2:$D$2552,$A10,Raw_Data!$B$2:$B$2552,$B10) | D10: =SUMIFS(Raw_Data!$S$2:$S$2552,Raw_Data!$D$2:$D$2552,$A10,Raw_Data!$B$2:$B$2552,$B10) | E10: =SUMIFS(Raw_Data!$T$2:$T$2552,Raw_Data!$D$2:$D$2552,$A10,Raw_Data!$B$2:$B$2552,$B10) | F10: =IFERROR(D10/E10,"") | G10: =SUMIFS(Raw_Data!$W$2:$W$2552,Raw_Data!$D$2:$D$2552,$A10,Raw_Data!$B$2:$B$2552,$B10) | H10: =IFERROR(G10/D10,"") | I10: =IFERROR(C10/G10,"") | J10: =IFERROR(C10/D10*1000,"") | K10: =SUMIFS(Raw_Data!$AA$2:$AA$2552,Raw_Data!$D$2:$D$2552,$A10,Raw_Data!$B$2:$B$2552,$B10) | L10: =IFERROR(K10/G10,"") | M10: =SUMIFS(Raw_Data!$AL$2:$AL$2552,Raw_Data!$D$2:$D$2552,$A10,Raw_Data!$B$2:$B$2552,$B10) | N10: =IFERROR(M10/K10,"") | O10: =IFERROR(C10/M10,"") | P10: =SUMIFS(Raw_Data!$AO$2:$AO$2552,Raw_Data!$D$2:$D$2552,$A10,Raw_Data!$B$2:$B$2552,$B10) | Q10: =IFERROR(P10/M10,"") | R10: =IFERROR(C10/P10,"") | S10: =SUMIFS(Raw_Data!$AR$2:$AR$2552,Raw_Data!$D$2:$D$2552,$A10,Raw_Data!$B$2:$B$2552,$B10) | T10: =SUMIFS(Raw_Data!$AS$2:$AS$2552,Raw_Data!$D$2:$D$2552,$A10,Raw_Data!$B$2:$B$2552,$B10) | U10: =M10+S10 | V10: =SUMIFS(Raw_Data!$AU$2:$AU$2552,Raw_Data!$D$2:$D$2552,$A10,Raw_Data!$B$2:$B$2552,$B10) | W10: =IFERROR(C10/Summary!$B$17,"") | X10: =IFERROR(M10/Summary!$L$17,"")
A11: Meta (FB/IG) | B11: Wk 36 | C11: =SUMIFS(Raw_Data!$R$2:$R$2552,Raw_Data!$D$2:$D$2552,$A11,Raw_Data!$B$2:$B$2552,$B11) | D11: =SUMIFS(Raw_Data!$S$2:$S$2552,Raw_Data!$D$2:$D$2552,$A11,Raw_Data!$B$2:$B$2552,$B11) | E11: =SUMIFS(Raw_Data!$T$2:$T$2552,Raw_Data!$D$2:$D$2552,$A11,Raw_Data!$B$2:$B$2552,$B11) | F11: =IFERROR(D11/E11,"") | G11: =SUMIFS(Raw_Data!$W$2:$W$2552,Raw_Data!$D$2:$D$2552,$A11,Raw_Data!$B$2:$B$2552,$B11) | H11: =IFERROR(G11/D11,"") | I11: =IFERROR(C11/G11,"") | J11: =IFERROR(C11/D11*1000,"") | K11: =SUMIFS(Raw_Data!$AA$2:$AA$2552,Raw_Data!$D$2:$D$2552,$A11,Raw_Data!$B$2:$B$2552,$B11) | L11: =IFERROR(K11/G11,"") | M11: =SUMIFS(Raw_Data!$AL$2:$AL$2552,Raw_Data!$D$2:$D$2552,$A11,Raw_Data!$B$2:$B$2552,$B11) | N11: =IFERROR(M11/K11,"") | O11: =IFERROR(C11/M11,"") | P11: =SUMIFS(Raw_Data!$AO$2:$AO$2552,Raw_Data!$D$2:$D$2552,$A11,Raw_Data!$B$2:$B$2552,$B11) | Q11: =IFERROR(P11/M11,"") | R11: =IFERROR(C11/P11,"") | S11: =SUMIFS(Raw_Data!$AR$2:$AR$2552,Raw_Data!$D$2:$D$2552,$A11,Raw_Data!$B$2:$B$2552,$B11) | T11: =SUMIFS(Raw_Data!$AS$2:$AS$2552,Raw_Data!$D$2:$D$2552,$A11,Raw_Data!$B$2:$B$2552,$B11) | U11: =M11+S11 | V11: =SUMIFS(Raw_Data!$AU$2:$AU$2552,Raw_Data!$D$2:$D$2552,$A11,Raw_Data!$B$2:$B$2552,$B11) | W11: =IFERROR(C11/Summary!$B$17,"") | X11: =IFERROR(M11/Summary!$L$17,"")
A12: TikTok | B12: Wk 31 | C12: =SUMIFS(Raw_Data!$R$2:$R$2552,Raw_Data!$D$2:$D$2552,$A12,Raw_Data!$B$2:$B$2552,$B12) | D12: =SUMIFS(Raw_Data!$S$2:$S$2552,Raw_Data!$D$2:$D$2552,$A12,Raw_Data!$B$2:$B$2552,$B12) | E12: =SUMIFS(Raw_Data!$T$2:$T$2552,Raw_Data!$D$2:$D$2552,$A12,Raw_Data!$B$2:$B$2552,$B12) | F12: =IFERROR(D12/E12,"") | G12: =SUMIFS(Raw_Data!$W$2:$W$2552,Raw_Data!$D$2:$D$2552,$A12,Raw_Data!$B$2:$B$2552,$B12) | H12: =IFERROR(G12/D12,"") | I12: =IFERROR(C12/G12,"") | J12: =IFERROR(C12/D12*1000,"") | K12: =SUMIFS(Raw_Data!$AA$2:$AA$2552,Raw_Data!$D$2:$D$2552,$A12,Raw_Data!$B$2:$B$2552,$B12) | L12: =IFERROR(K12/G12,"") | M12: =SUMIFS(Raw_Data!$AL$2:$AL$2552,Raw_Data!$D$2:$D$2552,$A12,Raw_Data!$B$2:$B$2552,$B12) | N12: =IFERROR(M12/K12,"") | O12: =IFERROR(C12/M12,"") | P12: =SUMIFS(Raw_Data!$AO$2:$AO$2552,Raw_Data!$D$2:$D$2552,$A12,Raw_Data!$B$2:$B$2552,$B12) | Q12: =IFERROR(P12/M12,"") | R12: =IFERROR(C12/P12,"") | S12: =SUMIFS(Raw_Data!$AR$2:$AR$2552,Raw_Data!$D$2:$D$2552,$A12,Raw_Data!$B$2:$B$2552,$B12) | T12: =SUMIFS(Raw_Data!$AS$2:$AS$2552,Raw_Data!$D$2:$D$2552,$A12,Raw_Data!$B$2:$B$2552,$B12) | U12: =M12+S12 | V12: =SUMIFS(Raw_Data!$AU$2:$AU$2552,Raw_Data!$D$2:$D$2552,$A12,Raw_Data!$B$2:$B$2552,$B12) | W12: =IFERROR(C12/Summary!$B$17,"") | X12: =IFERROR(M12/Summary!$L$17,"")
A13: TikTok | B13: Wk 32 | C13: =SUMIFS(Raw_Data!$R$2:$R$2552,Raw_Data!$D$2:$D$2552,$A13,Raw_Data!$B$2:$B$2552,$B13) | D13: =SUMIFS(Raw_Data!$S$2:$S$2552,Raw_Data!$D$2:$D$2552,$A13,Raw_Data!$B$2:$B$2552,$B13) | E13: =SUMIFS(Raw_Data!$T$2:$T$2552,Raw_Data!$D$2:$D$2552,$A13,Raw_Data!$B$2:$B$2552,$B13) | F13: =IFERROR(D13/E13,"") | G13: =SUMIFS(Raw_Data!$W$2:$W$2552,Raw_Data!$D$2:$D$2552,$A13,Raw_Data!$B$2:$B$2552,$B13) | H13: =IFERROR(G13/D13,"") | I13: =IFERROR(C13/G13,"") | J13: =IFERROR(C13/D13*1000,"") | K13: =SUMIFS(Raw_Data!$AA$2:$AA$2552,Raw_Data!$D$2:$D$2552,$A13,Raw_Data!$B$2:$B$2552,$B13) | L13: =IFERROR(K13/G13,"") | M13: =SUMIFS(Raw_Data!$AL$2:$AL$2552,Raw_Data!$D$2:$D$2552,$A13,Raw_Data!$B$2:$B$2552,$B13) | N13: =IFERROR(M13/K13,"") | O13: =IFERROR(C13/M13,"") | P13: =SUMIFS(Raw_Data!$AO$2:$AO$2552,Raw_Data!$D$2:$D$2552,$A13,Raw_Data!$B$2:$B$2552,$B13) | Q13: =IFERROR(P13/M13,"") | R13: =IFERROR(C13/P13,"") | S13: =SUMIFS(Raw_Data!$AR$2:$AR$2552,Raw_Data!$D$2:$D$2552,$A13,Raw_Data!$B$2:$B$2552,$B13) | T13: =SUMIFS(Raw_Data!$AS$2:$AS$2552,Raw_Data!$D$2:$D$2552,$A13,Raw_Data!$B$2:$B$2552,$B13) | U13: =M13+S13 | V13: =SUMIFS(Raw_Data!$AU$2:$AU$2552,Raw_Data!$D$2:$D$2552,$A13,Raw_Data!$B$2:$B$2552,$B13) | W13: =IFERROR(C13/Summary!$B$17,"") | X13: =IFERROR(M13/Summary!$L$17,"")
A14: TikTok | B14: Wk 33 | C14: =SUMIFS(Raw_Data!$R$2:$R$2552,Raw_Data!$D$2:$D$2552,$A14,Raw_Data!$B$2:$B$2552,$B14) | D14: =SUMIFS(Raw_Data!$S$2:$S$2552,Raw_Data!$D$2:$D$2552,$A14,Raw_Data!$B$2:$B$2552,$B14) | E14: =SUMIFS(Raw_Data!$T$2:$T$2552,Raw_Data!$D$2:$D$2552,$A14,Raw_Data!$B$2:$B$2552,$B14) | F14: =IFERROR(D14/E14,"") | G14: =SUMIFS(Raw_Data!$W$2:$W$2552,Raw_Data!$D$2:$D$2552,$A14,Raw_Data!$B$2:$B$2552,$B14) | H14: =IFERROR(G14/D14,"") | I14: =IFERROR(C14/G14,"") | J14: =IFERROR(C14/D14*1000,"") | K14: =SUMIFS(Raw_Data!$AA$2:$AA$2552,Raw_Data!$D$2:$D$2552,$A14,Raw_Data!$B$2:$B$2552,$B14) | L14: =IFERROR(K14/G14,"") | M14: =SUMIFS(Raw_Data!$AL$2:$AL$2552,Raw_Data!$D$2:$D$2552,$A14,Raw_Data!$B$2:$B$2552,$B14) | N14: =IFERROR(M14/K14,"") | O14: =IFERROR(C14/M14,"") | P14: =SUMIFS(Raw_Data!$AO$2:$AO$2552,Raw_Data!$D$2:$D$2552,$A14,Raw_Data!$B$2:$B$2552,$B14) | Q14: =IFERROR(P14/M14,"") | R14: =IFERROR(C14/P14,"") | S14: =SUMIFS(Raw_Data!$AR$2:$AR$2552,Raw_Data!$D$2:$D$2552,$A14,Raw_Data!$B$2:$B$2552,$B14) | T14: =SUMIFS(Raw_Data!$AS$2:$AS$2552,Raw_Data!$D$2:$D$2552,$A14,Raw_Data!$B$2:$B$2552,$B14) | U14: =M14+S14 | V14: =SUMIFS(Raw_Data!$AU$2:$AU$2552,Raw_Data!$D$2:$D$2552,$A14,Raw_Data!$B$2:$B$2552,$B14) | W14: =IFERROR(C14/Summary!$B$17,"") | X14: =IFERROR(M14/Summary!$L$17,"")
A15: TikTok | B15: Wk 34 | C15: =SUMIFS(Raw_Data!$R$2:$R$2552,Raw_Data!$D$2:$D$2552,$A15,Raw_Data!$B$2:$B$2552,$B15) | D15: =SUMIFS(Raw_Data!$S$2:$S$2552,Raw_Data!$D$2:$D$2552,$A15,Raw_Data!$B$2:$B$2552,$B15) | E15: =SUMIFS(Raw_Data!$T$2:$T$2552,Raw_Data!$D$2:$D$2552,$A15,Raw_Data!$B$2:$B$2552,$B15) | F15: =IFERROR(D15/E15,"") | G15: =SUMIFS(Raw_Data!$W$2:$W$2552,Raw_Data!$D$2:$D$2552,$A15,Raw_Data!$B$2:$B$2552,$B15) | H15: =IFERROR(G15/D15,"") | I15: =IFERROR(C15/G15,"") | J15: =IFERROR(C15/D15*1000,"") | K15: =SUMIFS(Raw_Data!$AA$2:$AA$2552,Raw_Data!$D$2:$D$2552,$A15,Raw_Data!$B$2:$B$2552,$B15) | L15: =IFERROR(K15/G15,"") | M15: =SUMIFS(Raw_Data!$AL$2:$AL$2552,Raw_Data!$D$2:$D$2552,$A15,Raw_Data!$B$2:$B$2552,$B15) | N15: =IFERROR(M15/K15,"") | O15: =IFERROR(C15/M15,"") | P15: =SUMIFS(Raw_Data!$AO$2:$AO$2552,Raw_Data!$D$2:$D$2552,$A15,Raw_Data!$B$2:$B$2552,$B15) | Q15: =IFERROR(P15/M15,"") | R15: =IFERROR(C15/P15,"") | S15: =SUMIFS(Raw_Data!$AR$2:$AR$2552,Raw_Data!$D$2:$D$2552,$A15,Raw_Data!$B$2:$B$2552,$B15) | T15: =SUMIFS(Raw_Data!$AS$2:$AS$2552,Raw_Data!$D$2:$D$2552,$A15,Raw_Data!$B$2:$B$2552,$B15) | U15: =M15+S15 | V15: =SUMIFS(Raw_Data!$AU$2:$AU$2552,Raw_Data!$D$2:$D$2552,$A15,Raw_Data!$B$2:$B$2552,$B15) | W15: =IFERROR(C15/Summary!$B$17,"") | X15: =IFERROR(M15/Summary!$L$17,"")
A16: TikTok | B16: Wk 35 | C16: =SUMIFS(Raw_Data!$R$2:$R$2552,Raw_Data!$D$2:$D$2552,$A16,Raw_Data!$B$2:$B$2552,$B16) | D16: =SUMIFS(Raw_Data!$S$2:$S$2552,Raw_Data!$D$2:$D$2552,$A16,Raw_Data!$B$2:$B$2552,$B16) | E16: =SUMIFS(Raw_Data!$T$2:$T$2552,Raw_Data!$D$2:$D$2552,$A16,Raw_Data!$B$2:$B$2552,$B16) | F16: =IFERROR(D16/E16,"") | G16: =SUMIFS(Raw_Data!$W$2:$W$2552,Raw_Data!$D$2:$D$2552,$A16,Raw_Data!$B$2:$B$2552,$B16) | H16: =IFERROR(G16/D16,"") | I16: =IFERROR(C16/G16,"") | J16: =IFERROR(C16/D16*1000,"") | K16: =SUMIFS(Raw_Data!$AA$2:$AA$2552,Raw_Data!$D$2:$D$2552,$A16,Raw_Data!$B$2:$B$2552,$B16) | L16: =IFERROR(K16/G16,"") | M16: =SUMIFS(Raw_Data!$AL$2:$AL$2552,Raw_Data!$D$2:$D$2552,$A16,Raw_Data!$B$2:$B$2552,$B16) | N16: =IFERROR(M16/K16,"") | O16: =IFERROR(C16/M16,"") | P16: =SUMIFS(Raw_Data!$AO$2:$AO$2552,Raw_Data!$D$2:$D$2552,$A16,Raw_Data!$B$2:$B$2552,$B16) | Q16: =IFERROR(P16/M16,"") | R16: =IFERROR(C16/P16,"") | S16: =SUMIFS(Raw_Data!$AR$2:$AR$2552,Raw_Data!$D$2:$D$2552,$A16,Raw_Data!$B$2:$B$2552,$B16) | T16: =SUMIFS(Raw_Data!$AS$2:$AS$2552,Raw_Data!$D$2:$D$2552,$A16,Raw_Data!$B$2:$B$2552,$B16) | U16: =M16+S16 | V16: =SUMIFS(Raw_Data!$AU$2:$AU$2552,Raw_Data!$D$2:$D$2552,$A16,Raw_Data!$B$2:$B$2552,$B16) | W16: =IFERROR(C16/Summary!$B$17,"") | X16: =IFERROR(M16/Summary!$L$17,"")
A17: TikTok | B17: Wk 36 | C17: =SUMIFS(Raw_Data!$R$2:$R$2552,Raw_Data!$D$2:$D$2552,$A17,Raw_Data!$B$2:$B$2552,$B17) | D17: =SUMIFS(Raw_Data!$S$2:$S$2552,Raw_Data!$D$2:$D$2552,$A17,Raw_Data!$B$2:$B$2552,$B17) | E17: =SUMIFS(Raw_Data!$T$2:$T$2552,Raw_Data!$D$2:$D$2552,$A17,Raw_Data!$B$2:$B$2552,$B17) | F17: =IFERROR(D17/E17,"") | G17: =SUMIFS(Raw_Data!$W$2:$W$2552,Raw_Data!$D$2:$D$2552,$A17,Raw_Data!$B$2:$B$2552,$B17) | H17: =IFERROR(G17/D17,"") | I17: =IFERROR(C17/G17,"") | J17: =IFERROR(C17/D17*1000,"") | K17: =SUMIFS(Raw_Data!$AA$2:$AA$2552,Raw_Data!$D$2:$D$2552,$A17,Raw_Data!$B$2:$B$2552,$B17) | L17: =IFERROR(K17/G17,"") | M17: =SUMIFS(Raw_Data!$AL$2:$AL$2552,Raw_Data!$D$2:$D$2552,$A17,Raw_Data!$B$2:$B$2552,$B17) | N17: =IFERROR(M17/K17,"") | O17: =IFERROR(C17/M17,"") | P17: =SUMIFS(Raw_Data!$AO$2:$AO$2552,Raw_Data!$D$2:$D$2552,$A17,Raw_Data!$B$2:$B$2552,$B17) | Q17: =IFERROR(P17/M17,"") | R17: =IFERROR(C17/P17,"") | S17: =SUMIFS(Raw_Data!$AR$2:$AR$2552,Raw_Data!$D$2:$D$2552,$A17,Raw_Data!$B$2:$B$2552,$B17) | T17: =SUMIFS(Raw_Data!$AS$2:$AS$2552,Raw_Data!$D$2:$D$2552,$A17,Raw_Data!$B$2:$B$2552,$B17) | U17: =M17+S17 | V17: =SUMIFS(Raw_Data!$AU$2:$AU$2552,Raw_Data!$D$2:$D$2552,$A17,Raw_Data!$B$2:$B$2552,$B17) | W17: =IFERROR(C17/Summary!$B$17,"") | X17: =IFERROR(M17/Summary!$L$17,"")
... A29: Programmatic | B29: Wk 36 | C29: =SUMIFS(Raw_Data!$R$2:$R$2552,Raw_Data!$D$2:$D$2552,$A29,Raw_Data!$B$2:$B$2552,$B29) | D29: =SUMIFS(Raw_Data!$S$2:$S$2552,Raw_Data!$D$2:$D$2552,$A29,Raw_Data!$B$2:$B$2552,$B29) | E29: =SUMIFS(Raw_Data!$T$2:$T$2552,Raw_Data!$D$2:$D$2552,$A29,Raw_Data!$B$2:$B$2552,$B29) | F29: =IFERROR(D29/E29,"") | G29: =SUMIFS(Raw_Data!$W$2:$W$2552,Raw_Data!$D$2:$D$2552,$A29,Raw_Data!$B$2:$B$2552,$B29) | H29: =IFERROR(G29/D29,"") | I29: =IFERROR(C29/G29,"") | J29: =IFERROR(C29/D29*1000,"") | K29: =SUMIFS(Raw_Data!$AA$2:$AA$2552,Raw_Data!$D$2:$D$2552,$A29,Raw_Data!$B$2:$B$2552,$B29) | L29: =IFERROR(K29/G29,"") | M29: =SUMIFS(Raw_Data!$AL$2:$AL$2552,Raw_Data!$D$2:$D$2552,$A29,Raw_Data!$B$2:$B$2552,$B29) | N29: =IFERROR(M29/K29,"") | O29: =IFERROR(C29/M29,"") | P29: =SUMIFS(Raw_Data!$AO$2:$AO$2552,Raw_Data!$D$2:$D$2552,$A29,Raw_Data!$B$2:$B$2552,$B29) | Q29: =IFERROR(P29/M29,"") | R29: =IFERROR(C29/P29,"") | S29: =SUMIFS(Raw_Data!$AR$2:$AR$2552,Raw_Data!$D$2:$D$2552,$A29,Raw_Data!$B$2:$B$2552,$B29) | T29: =SUMIFS(Raw_Data!$AS$2:$AS$2552,Raw_Data!$D$2:$D$2552,$A29,Raw_Data!$B$2:$B$2552,$B29) | U29: =M29+S29 | V29: =SUMIFS(Raw_Data!$AU$2:$AU$2552,Raw_Data!$D$2:$D$2552,$A29,Raw_Data!$B$2:$B$2552,$B29) | W29: =IFERROR(C29/Summary!$B$17,"") | X29: =IFERROR(M29/Summary!$L$17,"")
A30: TOTAL | F30: =IFERROR(D30/E30,"") | H30: =IFERROR(G30/D30,"") | I30: =IFERROR(C30/G30,"") | J30: =IFERROR(C30/D30*1000,"") | L30: =IFERROR(K30/G30,"") | N30: =IFERROR(M30/K30,"") | O30: =IFERROR(C30/M30,"") | Q30: =IFERROR(P30/M30,"") | R30: =IFERROR(C30/P30,"") | U30: =M30+S30 | W30: =IFERROR(C30/Summary!$B$17,"") | X30: =IFERROR(M30/Summary!$L$17,"")
A33: CHANNEL x MODEL
A34: Channel | B34: Model | C34: Spend (ZAR) | D34: Impressions | E34: Reach (sum of daily) | F34: Avg Daily Frequency | G34: Link Clicks | H34: CTR (Link) | I34: CPC (Link) | J34: CPM | K34: Landing Page Views | L34: LPV Rate | M34: Test Drive Bookings | N34: CVR (Booking / LPV) | O34: CPL (Cost / Booking) | P34: Qualified Leads | Q34: Qualified Rate | R34: Cost per Qualified Lead | S34: View-Through Conv. | T34: Assisted Conv. | U34: Total Attributed Conv. | V34: Est. Revenue Pipeline (ZAR) | W34: % of Spend | X34: % of Bookings
A35: Meta (FB/IG) | B35: AMUR | C35: =SUMIFS(Raw_Data!$R$2:$R$2552,Raw_Data!$D$2:$D$2552,$A35,Raw_Data!$H$2:$H$2552,$B35) | D35: =SUMIFS(Raw_Data!$S$2:$S$2552,Raw_Data!$D$2:$D$2552,$A35,Raw_Data!$H$2:$H$2552,$B35) | E35: =SUMIFS(Raw_Data!$T$2:$T$2552,Raw_Data!$D$2:$D$2552,$A35,Raw_Data!$H$2:$H$2552,$B35) | F35: =IFERROR(D35/E35,"") | G35: =SUMIFS(Raw_Data!$W$2:$W$2552,Raw_Data!$D$2:$D$2552,$A35,Raw_Data!$H$2:$H$2552,$B35) | H35: =IFERROR(G35/D35,"") | I35: =IFERROR(C35/G35,"") | J35: =IFERROR(C35/D35*1000,"") | K35: =SUMIFS(Raw_Data!$AA$2:$AA$2552,Raw_Data!$D$2:$D$2552,$A35,Raw_Data!$H$2:$H$2552,$B35) | L35: =IFERROR(K35/G35,"") | M35: =SUMIFS(Raw_Data!$AL$2:$AL$2552,Raw_Data!$D$2:$D$2552,$A35,Raw_Data!$H$2:$H$2552,$B35) | N35: =IFERROR(M35/K35,"") | O35: =IFERROR(C35/M35,"") | P35: =SUMIFS(Raw_Data!$AO$2:$AO$2552,Raw_Data!$D$2:$D$2552,$A35,Raw_Data!$H$2:$H$2552,$B35) | Q35: =IFERROR(P35/M35,"") | R35: =IFERROR(C35/P35,"") | S35: =SUMIFS(Raw_Data!$AR$2:$AR$2552,Raw_Data!$D$2:$D$2552,$A35,Raw_Data!$H$2:$H$2552,$B35) | T35: =SUMIFS(Raw_Data!$AS$2:$AS$2552,Raw_Data!$D$2:$D$2552,$A35,Raw_Data!$H$2:$H$2552,$B35) | U35: =M35+S35 | V35: =SUMIFS(Raw_Data!$AU$2:$AU$2552,Raw_Data!$D$2:$D$2552,$A35,Raw_Data!$H$2:$H$2552,$B35) | W35: =IFERROR(C35/Summary!$B$17,"") | X35: =IFERROR(M35/Summary!$L$17,"")
A36: Meta (FB/IG) | B36: JAVAN | C36: =SUMIFS(Raw_Data!$R$2:$R$2552,Raw_Data!$D$2:$D$2552,$A36,Raw_Data!$H$2:$H$2552,$B36) | D36: =SUMIFS(Raw_Data!$S$2:$S$2552,Raw_Data!$D$2:$D$2552,$A36,Raw_Data!$H$2:$H$2552,$B36) | E36: =SUMIFS(Raw_Data!$T$2:$T$2552,Raw_Data!$D$2:$D$2552,$A36,Raw_Data!$H$2:$H$2552,$B36) | F36: =IFERROR(D36/E36,"") | G36: =SUMIFS(Raw_Data!$W$2:$W$2552,Raw_Data!$D$2:$D$2552,$A36,Raw_Data!$H$2:$H$2552,$B36) | H36: =IFERROR(G36/D36,"") | I36: =IFERROR(C36/G36,"") | J36: =IFERROR(C36/D36*1000,"") | K36: =SUMIFS(Raw_Data!$AA$2:$AA$2552,Raw_Data!$D$2:$D$2552,$A36,Raw_Data!$H$2:$H$2552,$B36) | L36: =IFERROR(K36/G36,"") | M36: =SUMIFS(Raw_Data!$AL$2:$AL$2552,Raw_Data!$D$2:$D$2552,$A36,Raw_Data!$H$2:$H$2552,$B36) | N36: =IFERROR(M36/K36,"") | O36: =IFERROR(C36/M36,"") | P36: =SUMIFS(Raw_Data!$AO$2:$AO$2552,Raw_Data!$D$2:$D$2552,$A36,Raw_Data!$H$2:$H$2552,$B36) | Q36: =IFERROR(P36/M36,"") | R36: =IFERROR(C36/P36,"") | S36: =SUMIFS(Raw_Data!$AR$2:$AR$2552,Raw_Data!$D$2:$D$2552,$A36,Raw_Data!$H$2:$H$2552,$B36) | T36: =SUMIFS(Raw_Data!$AS$2:$AS$2552,Raw_Data!$D$2:$D$2552,$A36,Raw_Data!$H$2:$H$2552,$B36) | U36: =M36+S36 | V36: =SUMIFS(Raw_Data!$AU$2:$AU$2552,Raw_Data!$D$2:$D$2552,$A36,Raw_Data!$H$2:$H$2552,$B36) | W36: =IFERROR(C36/Summary!$B$17,"") | X36: =IFERROR(M36/Summary!$L$17,"")
A37: Meta (FB/IG) | B37: PANTERA | C37: =SUMIFS(Raw_Data!$R$2:$R$2552,Raw_Data!$D$2:$D$2552,$A37,Raw_Data!$H$2:$H$2552,$B37) | D37: =SUMIFS(Raw_Data!$S$2:$S$2552,Raw_Data!$D$2:$D$2552,$A37,Raw_Data!$H$2:$H$2552,$B37) | E37: =SUMIFS(Raw_Data!$T$2:$T$2552,Raw_Data!$D$2:$D$2552,$A37,Raw_Data!$H$2:$H$2552,$B37) | F37: =IFERROR(D37/E37,"") | G37: =SUMIFS(Raw_Data!$W$2:$W$2552,Raw_Data!$D$2:$D$2552,$A37,Raw_Data!$H$2:$H$2552,$B37) | H37: =IFERROR(G37/D37,"") | I37: =IFERROR(C37/G37,"") | J37: =IFERROR(C37/D37*1000,"") | K37: =SUMIFS(Raw_Data!$AA$2:$AA$2552,Raw_Data!$D$2:$D$2552,$A37,Raw_Data!$H$2:$H$2552,$B37) | L37: =IFERROR(K37/G37,"") | M37: =SUMIFS(Raw_Data!$AL$2:$AL$2552,Raw_Data!$D$2:$D$2552,$A37,Raw_Data!$H$2:$H$2552,$B37) | N37: =IFERROR(M37/K37,"") | O37: =IFERROR(C37/M37,"") | P37: =SUMIFS(Raw_Data!$AO$2:$AO$2552,Raw_Data!$D$2:$D$2552,$A37,Raw_Data!$H$2:$H$2552,$B37) | Q37: =IFERROR(P37/M37,"") | R37: =IFERROR(C37/P37,"") | S37: =SUMIFS(Raw_Data!$AR$2:$AR$2552,Raw_Data!$D$2:$D$2552,$A37,Raw_Data!$H$2:$H$2552,$B37) | T37: =SUMIFS(Raw_Data!$AS$2:$AS$2552,Raw_Data!$D$2:$D$2552,$A37,Raw_Data!$H$2:$H$2552,$B37) | U37: =M37+S37 | V37: =SUMIFS(Raw_Data!$AU$2:$AU$2552,Raw_Data!$D$2:$D$2552,$A37,Raw_Data!$H$2:$H$2552,$B37) | W37: =IFERROR(C37/Summary!$B$17,"") | X37: =IFERROR(M37/Summary!$L$17,"")
A38: Meta (FB/IG) | B38: Range | C38: =SUMIFS(Raw_Data!$R$2:$R$2552,Raw_Data!$D$2:$D$2552,$A38,Raw_Data!$H$2:$H$2552,$B38) | D38: =SUMIFS(Raw_Data!$S$2:$S$2552,Raw_Data!$D$2:$D$2552,$A38,Raw_Data!$H$2:$H$2552,$B38) | E38: =SUMIFS(Raw_Data!$T$2:$T$2552,Raw_Data!$D$2:$D$2552,$A38,Raw_Data!$H$2:$H$2552,$B38) | F38: =IFERROR(D38/E38,"") | G38: =SUMIFS(Raw_Data!$W$2:$W$2552,Raw_Data!$D$2:$D$2552,$A38,Raw_Data!$H$2:$H$2552,$B38) | H38: =IFERROR(G38/D38,"") | I38: =IFERROR(C38/G38,"") | J38: =IFERROR(C38/D38*1000,"") | K38: =SUMIFS(Raw_Data!$AA$2:$AA$2552,Raw_Data!$D$2:$D$2552,$A38,Raw_Data!$H$2:$H$2552,$B38) | L38: =IFERROR(K38/G38,"") | M38: =SUMIFS(Raw_Data!$AL$2:$AL$2552,Raw_Data!$D$2:$D$2552,$A38,Raw_Data!$H$2:$H$2552,$B38) | N38: =IFERROR(M38/K38,"") | O38: =IFERROR(C38/M38,"") | P38: =SUMIFS(Raw_Data!$AO$2:$AO$2552,Raw_Data!$D$2:$D$2552,$A38,Raw_Data!$H$2:$H$2552,$B38) | Q38: =IFERROR(P38/M38,"") | R38: =IFERROR(C38/P38,"") | S38: =SUMIFS(Raw_Data!$AR$2:$AR$2552,Raw_Data!$D$2:$D$2552,$A38,Raw_Data!$H$2:$H$2552,$B38) | T38: =SUMIFS(Raw_Data!$AS$2:$AS$2552,Raw_Data!$D$2:$D$2552,$A38,Raw_Data!$H$2:$H$2552,$B38) | U38: =M38+S38 | V38: =SUMIFS(Raw_Data!$AU$2:$AU$2552,Raw_Data!$D$2:$D$2552,$A38,Raw_Data!$H$2:$H$2552,$B38) | W38: =IFERROR(C38/Summary!$B$17,"") | X38: =IFERROR(M38/Summary!$L$17,"")
A39: TikTok | B39: AMUR | C39: =SUMIFS(Raw_Data!$R$2:$R$2552,Raw_Data!$D$2:$D$2552,$A39,Raw_Data!$H$2:$H$2552,$B39) | D39: =SUMIFS(Raw_Data!$S$2:$S$2552,Raw_Data!$D$2:$D$2552,$A39,Raw_Data!$H$2:$H$2552,$B39) | E39: =SUMIFS(Raw_Data!$T$2:$T$2552,Raw_Data!$D$2:$D$2552,$A39,Raw_Data!$H$2:$H$2552,$B39) | F39: =IFERROR(D39/E39,"") | G39: =SUMIFS(Raw_Data!$W$2:$W$2552,Raw_Data!$D$2:$D$2552,$A39,Raw_Data!$H$2:$H$2552,$B39) | H39: =IFERROR(G39/D39,"") | I39: =IFERROR(C39/G39,"") | J39: =IFERROR(C39/D39*1000,"") | K39: =SUMIFS(Raw_Data!$AA$2:$AA$2552,Raw_Data!$D$2:$D$2552,$A39,Raw_Data!$H$2:$H$2552,$B39) | L39: =IFERROR(K39/G39,"") | M39: =SUMIFS(Raw_Data!$AL$2:$AL$2552,Raw_Data!$D$2:$D$2552,$A39,Raw_Data!$H$2:$H$2552,$B39) | N39: =IFERROR(M39/K39,"") | O39: =IFERROR(C39/M39,"") | P39: =SUMIFS(Raw_Data!$AO$2:$AO$2552,Raw_Data!$D$2:$D$2552,$A39,Raw_Data!$H$2:$H$2552,$B39) | Q39: =IFERROR(P39/M39,"") | R39: =IFERROR(C39/P39,"") | S39: =SUMIFS(Raw_Data!$AR$2:$AR$2552,Raw_Data!$D$2:$D$2552,$A39,Raw_Data!$H$2:$H$2552,$B39) | T39: =SUMIFS(Raw_Data!$AS$2:$AS$2552,Raw_Data!$D$2:$D$2552,$A39,Raw_Data!$H$2:$H$2552,$B39) | U39: =M39+S39 | V39: =SUMIFS(Raw_Data!$AU$2:$AU$2552,Raw_Data!$D$2:$D$2552,$A39,Raw_Data!$H$2:$H$2552,$B39) | W39: =IFERROR(C39/Summary!$B$17,"") | X39: =IFERROR(M39/Summary!$L$17,"")
A40: TikTok | B40: PANTERA | C40: =SUMIFS(Raw_Data!$R$2:$R$2552,Raw_Data!$D$2:$D$2552,$A40,Raw_Data!$H$2:$H$2552,$B40) | D40: =SUMIFS(Raw_Data!$S$2:$S$2552,Raw_Data!$D$2:$D$2552,$A40,Raw_Data!$H$2:$H$2552,$B40) | E40: =SUMIFS(Raw_Data!$T$2:$T$2552,Raw_Data!$D$2:$D$2552,$A40,Raw_Data!$H$2:$H$2552,$B40) | F40: =IFERROR(D40/E40,"") | G40: =SUMIFS(Raw_Data!$W$2:$W$2552,Raw_Data!$D$2:$D$2552,$A40,Raw_Data!$H$2:$H$2552,$B40) | H40: =IFERROR(G40/D40,"") | I40: =IFERROR(C40/G40,"") | J40: =IFERROR(C40/D40*1000,"") | K40: =SUMIFS(Raw_Data!$AA$2:$AA$2552,Raw_Data!$D$2:$D$2552,$A40,Raw_Data!$H$2:$H$2552,$B40) | L40: =IFERROR(K40/G40,"") | M40: =SUMIFS(Raw_Data!$AL$2:$AL$2552,Raw_Data!$D$2:$D$2552,$A40,Raw_Data!$H$2:$H$2552,$B40) | N40: =IFERROR(M40/K40,"") | O40: =IFERROR(C40/M40,"") | P40: =SUMIFS(Raw_Data!$AO$2:$AO$2552,Raw_Data!$D$2:$D$2552,$A40,Raw_Data!$H$2:$H$2552,$B40) | Q40: =IFERROR(P40/M40,"") | R40: =IFERROR(C40/P40,"") | S40: =SUMIFS(Raw_Data!$AR$2:$AR$2552,Raw_Data!$D$2:$D$2552,$A40,Raw_Data!$H$2:$H$2552,$B40) | T40: =SUMIFS(Raw_Data!$AS$2:$AS$2552,Raw_Data!$D$2:$D$2552,$A40,Raw_Data!$H$2:$H$2552,$B40) | U40: =M40+S40 | V40: =SUMIFS(Raw_Data!$AU$2:$AU$2552,Raw_Data!$D$2:$D$2552,$A40,Raw_Data!$H$2:$H$2552,$B40) | W40: =IFERROR(C40/Summary!$B$17,"") | X40: =IFERROR(M40/Summary!$L$17,"")
A41: TikTok | B41: Range | C41: =SUMIFS(Raw_Data!$R$2:$R$2552,Raw_Data!$D$2:$D$2552,$A41,Raw_Data!$H$2:$H$2552,$B41) | D41: =SUMIFS(Raw_Data!$S$2:$S$2552,Raw_Data!$D$2:$D$2552,$A41,Raw_Data!$H$2:$H$2552,$B41) | E41: =SUMIFS(Raw_Data!$T$2:$T$2552,Raw_Data!$D$2:$D$2552,$A41,Raw_Data!$H$2:$H$2552,$B41) | F41: =IFERROR(D41/E41,"") | G41: =SUMIFS(Raw_Data!$W$2:$W$2552,Raw_Data!$D$2:$D$2552,$A41,Raw_Data!$H$2:$H$2552,$B41) | H41: =IFERROR(G41/D41,"") | I41: =IFERROR(C41/G41,"") | J41: =IFERROR(C41/D41*1000,"") | K41: =SUMIFS(Raw_Data!$AA$2:$AA$2552,Raw_Data!$D$2:$D$2552,$A41,Raw_Data!$H$2:$H$2552,$B41) | L41: =IFERROR(K41/G41,"") | M41: =SUMIFS(Raw_Data!$AL$2:$AL$2552,Raw_Data!$D$2:$D$2552,$A41,Raw_Data!$H$2:$H$2552,$B41) | N41: =IFERROR(M41/K41,"") | O41: =IFERROR(C41/M41,"") | P41: =SUMIFS(Raw_Data!$AO$2:$AO$2552,Raw_Data!$D$2:$D$2552,$A41,Raw_Data!$H$2:$H$2552,$B41) | Q41: =IFERROR(P41/M41,"") | R41: =IFERROR(C41/P41,"") | S41: =SUMIFS(Raw_Data!$AR$2:$AR$2552,Raw_Data!$D$2:$D$2552,$A41,Raw_Data!$H$2:$H$2552,$B41) | T41: =SUMIFS(Raw_Data!$AS$2:$AS$2552,Raw_Data!$D$2:$D$2552,$A41,Raw_Data!$H$2:$H$2552,$B41) | U41: =M41+S41 | V41: =SUMIFS(Raw_Data!$AU$2:$AU$2552,Raw_Data!$D$2:$D$2552,$A41,Raw_Data!$H$2:$H$2552,$B41) | W41: =IFERROR(C41/Summary!$B$17,"") | X41: =IFERROR(M41/Summary!$L$17,"")
A42: X | B42: Range | C42: =SUMIFS(Raw_Data!$R$2:$R$2552,Raw_Data!$D$2:$D$2552,$A42,Raw_Data!$H$2:$H$2552,$B42) | D42: =SUMIFS(Raw_Data!$S$2:$S$2552,Raw_Data!$D$2:$D$2552,$A42,Raw_Data!$H$2:$H$2552,$B42) | E42: =SUMIFS(Raw_Data!$T$2:$T$2552,Raw_Data!$D$2:$D$2552,$A42,Raw_Data!$H$2:$H$2552,$B42) | F42: =IFERROR(D42/E42,"") | G42: =SUMIFS(Raw_Data!$W$2:$W$2552,Raw_Data!$D$2:$D$2552,$A42,Raw_Data!$H$2:$H$2552,$B42) | H42: =IFERROR(G42/D42,"") | I42: =IFERROR(C42/G42,"") | J42: =IFERROR(C42/D42*1000,"") | K42: =SUMIFS(Raw_Data!$AA$2:$AA$2552,Raw_Data!$D$2:$D$2552,$A42,Raw_Data!$H$2:$H$2552,$B42) | L42: =IFERROR(K42/G42,"") | M42: =SUMIFS(Raw_Data!$AL$2:$AL$2552,Raw_Data!$D$2:$D$2552,$A42,Raw_Data!$H$2:$H$2552,$B42) | N42: =IFERROR(M42/K42,"") | O42: =IFERROR(C42/M42,"") | P42: =SUMIFS(Raw_Data!$AO$2:$AO$2552,Raw_Data!$D$2:$D$2552,$A42,Raw_Data!$H$2:$H$2552,$B42) | Q42: =IFERROR(P42/M42,"") | R42: =IFERROR(C42/P42,"") | S42: =SUMIFS(Raw_Data!$AR$2:$AR$2552,Raw_Data!$D$2:$D$2552,$A42,Raw_Data!$H$2:$H$2552,$B42) | T42: =SUMIFS(Raw_Data!$AS$2:$AS$2552,Raw_Data!$D$2:$D$2552,$A42,Raw_Data!$H$2:$H$2552,$B42) | U42: =M42+S42 | V42: =SUMIFS(Raw_Data!$AU$2:$AU$2552,Raw_Data!$D$2:$D$2552,$A42,Raw_Data!$H$2:$H$2552,$B42) | W42: =IFERROR(C42/Summary!$B$17,"") | X42: =IFERROR(M42/Summary!$L$17,"")
A43: Programmatic | B43: Range | C43: =SUMIFS(Raw_Data!$R$2:$R$2552,Raw_Data!$D$2:$D$2552,$A43,Raw_Data!$H$2:$H$2552,$B43) | D43: =SUMIFS(Raw_Data!$S$2:$S$2552,Raw_Data!$D$2:$D$2552,$A43,Raw_Data!$H$2:$H$2552,$B43) | E43: =SUMIFS(Raw_Data!$T$2:$T$2552,Raw_Data!$D$2:$D$2552,$A43,Raw_Data!$H$2:$H$2552,$B43) | F43: =IFERROR(D43/E43,"") | G43: =SUMIFS(Raw_Data!$W$2:$W$2552,Raw_Data!$D$2:$D$2552,$A43,Raw_Data!$H$2:$H$2552,$B43) | H43: =IFERROR(G43/D43,"") | I43: =IFERROR(C43/G43,"") | J43: =IFERROR(C43/D43*1000,"") | K43: =SUMIFS(Raw_Data!$AA$2:$AA$2552,Raw_Data!$D$2:$D$2552,$A43,Raw_Data!$H$2:$H$2552,$B43) | L43: =IFERROR(K43/G43,"") | M43: =SUMIFS(Raw_Data!$AL$2:$AL$2552,Raw_Data!$D$2:$D$2552,$A43,Raw_Data!$H$2:$H$2552,$B43) | N43: =IFERROR(M43/K43,"") | O43: =IFERROR(C43/M43,"") | P43: =SUMIFS(Raw_Data!$AO$2:$AO$2552,Raw_Data!$D$2:$D$2552,$A43,Raw_Data!$H$2:$H$2552,$B43) | Q43: =IFERROR(P43/M43,"") | R43: =IFERROR(C43/P43,"") | S43: =SUMIFS(Raw_Data!$AR$2:$AR$2552,Raw_Data!$D$2:$D$2552,$A43,Raw_Data!$H$2:$H$2552,$B43) | T43: =SUMIFS(Raw_Data!$AS$2:$AS$2552,Raw_Data!$D$2:$D$2552,$A43,Raw_Data!$H$2:$H$2552,$B43) | U43: =M43+S43 | V43: =SUMIFS(Raw_Data!$AU$2:$AU$2552,Raw_Data!$D$2:$D$2552,$A43,Raw_Data!$H$2:$H$2552,$B43) | W43: =IFERROR(C43/Summary!$B$17,"") | X43: =IFERROR(M43/Summary!$L$17,"")
A44: TOTAL | F44: =IFERROR(D44/E44,"") | H44: =IFERROR(G44/D44,"") | I44: =IFERROR(C44/G44,"") | J44: =IFERROR(C44/D44*1000,"") | L44: =IFERROR(K44/G44,"") | N44: =IFERROR(M44/K44,"") | O44: =IFERROR(C44/M44,"") | Q44: =IFERROR(P44/M44,"") | R44: =IFERROR(C44/P44,"") | U44: =M44+S44 | W44: =IFERROR(C44/Summary!$B$17,"") | X44: =IFERROR(M44/Summary!$L$17,"")
A47: CHANNEL x AUDIENCE
A48: Channel | B48: Audience Type | C48: Spend (ZAR) | D48: Impressions | E48: Reach (sum of daily) | F48: Avg Daily Frequency | G48: Link Clicks | H48: CTR (Link) | I48: CPC (Link) | J48: CPM | K48: Landing Page Views | L48: LPV Rate | M48: Test Drive Bookings | N48: CVR (Booking / LPV) | O48: CPL (Cost / Booking) | P48: Qualified Leads | Q48: Qualified Rate | R48: Cost per Qualified Lead | S48: View-Through Conv. | T48: Assisted Conv. | U48: Total Attributed Conv. | V48: Est. Revenue Pipeline (ZAR) | W48: % of Spend | X48: % of Bookings
A49: Meta (FB/IG) | B49: In-Market | C49: =SUMIFS(Raw_Data!$R$2:$R$2552,Raw_Data!$D$2:$D$2552,$A49,Raw_Data!$K$2:$K$2552,$B49) | D49: =SUMIFS(Raw_Data!$S$2:$S$2552,Raw_Data!$D$2:$D$2552,$A49,Raw_Data!$K$2:$K$2552,$B49) | E49: =SUMIFS(Raw_Data!$T$2:$T$2552,Raw_Data!$D$2:$D$2552,$A49,Raw_Data!$K$2:$K$2552,$B49) | F49: =IFERROR(D49/E49,"") | G49: =SUMIFS(Raw_Data!$W$2:$W$2552,Raw_Data!$D$2:$D$2552,$A49,Raw_Data!$K$2:$K$2552,$B49) | H49: =IFERROR(G49/D49,"") | I49: =IFERROR(C49/G49,"") | J49: =IFERROR(C49/D49*1000,"") | K49: =SUMIFS(Raw_Data!$AA$2:$AA$2552,Raw_Data!$D$2:$D$2552,$A49,Raw_Data!$K$2:$K$2552,$B49) | L49: =IFERROR(K49/G49,"") | M49: =SUMIFS(Raw_Data!$AL$2:$AL$2552,Raw_Data!$D$2:$D$2552,$A49,Raw_Data!$K$2:$K$2552,$B49) | N49: =IFERROR(M49/K49,"") | O49: =IFERROR(C49/M49,"") | P49: =SUMIFS(Raw_Data!$AO$2:$AO$2552,Raw_Data!$D$2:$D$2552,$A49,Raw_Data!$K$2:$K$2552,$B49) | Q49: =IFERROR(P49/M49,"") | R49: =IFERROR(C49/P49,"") | S49: =SUMIFS(Raw_Data!$AR$2:$AR$2552,Raw_Data!$D$2:$D$2552,$A49,Raw_Data!$K$2:$K$2552,$B49) | T49: =SUMIFS(Raw_Data!$AS$2:$AS$2552,Raw_Data!$D$2:$D$2552,$A49,Raw_Data!$K$2:$K$2552,$B49) | U49: =M49+S49 | V49: =SUMIFS(Raw_Data!$AU$2:$AU$2552,Raw_Data!$D$2:$D$2552,$A49,Raw_Data!$K$2:$K$2552,$B49) | W49: =IFERROR(C49/Summary!$B$17,"") | X49: =IFERROR(M49/Summary!$L$17,"")
A50: Meta (FB/IG) | B50: Interest | C50: =SUMIFS(Raw_Data!$R$2:$R$2552,Raw_Data!$D$2:$D$2552,$A50,Raw_Data!$K$2:$K$2552,$B50) | D50: =SUMIFS(Raw_Data!$S$2:$S$2552,Raw_Data!$D$2:$D$2552,$A50,Raw_Data!$K$2:$K$2552,$B50) | E50: =SUMIFS(Raw_Data!$T$2:$T$2552,Raw_Data!$D$2:$D$2552,$A50,Raw_Data!$K$2:$K$2552,$B50) | F50: =IFERROR(D50/E50,"") | G50: =SUMIFS(Raw_Data!$W$2:$W$2552,Raw_Data!$D$2:$D$2552,$A50,Raw_Data!$K$2:$K$2552,$B50) | H50: =IFERROR(G50/D50,"") | I50: =IFERROR(C50/G50,"") | J50: =IFERROR(C50/D50*1000,"") | K50: =SUMIFS(Raw_Data!$AA$2:$AA$2552,Raw_Data!$D$2:$D$2552,$A50,Raw_Data!$K$2:$K$2552,$B50) | L50: =IFERROR(K50/G50,"") | M50: =SUMIFS(Raw_Data!$AL$2:$AL$2552,Raw_Data!$D$2:$D$2552,$A50,Raw_Data!$K$2:$K$2552,$B50) | N50: =IFERROR(M50/K50,"") | O50: =IFERROR(C50/M50,"") | P50: =SUMIFS(Raw_Data!$AO$2:$AO$2552,Raw_Data!$D$2:$D$2552,$A50,Raw_Data!$K$2:$K$2552,$B50) | Q50: =IFERROR(P50/M50,"") | R50: =IFERROR(C50/P50,"") | S50: =SUMIFS(Raw_Data!$AR$2:$AR$2552,Raw_Data!$D$2:$D$2552,$A50,Raw_Data!$K$2:$K$2552,$B50) | T50: =SUMIFS(Raw_Data!$AS$2:$AS$2552,Raw_Data!$D$2:$D$2552,$A50,Raw_Data!$K$2:$K$2552,$B50) | U50: =M50+S50 | V50: =SUMIFS(Raw_Data!$AU$2:$AU$2552,Raw_Data!$D$2:$D$2552,$A50,Raw_Data!$K$2:$K$2552,$B50) | W50: =IFERROR(C50/Summary!$B$17,"") | X50: =IFERROR(M50/Summary!$L$17,"")
A51: Meta (FB/IG) | B51: Lookalike | C51: =SUMIFS(Raw_Data!$R$2:$R$2552,Raw_Data!$D$2:$D$2552,$A51,Raw_Data!$K$2:$K$2552,$B51) | D51: =SUMIFS(Raw_Data!$S$2:$S$2552,Raw_Data!$D$2:$D$2552,$A51,Raw_Data!$K$2:$K$2552,$B51) | E51: =SUMIFS(Raw_Data!$T$2:$T$2552,Raw_Data!$D$2:$D$2552,$A51,Raw_Data!$K$2:$K$2552,$B51) | F51: =IFERROR(D51/E51,"") | G51: =SUMIFS(Raw_Data!$W$2:$W$2552,Raw_Data!$D$2:$D$2552,$A51,Raw_Data!$K$2:$K$2552,$B51) | H51: =IFERROR(G51/D51,"") | I51: =IFERROR(C51/G51,"") | J51: =IFERROR(C51/D51*1000,"") | K51: =SUMIFS(Raw_Data!$AA$2:$AA$2552,Raw_Data!$D$2:$D$2552,$A51,Raw_Data!$K$2:$K$2552,$B51) | L51: =IFERROR(K51/G51,"") | M51: =SUMIFS(Raw_Data!$AL$2:$AL$2552,Raw_Data!$D$2:$D$2552,$A51,Raw_Data!$K$2:$K$2552,$B51) | N51: =IFERROR(M51/K51,"") | O51: =IFERROR(C51/M51,"") | P51: =SUMIFS(Raw_Data!$AO$2:$AO$2552,Raw_Data!$D$2:$D$2552,$A51,Raw_Data!$K$2:$K$2552,$B51) | Q51: =IFERROR(P51/M51,"") | R51: =IFERROR(C51/P51,"") | S51: =SUMIFS(Raw_Data!$AR$2:$AR$2552,Raw_Data!$D$2:$D$2552,$A51,Raw_Data!$K$2:$K$2552,$B51) | T51: =SUMIFS(Raw_Data!$AS$2:$AS$2552,Raw_Data!$D$2:$D$2552,$A51,Raw_Data!$K$2:$K$2552,$B51) | U51: =M51+S51 | V51: =SUMIFS(Raw_Data!$AU$2:$AU$2552,Raw_Data!$D$2:$D$2552,$A51,Raw_Data!$K$2:$K$2552,$B51) | W51: =IFERROR(C51/Summary!$B$17,"") | X51: =IFERROR(M51/Summary!$L$17,"")
A52: Meta (FB/IG) | B52: Prospecting | C52: =SUMIFS(Raw_Data!$R$2:$R$2552,Raw_Data!$D$2:$D$2552,$A52,Raw_Data!$K$2:$K$2552,$B52) | D52: =SUMIFS(Raw_Data!$S$2:$S$2552,Raw_Data!$D$2:$D$2552,$A52,Raw_Data!$K$2:$K$2552,$B52) | E52: =SUMIFS(Raw_Data!$T$2:$T$2552,Raw_Data!$D$2:$D$2552,$A52,Raw_Data!$K$2:$K$2552,$B52) | F52: =IFERROR(D52/E52,"") | G52: =SUMIFS(Raw_Data!$W$2:$W$2552,Raw_Data!$D$2:$D$2552,$A52,Raw_Data!$K$2:$K$2552,$B52) | H52: =IFERROR(G52/D52,"") | I52: =IFERROR(C52/G52,"") | J52: =IFERROR(C52/D52*1000,"") | K52: =SUMIFS(Raw_Data!$AA$2:$AA$2552,Raw_Data!$D$2:$D$2552,$A52,Raw_Data!$K$2:$K$2552,$B52) | L52: =IFERROR(K52/G52,"") | M52: =SUMIFS(Raw_Data!$AL$2:$AL$2552,Raw_Data!$D$2:$D$2552,$A52,Raw_Data!$K$2:$K$2552,$B52) | N52: =IFERROR(M52/K52,"") | O52: =IFERROR(C52/M52,"") | P52: =SUMIFS(Raw_Data!$AO$2:$AO$2552,Raw_Data!$D$2:$D$2552,$A52,Raw_Data!$K$2:$K$2552,$B52) | Q52: =IFERROR(P52/M52,"") | R52: =IFERROR(C52/P52,"") | S52: =SUMIFS(Raw_Data!$AR$2:$AR$2552,Raw_Data!$D$2:$D$2552,$A52,Raw_Data!$K$2:$K$2552,$B52) | T52: =SUMIFS(Raw_Data!$AS$2:$AS$2552,Raw_Data!$D$2:$D$2552,$A52,Raw_Data!$K$2:$K$2552,$B52) | U52: =M52+S52 | V52: =SUMIFS(Raw_Data!$AU$2:$AU$2552,Raw_Data!$D$2:$D$2552,$A52,Raw_Data!$K$2:$K$2552,$B52) | W52: =IFERROR(C52/Summary!$B$17,"") | X52: =IFERROR(M52/Summary!$L$17,"")
A53: Meta (FB/IG) | B53: Retargeting | C53: =SUMIFS(Raw_Data!$R$2:$R$2552,Raw_Data!$D$2:$D$2552,$A53,Raw_Data!$K$2:$K$2552,$B53) | D53: =SUMIFS(Raw_Data!$S$2:$S$2552,Raw_Data!$D$2:$D$2552,$A53,Raw_Data!$K$2:$K$2552,$B53) | E53: =SUMIFS(Raw_Data!$T$2:$T$2552,Raw_Data!$D$2:$D$2552,$A53,Raw_Data!$K$2:$K$2552,$B53) | F53: =IFERROR(D53/E53,"") | G53: =SUMIFS(Raw_Data!$W$2:$W$2552,Raw_Data!$D$2:$D$2552,$A53,Raw_Data!$K$2:$K$2552,$B53) | H53: =IFERROR(G53/D53,"") | I53: =IFERROR(C53/G53,"") | J53: =IFERROR(C53/D53*1000,"") | K53: =SUMIFS(Raw_Data!$AA$2:$AA$2552,Raw_Data!$D$2:$D$2552,$A53,Raw_Data!$K$2:$K$2552,$B53) | L53: =IFERROR(K53/G53,"") | M53: =SUMIFS(Raw_Data!$AL$2:$AL$2552,Raw_Data!$D$2:$D$2552,$A53,Raw_Data!$K$2:$K$2552,$B53) | N53: =IFERROR(M53/K53,"") | O53: =IFERROR(C53/M53,"") | P53: =SUMIFS(Raw_Data!$AO$2:$AO$2552,Raw_Data!$D$2:$D$2552,$A53,Raw_Data!$K$2:$K$2552,$B53) | Q53: =IFERROR(P53/M53,"") | R53: =IFERROR(C53/P53,"") | S53: =SUMIFS(Raw_Data!$AR$2:$AR$2552,Raw_Data!$D$2:$D$2552,$A53,Raw_Data!$K$2:$K$2552,$B53) | T53: =SUMIFS(Raw_Data!$AS$2:$AS$2552,Raw_Data!$D$2:$D$2552,$A53,Raw_Data!$K$2:$K$2552,$B53) | U53: =M53+S53 | V53: =SUMIFS(Raw_Data!$AU$2:$AU$2552,Raw_Data!$D$2:$D$2552,$A53,Raw_Data!$K$2:$K$2552,$B53) | W53: =IFERROR(C53/Summary!$B$17,"") | X53: =IFERROR(M53/Summary!$L$17,"")
A54: TikTok | B54: Interest | C54: =SUMIFS(Raw_Data!$R$2:$R$2552,Raw_Data!$D$2:$D$2552,$A54,Raw_Data!$K$2:$K$2552,$B54) | D54: =SUMIFS(Raw_Data!$S$2:$S$2552,Raw_Data!$D$2:$D$2552,$A54,Raw_Data!$K$2:$K$2552,$B54) | E54: =SUMIFS(Raw_Data!$T$2:$T$2552,Raw_Data!$D$2:$D$2552,$A54,Raw_Data!$K$2:$K$2552,$B54) | F54: =IFERROR(D54/E54,"") | G54: =SUMIFS(Raw_Data!$W$2:$W$2552,Raw_Data!$D$2:$D$2552,$A54,Raw_Data!$K$2:$K$2552,$B54) | H54: =IFERROR(G54/D54,"") | I54: =IFERROR(C54/G54,"") | J54: =IFERROR(C54/D54*1000,"") | K54: =SUMIFS(Raw_Data!$AA$2:$AA$2552,Raw_Data!$D$2:$D$2552,$A54,Raw_Data!$K$2:$K$2552,$B54) | L54: =IFERROR(K54/G54,"") | M54: =SUMIFS(Raw_Data!$AL$2:$AL$2552,Raw_Data!$D$2:$D$2552,$A54,Raw_Data!$K$2:$K$2552,$B54) | N54: =IFERROR(M54/K54,"") | O54: =IFERROR(C54/M54,"") | P54: =SUMIFS(Raw_Data!$AO$2:$AO$2552,Raw_Data!$D$2:$D$2552,$A54,Raw_Data!$K$2:$K$2552,$B54) | Q54: =IFERROR(P54/M54,"") | R54: =IFERROR(C54/P54,"") | S54: =SUMIFS(Raw_Data!$AR$2:$AR$2552,Raw_Data!$D$2:$D$2552,$A54,Raw_Data!$K$2:$K$2552,$B54) | T54: =SUMIFS(Raw_Data!$AS$2:$AS$2552,Raw_Data!$D$2:$D$2552,$A54,Raw_Data!$K$2:$K$2552,$B54) | U54: =M54+S54 | V54: =SUMIFS(Raw_Data!$AU$2:$AU$2552,Raw_Data!$D$2:$D$2552,$A54,Raw_Data!$K$2:$K$2552,$B54) | W54: =IFERROR(C54/Summary!$B$17,"") | X54: =IFERROR(M54/Summary!$L$17,"")
A55: TikTok | B55: Lookalike | C55: =SUMIFS(Raw_Data!$R$2:$R$2552,Raw_Data!$D$2:$D$2552,$A55,Raw_Data!$K$2:$K$2552,$B55) | D55: =SUMIFS(Raw_Data!$S$2:$S$2552,Raw_Data!$D$2:$D$2552,$A55,Raw_Data!$K$2:$K$2552,$B55) | E55: =SUMIFS(Raw_Data!$T$2:$T$2552,Raw_Data!$D$2:$D$2552,$A55,Raw_Data!$K$2:$K$2552,$B55) | F55: =IFERROR(D55/E55,"") | G55: =SUMIFS(Raw_Data!$W$2:$W$2552,Raw_Data!$D$2:$D$2552,$A55,Raw_Data!$K$2:$K$2552,$B55) | H55: =IFERROR(G55/D55,"") | I55: =IFERROR(C55/G55,"") | J55: =IFERROR(C55/D55*1000,"") | K55: =SUMIFS(Raw_Data!$AA$2:$AA$2552,Raw_Data!$D$2:$D$2552,$A55,Raw_Data!$K$2:$K$2552,$B55) | L55: =IFERROR(K55/G55,"") | M55: =SUMIFS(Raw_Data!$AL$2:$AL$2552,Raw_Data!$D$2:$D$2552,$A55,Raw_Data!$K$2:$K$2552,$B55) | N55: =IFERROR(M55/K55,"") | O55: =IFERROR(C55/M55,"") | P55: =SUMIFS(Raw_Data!$AO$2:$AO$2552,Raw_Data!$D$2:$D$2552,$A55,Raw_Data!$K$2:$K$2552,$B55) | Q55: =IFERROR(P55/M55,"") | R55: =IFERROR(C55/P55,"") | S55: =SUMIFS(Raw_Data!$AR$2:$AR$2552,Raw_Data!$D$2:$D$2552,$A55,Raw_Data!$K$2:$K$2552,$B55) | T55: =SUMIFS(Raw_Data!$AS$2:$AS$2552,Raw_Data!$D$2:$D$2552,$A55,Raw_Data!$K$2:$K$2552,$B55) | U55: =M55+S55 | V55: =SUMIFS(Raw_Data!$AU$2:$AU$2552,Raw_Data!$D$2:$D$2552,$A55,Raw_Data!$K$2:$K$2552,$B55) | W55: =IFERROR(C55/Summary!$B$17,"") | X55: =IFERROR(M55/Summary!$L$17,"")
A56: TikTok | B56: Prospecting | C56: =SUMIFS(Raw_Data!$R$2:$R$2552,Raw_Data!$D$2:$D$2552,$A56,Raw_Data!$K$2:$K$2552,$B56) | D56: =SUMIFS(Raw_Data!$S$2:$S$2552,Raw_Data!$D$2:$D$2552,$A56,Raw_Data!$K$2:$K$2552,$B56) | E56: =SUMIFS(Raw_Data!$T$2:$T$2552,Raw_Data!$D$2:$D$2552,$A56,Raw_Data!$K$2:$K$2552,$B56) | F56: =IFERROR(D56/E56,"") | G56: =SUMIFS(Raw_Data!$W$2:$W$2552,Raw_Data!$D$2:$D$2552,$A56,Raw_Data!$K$2:$K$2552,$B56) | H56: =IFERROR(G56/D56,"") | I56: =IFERROR(C56/G56,"") | J56: =IFERROR(C56/D56*1000,"") | K56: =SUMIFS(Raw_Data!$AA$2:$AA$2552,Raw_Data!$D$2:$D$2552,$A56,Raw_Data!$K$2:$K$2552,$B56) | L56: =IFERROR(K56/G56,"") | M56: =SUMIFS(Raw_Data!$AL$2:$AL$2552,Raw_Data!$D$2:$D$2552,$A56,Raw_Data!$K$2:$K$2552,$B56) | N56: =IFERROR(M56/K56,"") | O56: =IFERROR(C56/M56,"") | P56: =SUMIFS(Raw_Data!$AO$2:$AO$2552,Raw_Data!$D$2:$D$2552,$A56,Raw_Data!$K$2:$K$2552,$B56) | Q56: =IFERROR(P56/M56,"") | R56: =IFERROR(C56/P56,"") | S56: =SUMIFS(Raw_Data!$AR$2:$AR$2552,Raw_Data!$D$2:$D$2552,$A56,Raw_Data!$K$2:$K$2552,$B56) | T56: =SUMIFS(Raw_Data!$AS$2:$AS$2552,Raw_Data!$D$2:$D$2552,$A56,Raw_Data!$K$2:$K$2552,$B56) | U56: =M56+S56 | V56: =SUMIFS(Raw_Data!$AU$2:$AU$2552,Raw_Data!$D$2:$D$2552,$A56,Raw_Data!$K$2:$K$2552,$B56) | W56: =IFERROR(C56/Summary!$B$17,"") | X56: =IFERROR(M56/Summary!$L$17,"")
A57: TikTok | B57: Retargeting | C57: =SUMIFS(Raw_Data!$R$2:$R$2552,Raw_Data!$D$2:$D$2552,$A57,Raw_Data!$K$2:$K$2552,$B57) | D57: =SUMIFS(Raw_Data!$S$2:$S$2552,Raw_Data!$D$2:$D$2552,$A57,Raw_Data!$K$2:$K$2552,$B57) | E57: =SUMIFS(Raw_Data!$T$2:$T$2552,Raw_Data!$D$2:$D$2552,$A57,Raw_Data!$K$2:$K$2552,$B57) | F57: =IFERROR(D57/E57,"") | G57: =SUMIFS(Raw_Data!$W$2:$W$2552,Raw_Data!$D$2:$D$2552,$A57,Raw_Data!$K$2:$K$2552,$B57) | H57: =IFERROR(G57/D57,"") | I57: =IFERROR(C57/G57,"") | J57: =IFERROR(C57/D57*1000,"") | K57: =SUMIFS(Raw_Data!$AA$2:$AA$2552,Raw_Data!$D$2:$D$2552,$A57,Raw_Data!$K$2:$K$2552,$B57) | L57: =IFERROR(K57/G57,"") | M57: =SUMIFS(Raw_Data!$AL$2:$AL$2552,Raw_Data!$D$2:$D$2552,$A57,Raw_Data!$K$2:$K$2552,$B57) | N57: =IFERROR(M57/K57,"") | O57: =IFERROR(C57/M57,"") | P57: =SUMIFS(Raw_Data!$AO$2:$AO$2552,Raw_Data!$D$2:$D$2552,$A57,Raw_Data!$K$2:$K$2552,$B57) | Q57: =IFERROR(P57/M57,"") | R57: =IFERROR(C57/P57,"") | S57: =SUMIFS(Raw_Data!$AR$2:$AR$2552,Raw_Data!$D$2:$D$2552,$A57,Raw_Data!$K$2:$K$2552,$B57) | T57: =SUMIFS(Raw_Data!$AS$2:$AS$2552,Raw_Data!$D$2:$D$2552,$A57,Raw_Data!$K$2:$K$2552,$B57) | U57: =M57+S57 | V57: =SUMIFS(Raw_Data!$AU$2:$AU$2552,Raw_Data!$D$2:$D$2552,$A57,Raw_Data!$K$2:$K$2552,$B57) | W57: =IFERROR(C57/Summary!$B$17,"") | X57: =IFERROR(M57/Summary!$L$17,"")
A58: X | B58: In-Market | C58: =SUMIFS(Raw_Data!$R$2:$R$2552,Raw_Data!$D$2:$D$2552,$A58,Raw_Data!$K$2:$K$2552,$B58) | D58: =SUMIFS(Raw_Data!$S$2:$S$2552,Raw_Data!$D$2:$D$2552,$A58,Raw_Data!$K$2:$K$2552,$B58) | E58: =SUMIFS(Raw_Data!$T$2:$T$2552,Raw_Data!$D$2:$D$2552,$A58,Raw_Data!$K$2:$K$2552,$B58) | F58: =IFERROR(D58/E58,"") | G58: =SUMIFS(Raw_Data!$W$2:$W$2552,Raw_Data!$D$2:$D$2552,$A58,Raw_Data!$K$2:$K$2552,$B58) | H58: =IFERROR(G58/D58,"") | I58: =IFERROR(C58/G58,"") | J58: =IFERROR(C58/D58*1000,"") | K58: =SUMIFS(Raw_Data!$AA$2:$AA$2552,Raw_Data!$D$2:$D$2552,$A58,Raw_Data!$K$2:$K$2552,$B58) | L58: =IFERROR(K58/G58,"") | M58: =SUMIFS(Raw_Data!$AL$2:$AL$2552,Raw_Data!$D$2:$D$2552,$A58,Raw_Data!$K$2:$K$2552,$B58) | N58: =IFERROR(M58/K58,"") | O58: =IFERROR(C58/M58,"") | P58: =SUMIFS(Raw_Data!$AO$2:$AO$2552,Raw_Data!$D$2:$D$2552,$A58,Raw_Data!$K$2:$K$2552,$B58) | Q58: =IFERROR(P58/M58,"") | R58: =IFERROR(C58/P58,"") | S58: =SUMIFS(Raw_Data!$AR$2:$AR$2552,Raw_Data!$D$2:$D$2552,$A58,Raw_Data!$K$2:$K$2552,$B58) | T58: =SUMIFS(Raw_Data!$AS$2:$AS$2552,Raw_Data!$D$2:$D$2552,$A58,Raw_Data!$K$2:$K$2552,$B58) | U58: =M58+S58 | V58: =SUMIFS(Raw_Data!$AU$2:$AU$2552,Raw_Data!$D$2:$D$2552,$A58,Raw_Data!$K$2:$K$2552,$B58) | W58: =IFERROR(C58/Summary!$B$17,"") | X58: =IFERROR(M58/Summary!$L$17,"")
A59: X | B59: Interest | C59: =SUMIFS(Raw_Data!$R$2:$R$2552,Raw_Data!$D$2:$D$2552,$A59,Raw_Data!$K$2:$K$2552,$B59) | D59: =SUMIFS(Raw_Data!$S$2:$S$2552,Raw_Data!$D$2:$D$2552,$A59,Raw_Data!$K$2:$K$2552,$B59) | E59: =SUMIFS(Raw_Data!$T$2:$T$2552,Raw_Data!$D$2:$D$2552,$A59,Raw_Data!$K$2:$K$2552,$B59) | F59: =IFERROR(D59/E59,"") | G59: =SUMIFS(Raw_Data!$W$2:$W$2552,Raw_Data!$D$2:$D$2552,$A59,Raw_Data!$K$2:$K$2552,$B59) | H59: =IFERROR(G59/D59,"") | I59: =IFERROR(C59/G59,"") | J59: =IFERROR(C59/D59*1000,"") | K59: =SUMIFS(Raw_Data!$AA$2:$AA$2552,Raw_Data!$D$2:$D$2552,$A59,Raw_Data!$K$2:$K$2552,$B59) | L59: =IFERROR(K59/G59,"") | M59: =SUMIFS(Raw_Data!$AL$2:$AL$2552,Raw_Data!$D$2:$D$2552,$A59,Raw_Data!$K$2:$K$2552,$B59) | N59: =IFERROR(M59/K59,"") | O59: =IFERROR(C59/M59,"") | P59: =SUMIFS(Raw_Data!$AO$2:$AO$2552,Raw_Data!$D$2:$D$2552,$A59,Raw_Data!$K$2:$K$2552,$B59) | Q59: =IFERROR(P59/M59,"") | R59: =IFERROR(C59/P59,"") | S59: =SUMIFS(Raw_Data!$AR$2:$AR$2552,Raw_Data!$D$2:$D$2552,$A59,Raw_Data!$K$2:$K$2552,$B59) | T59: =SUMIFS(Raw_Data!$AS$2:$AS$2552,Raw_Data!$D$2:$D$2552,$A59,Raw_Data!$K$2:$K$2552,$B59) | U59: =M59+S59 | V59: =SUMIFS(Raw_Data!$AU$2:$AU$2552,Raw_Data!$D$2:$D$2552,$A59,Raw_Data!$K$2:$K$2552,$B59) | W59: =IFERROR(C59/Summary!$B$17,"") | X59: =IFERROR(M59/Summary!$L$17,"")
A60: X | B60: Lookalike | C60: =SUMIFS(Raw_Data!$R$2:$R$2552,Raw_Data!$D$2:$D$2552,$A60,Raw_Data!$K$2:$K$2552,$B60) | D60: =SUMIFS(Raw_Data!$S$2:$S$2552,Raw_Data!$D$2:$D$2552,$A60,Raw_Data!$K$2:$K$2552,$B60) | E60: =SUMIFS(Raw_Data!$T$2:$T$2552,Raw_Data!$D$2:$D$2552,$A60,Raw_Data!$K$2:$K$2552,$B60) | F60: =IFERROR(D60/E60,"") | G60: =SUMIFS(Raw_Data!$W$2:$W$2552,Raw_Data!$D$2:$D$2552,$A60,Raw_Data!$K$2:$K$2552,$B60) | H60: =IFERROR(G60/D60,"") | I60: =IFERROR(C60/G60,"") | J60: =IFERROR(C60/D60*1000,"") | K60: =SUMIFS(Raw_Data!$AA$2:$AA$2552,Raw_Data!$D$2:$D$2552,$A60,Raw_Data!$K$2:$K$2552,$B60) | L60: =IFERROR(K60/G60,"") | M60: =SUMIFS(Raw_Data!$AL$2:$AL$2552,Raw_Data!$D$2:$D$2552,$A60,Raw_Data!$K$2:$K$2552,$B60) | N60: =IFERROR(M60/K60,"") | O60: =IFERROR(C60/M60,"") | P60: =SUMIFS(Raw_Data!$AO$2:$AO$2552,Raw_Data!$D$2:$D$2552,$A60,Raw_Data!$K$2:$K$2552,$B60) | Q60: =IFERROR(P60/M60,"") | R60: =IFERROR(C60/P60,"") | S60: =SUMIFS(Raw_Data!$AR$2:$AR$2552,Raw_Data!$D$2:$D$2552,$A60,Raw_Data!$K$2:$K$2552,$B60) | T60: =SUMIFS(Raw_Data!$AS$2:$AS$2552,Raw_Data!$D$2:$D$2552,$A60,Raw_Data!$K$2:$K$2552,$B60) | U60: =M60+S60 | V60: =SUMIFS(Raw_Data!$AU$2:$AU$2552,Raw_Data!$D$2:$D$2552,$A60,Raw_Data!$K$2:$K$2552,$B60) | W60: =IFERROR(C60/Summary!$B$17,"") | X60: =IFERROR(M60/Summary!$L$17,"")
... A66: Programmatic | B66: Retargeting | C66: =SUMIFS(Raw_Data!$R$2:$R$2552,Raw_Data!$D$2:$D$2552,$A66,Raw_Data!$K$2:$K$2552,$B66) | D66: =SUMIFS(Raw_Data!$S$2:$S$2552,Raw_Data!$D$2:$D$2552,$A66,Raw_Data!$K$2:$K$2552,$B66) | E66: =SUMIFS(Raw_Data!$T$2:$T$2552,Raw_Data!$D$2:$D$2552,$A66,Raw_Data!$K$2:$K$2552,$B66) | F66: =IFERROR(D66/E66,"") | G66: =SUMIFS(Raw_Data!$W$2:$W$2552,Raw_Data!$D$2:$D$2552,$A66,Raw_Data!$K$2:$K$2552,$B66) | H66: =IFERROR(G66/D66,"") | I66: =IFERROR(C66/G66,"") | J66: =IFERROR(C66/D66*1000,"") | K66: =SUMIFS(Raw_Data!$AA$2:$AA$2552,Raw_Data!$D$2:$D$2552,$A66,Raw_Data!$K$2:$K$2552,$B66) | L66: =IFERROR(K66/G66,"") | M66: =SUMIFS(Raw_Data!$AL$2:$AL$2552,Raw_Data!$D$2:$D$2552,$A66,Raw_Data!$K$2:$K$2552,$B66) | N66: =IFERROR(M66/K66,"") | O66: =IFERROR(C66/M66,"") | P66: =SUMIFS(Raw_Data!$AO$2:$AO$2552,Raw_Data!$D$2:$D$2552,$A66,Raw_Data!$K$2:$K$2552,$B66) | Q66: =IFERROR(P66/M66,"") | R66: =IFERROR(C66/P66,"") | S66: =SUMIFS(Raw_Data!$AR$2:$AR$2552,Raw_Data!$D$2:$D$2552,$A66,Raw_Data!$K$2:$K$2552,$B66) | T66: =SUMIFS(Raw_Data!$AS$2:$AS$2552,Raw_Data!$D$2:$D$2552,$A66,Raw_Data!$K$2:$K$2552,$B66) | U66: =M66+S66 | V66: =SUMIFS(Raw_Data!$AU$2:$AU$2552,Raw_Data!$D$2:$D$2552,$A66,Raw_Data!$K$2:$K$2552,$B66) | W66: =IFERROR(C66/Summary!$B$17,"") | X66: =IFERROR(M66/Summary!$L$17,"")
A67: TOTAL | F67: =IFERROR(D67/E67,"") | H67: =IFERROR(G67/D67,"") | I67: =IFERROR(C67/G67,"") | J67: =IFERROR(C67/D67*1000,"") | L67: =IFERROR(K67/G67,"") | N67: =IFERROR(M67/K67,"") | O67: =IFERROR(C67/M67,"") | Q67: =IFERROR(P67/M67,"") | R67: =IFERROR(C67/P67,"") | U67: =M67+S67 | W67: =IFERROR(C67/Summary!$B$17,"") | X67: =IFERROR(M67/Summary!$L$17,"")

Sheet Campaign_AdSet
A1: Campaign & Ad Set Performance
A2: Campaign roll-up followed by every ad set / line item in the plan.
A4: CAMPAIGN LEVEL
A5: Channel | B5: Campaign Name | C5: Campaign Objective | D5: Model | E5: Offer | F5: Spend (ZAR) | G5: Impressions | H5: Reach (sum of daily) | I5: Avg Daily Frequency | J5: Link Clicks | K5: CTR (Link) | L5: CPC (Link) | M5: CPM | N5: Landing Page Views | O5: LPV Rate | P5: Test Drive Bookings | Q5: CVR (Booking / LPV) | R5: CPL (Cost / Booking) | S5: Qualified Leads | T5: Qualified Rate | U5: Cost per Qualified Lead | V5: View-Through Conv. | W5: Assisted Conv. | X5: Total Attributed Conv. | Y5: Est. Revenue Pipeline (ZAR) | Z5: % of Spend | AA5: % of Bookings
A6: Meta (FB/IG) | B6: LEP_ZA_AUG26_META_TD_AMUR_CONV | C6: Leads - Website Conversions | D6: AMUR | E6: 0% Deposit | F6: =SUMIFS(Raw_Data!$R$2:$R$2552,Raw_Data!$F$2:$F$2552,$B6) | G6: =SUMIFS(Raw_Data!$S$2:$S$2552,Raw_Data!$F$2:$F$2552,$B6) | H6: =SUMIFS(Raw_Data!$T$2:$T$2552,Raw_Data!$F$2:$F$2552,$B6) | I6: =IFERROR(G6/H6,"") | J6: =SUMIFS(Raw_Data!$W$2:$W$2552,Raw_Data!$F$2:$F$2552,$B6) | K6: =IFERROR(J6/G6,"") | L6: =IFERROR(F6/J6,"") | M6: =IFERROR(F6/G6*1000,"") | N6: =SUMIFS(Raw_Data!$AA$2:$AA$2552,Raw_Data!$F$2:$F$2552,$B6) | O6: =IFERROR(N6/J6,"") | P6: =SUMIFS(Raw_Data!$AL$2:$AL$2552,Raw_Data!$F$2:$F$2552,$B6) | Q6: =IFERROR(P6/N6,"") | R6: =IFERROR(F6/P6,"") | S6: =SUMIFS(Raw_Data!$AO$2:$AO$2552,Raw_Data!$F$2:$F$2552,$B6) | T6: =IFERROR(S6/P6,"") | U6: =IFERROR(F6/S6,"") | V6: =SUMIFS(Raw_Data!$AR$2:$AR$2552,Raw_Data!$F$2:$F$2552,$B6) | W6: =SUMIFS(Raw_Data!$AS$2:$AS$2552,Raw_Data!$F$2:$F$2552,$B6) | X6: =P6+V6 | Y6: =SUMIFS(Raw_Data!$AU$2:$AU$2552,Raw_Data!$F$2:$F$2552,$B6) | Z6: =IFERROR(F6/Summary!$B$17,"") | AA6: =IFERROR(P6/Summary!$L$17,"")
A7: Meta (FB/IG) | B7: LEP_ZA_AUG26_META_TD_JAVAN_CONV | C7: Leads - Website Conversions | D7: JAVAN | E7: 10% Deposit | F7: =SUMIFS(Raw_Data!$R$2:$R$2552,Raw_Data!$F$2:$F$2552,$B7) | G7: =SUMIFS(Raw_Data!$S$2:$S$2552,Raw_Data!$F$2:$F$2552,$B7) | H7: =SUMIFS(Raw_Data!$T$2:$T$2552,Raw_Data!$F$2:$F$2552,$B7) | I7: =IFERROR(G7/H7,"") | J7: =SUMIFS(Raw_Data!$W$2:$W$2552,Raw_Data!$F$2:$F$2552,$B7) | K7: =IFERROR(J7/G7,"") | L7: =IFERROR(F7/J7,"") | M7: =IFERROR(F7/G7*1000,"") | N7: =SUMIFS(Raw_Data!$AA$2:$AA$2552,Raw_Data!$F$2:$F$2552,$B7) | O7: =IFERROR(N7/J7,"") | P7: =SUMIFS(Raw_Data!$AL$2:$AL$2552,Raw_Data!$F$2:$F$2552,$B7) | Q7: =IFERROR(P7/N7,"") | R7: =IFERROR(F7/P7,"") | S7: =SUMIFS(Raw_Data!$AO$2:$AO$2552,Raw_Data!$F$2:$F$2552,$B7) | T7: =IFERROR(S7/P7,"") | U7: =IFERROR(F7/S7,"") | V7: =SUMIFS(Raw_Data!$AR$2:$AR$2552,Raw_Data!$F$2:$F$2552,$B7) | W7: =SUMIFS(Raw_Data!$AS$2:$AS$2552,Raw_Data!$F$2:$F$2552,$B7) | X7: =P7+V7 | Y7: =SUMIFS(Raw_Data!$AU$2:$AU$2552,Raw_Data!$F$2:$F$2552,$B7) | Z7: =IFERROR(F7/Summary!$B$17,"") | AA7: =IFERROR(P7/Summary!$L$17,"")
A8: Meta (FB/IG) | B8: LEP_ZA_AUG26_META_TD_PANTERA_CONV | C8: Leads - Website Conversions | D8: PANTERA | E8: 0% Deposit | F8: =SUMIFS(Raw_Data!$R$2:$R$2552,Raw_Data!$F$2:$F$2552,$B8) | G8: =SUMIFS(Raw_Data!$S$2:$S$2552,Raw_Data!$F$2:$F$2552,$B8) | H8: =SUMIFS(Raw_Data!$T$2:$T$2552,Raw_Data!$F$2:$F$2552,$B8) | I8: =IFERROR(G8/H8,"") | J8: =SUMIFS(Raw_Data!$W$2:$W$2552,Raw_Data!$F$2:$F$2552,$B8) | K8: =IFERROR(J8/G8,"") | L8: =IFERROR(F8/J8,"") | M8: =IFERROR(F8/G8*1000,"") | N8: =SUMIFS(Raw_Data!$AA$2:$AA$2552,Raw_Data!$F$2:$F$2552,$B8) | O8: =IFERROR(N8/J8,"") | P8: =SUMIFS(Raw_Data!$AL$2:$AL$2552,Raw_Data!$F$2:$F$2552,$B8) | Q8: =IFERROR(P8/N8,"") | R8: =IFERROR(F8/P8,"") | S8: =SUMIFS(Raw_Data!$AO$2:$AO$2552,Raw_Data!$F$2:$F$2552,$B8) | T8: =IFERROR(S8/P8,"") | U8: =IFERROR(F8/S8,"") | V8: =SUMIFS(Raw_Data!$AR$2:$AR$2552,Raw_Data!$F$2:$F$2552,$B8) | W8: =SUMIFS(Raw_Data!$AS$2:$AS$2552,Raw_Data!$F$2:$F$2552,$B8) | X8: =P8+V8 | Y8: =SUMIFS(Raw_Data!$AU$2:$AU$2552,Raw_Data!$F$2:$F$2552,$B8) | Z8: =IFERROR(F8/Summary!$B$17,"") | AA8: =IFERROR(P8/Summary!$L$17,"")
A9: Meta (FB/IG) | B9: LEP_ZA_AUG26_META_RMKT_ALL_CONV | C9: Leads - Website Conversions | D9: Range | E9: Range Offer | F9: =SUMIFS(Raw_Data!$R$2:$R$2552,Raw_Data!$F$2:$F$2552,$B9) | G9: =SUMIFS(Raw_Data!$S$2:$S$2552,Raw_Data!$F$2:$F$2552,$B9) | H9: =SUMIFS(Raw_Data!$T$2:$T$2552,Raw_Data!$F$2:$F$2552,$B9) | I9: =IFERROR(G9/H9,"") | J9: =SUMIFS(Raw_Data!$W$2:$W$2552,Raw_Data!$F$2:$F$2552,$B9) | K9: =IFERROR(J9/G9,"") | L9: =IFERROR(F9/J9,"") | M9: =IFERROR(F9/G9*1000,"") | N9: =SUMIFS(Raw_Data!$AA$2:$AA$2552,Raw_Data!$F$2:$F$2552,$B9) | O9: =IFERROR(N9/J9,"") | P9: =SUMIFS(Raw_Data!$AL$2:$AL$2552,Raw_Data!$F$2:$F$2552,$B9) | Q9: =IFERROR(P9/N9,"") | R9: =IFERROR(F9/P9,"") | S9: =SUMIFS(Raw_Data!$AO$2:$AO$2552,Raw_Data!$F$2:$F$2552,$B9) | T9: =IFERROR(S9/P9,"") | U9: =IFERROR(F9/S9,"") | V9: =SUMIFS(Raw_Data!$AR$2:$AR$2552,Raw_Data!$F$2:$F$2552,$B9) | W9: =SUMIFS(Raw_Data!$AS$2:$AS$2552,Raw_Data!$F$2:$F$2552,$B9) | X9: =P9+V9 | Y9: =SUMIFS(Raw_Data!$AU$2:$AU$2552,Raw_Data!$F$2:$F$2552,$B9) | Z9: =IFERROR(F9/Summary!$B$17,"") | AA9: =IFERROR(P9/Summary!$L$17,"")
A10: TikTok | B10: LEP_ZA_AUG26_TT_TD_AMUR_CONV | C10: Website Conversions | D10: AMUR | E10: 0% Deposit | F10: =SUMIFS(Raw_Data!$R$2:$R$2552,Raw_Data!$F$2:$F$2552,$B10) | G10: =SUMIFS(Raw_Data!$S$2:$S$2552,Raw_Data!$F$2:$F$2552,$B10) | H10: =SUMIFS(Raw_Data!$T$2:$T$2552,Raw_Data!$F$2:$F$2552,$B10) | I10: =IFERROR(G10/H10,"") | J10: =SUMIFS(Raw_Data!$W$2:$W$2552,Raw_Data!$F$2:$F$2552,$B10) | K10: =IFERROR(J10/G10,"") | L10: =IFERROR(F10/J10,"") | M10: =IFERROR(F10/G10*1000,"") | N10: =SUMIFS(Raw_Data!$AA$2:$AA$2552,Raw_Data!$F$2:$F$2552,$B10) | O10: =IFERROR(N10/J10,"") | P10: =SUMIFS(Raw_Data!$AL$2:$AL$2552,Raw_Data!$F$2:$F$2552,$B10) | Q10: =IFERROR(P10/N10,"") | R10: =IFERROR(F10/P10,"") | S10: =SUMIFS(Raw_Data!$AO$2:$AO$2552,Raw_Data!$F$2:$F$2552,$B10) | T10: =IFERROR(S10/P10,"") | U10: =IFERROR(F10/S10,"") | V10: =SUMIFS(Raw_Data!$AR$2:$AR$2552,Raw_Data!$F$2:$F$2552,$B10) | W10: =SUMIFS(Raw_Data!$AS$2:$AS$2552,Raw_Data!$F$2:$F$2552,$B10) | X10: =P10+V10 | Y10: =SUMIFS(Raw_Data!$AU$2:$AU$2552,Raw_Data!$F$2:$F$2552,$B10) | Z10: =IFERROR(F10/Summary!$B$17,"") | AA10: =IFERROR(P10/Summary!$L$17,"")
A11: TikTok | B11: LEP_ZA_AUG26_TT_TD_PANTERA_CONV | C11: Website Conversions | D11: PANTERA | E11: 0% Deposit | F11: =SUMIFS(Raw_Data!$R$2:$R$2552,Raw_Data!$F$2:$F$2552,$B11) | G11: =SUMIFS(Raw_Data!$S$2:$S$2552,Raw_Data!$F$2:$F$2552,$B11) | H11: =SUMIFS(Raw_Data!$T$2:$T$2552,Raw_Data!$F$2:$F$2552,$B11) | I11: =IFERROR(G11/H11,"") | J11: =SUMIFS(Raw_Data!$W$2:$W$2552,Raw_Data!$F$2:$F$2552,$B11) | K11: =IFERROR(J11/G11,"") | L11: =IFERROR(F11/J11,"") | M11: =IFERROR(F11/G11*1000,"") | N11: =SUMIFS(Raw_Data!$AA$2:$AA$2552,Raw_Data!$F$2:$F$2552,$B11) | O11: =IFERROR(N11/J11,"") | P11: =SUMIFS(Raw_Data!$AL$2:$AL$2552,Raw_Data!$F$2:$F$2552,$B11) | Q11: =IFERROR(P11/N11,"") | R11: =IFERROR(F11/P11,"") | S11: =SUMIFS(Raw_Data!$AO$2:$AO$2552,Raw_Data!$F$2:$F$2552,$B11) | T11: =IFERROR(S11/P11,"") | U11: =IFERROR(F11/S11,"") | V11: =SUMIFS(Raw_Data!$AR$2:$AR$2552,Raw_Data!$F$2:$F$2552,$B11) | W11: =SUMIFS(Raw_Data!$AS$2:$AS$2552,Raw_Data!$F$2:$F$2552,$B11) | X11: =P11+V11 | Y11: =SUMIFS(Raw_Data!$AU$2:$AU$2552,Raw_Data!$F$2:$F$2552,$B11) | Z11: =IFERROR(F11/Summary!$B$17,"") | AA11: =IFERROR(P11/Summary!$L$17,"")
A12: TikTok | B12: LEP_ZA_AUG26_TT_SPARK_RANGE_TRAFFIC | C12: Traffic - Spark Ads | D12: Range | E12: Range Offer | F12: =SUMIFS(Raw_Data!$R$2:$R$2552,Raw_Data!$F$2:$F$2552,$B12) | G12: =SUMIFS(Raw_Data!$S$2:$S$2552,Raw_Data!$F$2:$F$2552,$B12) | H12: =SUMIFS(Raw_Data!$T$2:$T$2552,Raw_Data!$F$2:$F$2552,$B12) | I12: =IFERROR(G12/H12,"") | J12: =SUMIFS(Raw_Data!$W$2:$W$2552,Raw_Data!$F$2:$F$2552,$B12) | K12: =IFERROR(J12/G12,"") | L12: =IFERROR(F12/J12,"") | M12: =IFERROR(F12/G12*1000,"") | N12: =SUMIFS(Raw_Data!$AA$2:$AA$2552,Raw_Data!$F$2:$F$2552,$B12) | O12: =IFERROR(N12/J12,"") | P12: =SUMIFS(Raw_Data!$AL$2:$AL$2552,Raw_Data!$F$2:$F$2552,$B12) | Q12: =IFERROR(P12/N12,"") | R12: =IFERROR(F12/P12,"") | S12: =SUMIFS(Raw_Data!$AO$2:$AO$2552,Raw_Data!$F$2:$F$2552,$B12) | T12: =IFERROR(S12/P12,"") | U12: =IFERROR(F12/S12,"") | V12: =SUMIFS(Raw_Data!$AR$2:$AR$2552,Raw_Data!$F$2:$F$2552,$B12) | W12: =SUMIFS(Raw_Data!$AS$2:$AS$2552,Raw_Data!$F$2:$F$2552,$B12) | X12: =P12+V12 | Y12: =SUMIFS(Raw_Data!$AU$2:$AU$2552,Raw_Data!$F$2:$F$2552,$B12) | Z12: =IFERROR(F12/Summary!$B$17,"") | AA12: =IFERROR(P12/Summary!$L$17,"")
A13: X | B13: LEP_ZA_AUG26_X_TD_RANGE_CONV | C13: Website Conversions | D13: Range | E13: Range Offer | F13: =SUMIFS(Raw_Data!$R$2:$R$2552,Raw_Data!$F$2:$F$2552,$B13) | G13: =SUMIFS(Raw_Data!$S$2:$S$2552,Raw_Data!$F$2:$F$2552,$B13) | H13: =SUMIFS(Raw_Data!$T$2:$T$2552,Raw_Data!$F$2:$F$2552,$B13) | I13: =IFERROR(G13/H13,"") | J13: =SUMIFS(Raw_Data!$W$2:$W$2552,Raw_Data!$F$2:$F$2552,$B13) | K13: =IFERROR(J13/G13,"") | L13: =IFERROR(F13/J13,"") | M13: =IFERROR(F13/G13*1000,"") | N13: =SUMIFS(Raw_Data!$AA$2:$AA$2552,Raw_Data!$F$2:$F$2552,$B13) | O13: =IFERROR(N13/J13,"") | P13: =SUMIFS(Raw_Data!$AL$2:$AL$2552,Raw_Data!$F$2:$F$2552,$B13) | Q13: =IFERROR(P13/N13,"") | R13: =IFERROR(F13/P13,"") | S13: =SUMIFS(Raw_Data!$AO$2:$AO$2552,Raw_Data!$F$2:$F$2552,$B13) | T13: =IFERROR(S13/P13,"") | U13: =IFERROR(F13/S13,"") | V13: =SUMIFS(Raw_Data!$AR$2:$AR$2552,Raw_Data!$F$2:$F$2552,$B13) | W13: =SUMIFS(Raw_Data!$AS$2:$AS$2552,Raw_Data!$F$2:$F$2552,$B13) | X13: =P13+V13 | Y13: =SUMIFS(Raw_Data!$AU$2:$AU$2552,Raw_Data!$F$2:$F$2552,$B13) | Z13: =IFERROR(F13/Summary!$B$17,"") | AA13: =IFERROR(P13/Summary!$L$17,"")
A14: X | B14: LEP_ZA_AUG26_X_RMKT_TD_CONV | C14: Website Conversions | D14: Range | E14: Range Offer | F14: =SUMIFS(Raw_Data!$R$2:$R$2552,Raw_Data!$F$2:$F$2552,$B14) | G14: =SUMIFS(Raw_Data!$S$2:$S$2552,Raw_Data!$F$2:$F$2552,$B14) | H14: =SUMIFS(Raw_Data!$T$2:$T$2552,Raw_Data!$F$2:$F$2552,$B14) | I14: =IFERROR(G14/H14,"") | J14: =SUMIFS(Raw_Data!$W$2:$W$2552,Raw_Data!$F$2:$F$2552,$B14) | K14: =IFERROR(J14/G14,"") | L14: =IFERROR(F14/J14,"") | M14: =IFERROR(F14/G14*1000,"") | N14: =SUMIFS(Raw_Data!$AA$2:$AA$2552,Raw_Data!$F$2:$F$2552,$B14) | O14: =IFERROR(N14/J14,"") | P14: =SUMIFS(Raw_Data!$AL$2:$AL$2552,Raw_Data!$F$2:$F$2552,$B14) | Q14: =IFERROR(P14/N14,"") | R14: =IFERROR(F14/P14,"") | S14: =SUMIFS(Raw_Data!$AO$2:$AO$2552,Raw_Data!$F$2:$F$2552,$B14) | T14: =IFERROR(S14/P14,"") | U14: =IFERROR(F14/S14,"") | V14: =SUMIFS(Raw_Data!$AR$2:$AR$2552,Raw_Data!$F$2:$F$2552,$B14) | W14: =SUMIFS(Raw_Data!$AS$2:$AS$2552,Raw_Data!$F$2:$F$2552,$B14) | X14: =P14+V14 | Y14: =SUMIFS(Raw_Data!$AU$2:$AU$2552,Raw_Data!$F$2:$F$2552,$B14) | Z14: =IFERROR(F14/Summary!$B$17,"") | AA14: =IFERROR(P14/Summary!$L$17,"")
A15: Programmatic | B15: LEP_ZA_AUG26_PROG_TD_PROSPECT_DISPLAY | C15: Display Prospecting | D15: Range | E15: Range Offer | F15: =SUMIFS(Raw_Data!$R$2:$R$2552,Raw_Data!$F$2:$F$2552,$B15) | G15: =SUMIFS(Raw_Data!$S$2:$S$2552,Raw_Data!$F$2:$F$2552,$B15) | H15: =SUMIFS(Raw_Data!$T$2:$T$2552,Raw_Data!$F$2:$F$2552,$B15) | I15: =IFERROR(G15/H15,"") | J15: =SUMIFS(Raw_Data!$W$2:$W$2552,Raw_Data!$F$2:$F$2552,$B15) | K15: =IFERROR(J15/G15,"") | L15: =IFERROR(F15/J15,"") | M15: =IFERROR(F15/G15*1000,"") | N15: =SUMIFS(Raw_Data!$AA$2:$AA$2552,Raw_Data!$F$2:$F$2552,$B15) | O15: =IFERROR(N15/J15,"") | P15: =SUMIFS(Raw_Data!$AL$2:$AL$2552,Raw_Data!$F$2:$F$2552,$B15) | Q15: =IFERROR(P15/N15,"") | R15: =IFERROR(F15/P15,"") | S15: =SUMIFS(Raw_Data!$AO$2:$AO$2552,Raw_Data!$F$2:$F$2552,$B15) | T15: =IFERROR(S15/P15,"") | U15: =IFERROR(F15/S15,"") | V15: =SUMIFS(Raw_Data!$AR$2:$AR$2552,Raw_Data!$F$2:$F$2552,$B15) | W15: =SUMIFS(Raw_Data!$AS$2:$AS$2552,Raw_Data!$F$2:$F$2552,$B15) | X15: =P15+V15 | Y15: =SUMIFS(Raw_Data!$AU$2:$AU$2552,Raw_Data!$F$2:$F$2552,$B15) | Z15: =IFERROR(F15/Summary!$B$17,"") | AA15: =IFERROR(P15/Summary!$L$17,"")
A16: Programmatic | B16: LEP_ZA_AUG26_PROG_TD_VIDEO_OLV | C16: Online Video / CTV | D16: Range | E16: Range Offer | F16: =SUMIFS(Raw_Data!$R$2:$R$2552,Raw_Data!$F$2:$F$2552,$B16) | G16: =SUMIFS(Raw_Data!$S$2:$S$2552,Raw_Data!$F$2:$F$2552,$B16) | H16: =SUMIFS(Raw_Data!$T$2:$T$2552,Raw_Data!$F$2:$F$2552,$B16) | I16: =IFERROR(G16/H16,"") | J16: =SUMIFS(Raw_Data!$W$2:$W$2552,Raw_Data!$F$2:$F$2552,$B16) | K16: =IFERROR(J16/G16,"") | L16: =IFERROR(F16/J16,"") | M16: =IFERROR(F16/G16*1000,"") | N16: =SUMIFS(Raw_Data!$AA$2:$AA$2552,Raw_Data!$F$2:$F$2552,$B16) | O16: =IFERROR(N16/J16,"") | P16: =SUMIFS(Raw_Data!$AL$2:$AL$2552,Raw_Data!$F$2:$F$2552,$B16) | Q16: =IFERROR(P16/N16,"") | R16: =IFERROR(F16/P16,"") | S16: =SUMIFS(Raw_Data!$AO$2:$AO$2552,Raw_Data!$F$2:$F$2552,$B16) | T16: =IFERROR(S16/P16,"") | U16: =IFERROR(F16/S16,"") | V16: =SUMIFS(Raw_Data!$AR$2:$AR$2552,Raw_Data!$F$2:$F$2552,$B16) | W16: =SUMIFS(Raw_Data!$AS$2:$AS$2552,Raw_Data!$F$2:$F$2552,$B16) | X16: =P16+V16 | Y16: =SUMIFS(Raw_Data!$AU$2:$AU$2552,Raw_Data!$F$2:$F$2552,$B16) | Z16: =IFERROR(F16/Summary!$B$17,"") | AA16: =IFERROR(P16/Summary!$L$17,"")
A17: Programmatic | B17: LEP_ZA_AUG26_PROG_RMKT_DYNAMIC | C17: Dynamic Retargeting | D17: Range | E17: Range Offer | F17: =SUMIFS(Raw_Data!$R$2:$R$2552,Raw_Data!$F$2:$F$2552,$B17) | G17: =SUMIFS(Raw_Data!$S$2:$S$2552,Raw_Data!$F$2:$F$2552,$B17) | H17: =SUMIFS(Raw_Data!$T$2:$T$2552,Raw_Data!$F$2:$F$2552,$B17) | I17: =IFERROR(G17/H17,"") | J17: =SUMIFS(Raw_Data!$W$2:$W$2552,Raw_Data!$F$2:$F$2552,$B17) | K17: =IFERROR(J17/G17,"") | L17: =IFERROR(F17/J17,"") | M17: =IFERROR(F17/G17*1000,"") | N17: =SUMIFS(Raw_Data!$AA$2:$AA$2552,Raw_Data!$F$2:$F$2552,$B17) | O17: =IFERROR(N17/J17,"") | P17: =SUMIFS(Raw_Data!$AL$2:$AL$2552,Raw_Data!$F$2:$F$2552,$B17) | Q17: =IFERROR(P17/N17,"") | R17: =IFERROR(F17/P17,"") | S17: =SUMIFS(Raw_Data!$AO$2:$AO$2552,Raw_Data!$F$2:$F$2552,$B17) | T17: =IFERROR(S17/P17,"") | U17: =IFERROR(F17/S17,"") | V17: =SUMIFS(Raw_Data!$AR$2:$AR$2552,Raw_Data!$F$2:$F$2552,$B17) | W17: =SUMIFS(Raw_Data!$AS$2:$AS$2552,Raw_Data!$F$2:$F$2552,$B17) | X17: =P17+V17 | Y17: =SUMIFS(Raw_Data!$AU$2:$AU$2552,Raw_Data!$F$2:$F$2552,$B17) | Z17: =IFERROR(F17/Summary!$B$17,"") | AA17: =IFERROR(P17/Summary!$L$17,"")
A18: TOTAL | I18: =IFERROR(G18/H18,"") | K18: =IFERROR(J18/G18,"") | L18: =IFERROR(F18/J18,"") | M18: =IFERROR(F18/G18*1000,"") | O18: =IFERROR(N18/J18,"") | Q18: =IFERROR(P18/N18,"") | R18: =IFERROR(F18/P18,"") | T18: =IFERROR(S18/P18,"") | U18: =IFERROR(F18/S18,"") | X18: =P18+V18 | Z18: =IFERROR(F18/Summary!$B$17,"") | AA18: =IFERROR(P18/Summary!$L$17,"")
A21: AD SET / LINE ITEM LEVEL
A22: Channel | B22: Campaign Name | C22: Ad Set / Line Item | D22: Audience Type | E22: Spend (ZAR) | F22: Impressions | G22: Reach (sum of daily) | H22: Avg Daily Frequency | I22: Link Clicks | J22: CTR (Link) | K22: CPC (Link) | L22: CPM | M22: Landing Page Views | N22: LPV Rate | O22: Test Drive Bookings | P22: CVR (Booking / LPV) | Q22: CPL (Cost / Booking) | R22: Qualified Leads | S22: Qualified Rate | T22: Cost per Qualified Lead | U22: View-Through Conv. | V22: Assisted Conv. | W22: Total Attributed Conv. | X22: Est. Revenue Pipeline (ZAR) | Y22: % of Spend | Z22: % of Bookings
A23: Meta (FB/IG) | B23: LEP_ZA_AUG26_META_TD_AMUR_CONV | C23: MET_AMUR_BROAD_25-54_ZA | D23: Prospecting | E23: =SUMIFS(Raw_Data!$R$2:$R$2552,Raw_Data!$F$2:$F$2552,$B23,Raw_Data!$J$2:$J$2552,$C23) | F23: =SUMIFS(Raw_Data!$S$2:$S$2552,Raw_Data!$F$2:$F$2552,$B23,Raw_Data!$J$2:$J$2552,$C23) | G23: =SUMIFS(Raw_Data!$T$2:$T$2552,Raw_Data!$F$2:$F$2552,$B23,Raw_Data!$J$2:$J$2552,$C23) | H23: =IFERROR(F23/G23,"") | I23: =SUMIFS(Raw_Data!$W$2:$W$2552,Raw_Data!$F$2:$F$2552,$B23,Raw_Data!$J$2:$J$2552,$C23) | J23: =IFERROR(I23/F23,"") | K23: =IFERROR(E23/I23,"") | L23: =IFERROR(E23/F23*1000,"") | M23: =SUMIFS(Raw_Data!$AA$2:$AA$2552,Raw_Data!$F$2:$F$2552,$B23,Raw_Data!$J$2:$J$2552,$C23) | N23: =IFERROR(M23/I23,"") | O23: =SUMIFS(Raw_Data!$AL$2:$AL$2552,Raw_Data!$F$2:$F$2552,$B23,Raw_Data!$J$2:$J$2552,$C23) | P23: =IFERROR(O23/M23,"") | Q23: =IFERROR(E23/O23,"") | R23: =SUMIFS(Raw_Data!$AO$2:$AO$2552,Raw_Data!$F$2:$F$2552,$B23,Raw_Data!$J$2:$J$2552,$C23) | S23: =IFERROR(R23/O23,"") | T23: =IFERROR(E23/R23,"") | U23: =SUMIFS(Raw_Data!$AR$2:$AR$2552,Raw_Data!$F$2:$F$2552,$B23,Raw_Data!$J$2:$J$2552,$C23) | V23: =SUMIFS(Raw_Data!$AS$2:$AS$2552,Raw_Data!$F$2:$F$2552,$B23,Raw_Data!$J$2:$J$2552,$C23) | W23: =O23+U23 | X23: =SUMIFS(Raw_Data!$AU$2:$AU$2552,Raw_Data!$F$2:$F$2552,$B23,Raw_Data!$J$2:$J$2552,$C23) | Y23: =IFERROR(E23/Summary!$B$17,"") | Z23: =IFERROR(O23/Summary!$L$17,"")
A24: Meta (FB/IG) | B24: LEP_ZA_AUG26_META_TD_AMUR_CONV | C24: MET_AMUR_LAL3_LEADS_ZA | D24: Lookalike | E24: =SUMIFS(Raw_Data!$R$2:$R$2552,Raw_Data!$F$2:$F$2552,$B24,Raw_Data!$J$2:$J$2552,$C24) | F24: =SUMIFS(Raw_Data!$S$2:$S$2552,Raw_Data!$F$2:$F$2552,$B24,Raw_Data!$J$2:$J$2552,$C24) | G24: =SUMIFS(Raw_Data!$T$2:$T$2552,Raw_Data!$F$2:$F$2552,$B24,Raw_Data!$J$2:$J$2552,$C24) | H24: =IFERROR(F24/G24,"") | I24: =SUMIFS(Raw_Data!$W$2:$W$2552,Raw_Data!$F$2:$F$2552,$B24,Raw_Data!$J$2:$J$2552,$C24) | J24: =IFERROR(I24/F24,"") | K24: =IFERROR(E24/I24,"") | L24: =IFERROR(E24/F24*1000,"") | M24: =SUMIFS(Raw_Data!$AA$2:$AA$2552,Raw_Data!$F$2:$F$2552,$B24,Raw_Data!$J$2:$J$2552,$C24) | N24: =IFERROR(M24/I24,"") | O24: =SUMIFS(Raw_Data!$AL$2:$AL$2552,Raw_Data!$F$2:$F$2552,$B24,Raw_Data!$J$2:$J$2552,$C24) | P24: =IFERROR(O24/M24,"") | Q24: =IFERROR(E24/O24,"") | R24: =SUMIFS(Raw_Data!$AO$2:$AO$2552,Raw_Data!$F$2:$F$2552,$B24,Raw_Data!$J$2:$J$2552,$C24) | S24: =IFERROR(R24/O24,"") | T24: =IFERROR(E24/R24,"") | U24: =SUMIFS(Raw_Data!$AR$2:$AR$2552,Raw_Data!$F$2:$F$2552,$B24,Raw_Data!$J$2:$J$2552,$C24) | V24: =SUMIFS(Raw_Data!$AS$2:$AS$2552,Raw_Data!$F$2:$F$2552,$B24,Raw_Data!$J$2:$J$2552,$C24) | W24: =O24+U24 | X24: =SUMIFS(Raw_Data!$AU$2:$AU$2552,Raw_Data!$F$2:$F$2552,$B24,Raw_Data!$J$2:$J$2552,$C24) | Y24: =IFERROR(E24/Summary!$B$17,"") | Z24: =IFERROR(O24/Summary!$L$17,"")
A25: Meta (FB/IG) | B25: LEP_ZA_AUG26_META_TD_AMUR_CONV | C25: MET_AMUR_INMKT_HATCH_ZA | D25: In-Market | E25: =SUMIFS(Raw_Data!$R$2:$R$2552,Raw_Data!$F$2:$F$2552,$B25,Raw_Data!$J$2:$J$2552,$C25) | F25: =SUMIFS(Raw_Data!$S$2:$S$2552,Raw_Data!$F$2:$F$2552,$B25,Raw_Data!$J$2:$J$2552,$C25) | G25: =SUMIFS(Raw_Data!$T$2:$T$2552,Raw_Data!$F$2:$F$2552,$B25,Raw_Data!$J$2:$J$2552,$C25) | H25: =IFERROR(F25/G25,"") | I25: =SUMIFS(Raw_Data!$W$2:$W$2552,Raw_Data!$F$2:$F$2552,$B25,Raw_Data!$J$2:$J$2552,$C25) | J25: =IFERROR(I25/F25,"") | K25: =IFERROR(E25/I25,"") | L25: =IFERROR(E25/F25*1000,"") | M25: =SUMIFS(Raw_Data!$AA$2:$AA$2552,Raw_Data!$F$2:$F$2552,$B25,Raw_Data!$J$2:$J$2552,$C25) | N25: =IFERROR(M25/I25,"") | O25: =SUMIFS(Raw_Data!$AL$2:$AL$2552,Raw_Data!$F$2:$F$2552,$B25,Raw_Data!$J$2:$J$2552,$C25) | P25: =IFERROR(O25/M25,"") | Q25: =IFERROR(E25/O25,"") | R25: =SUMIFS(Raw_Data!$AO$2:$AO$2552,Raw_Data!$F$2:$F$2552,$B25,Raw_Data!$J$2:$J$2552,$C25) | S25: =IFERROR(R25/O25,"") | T25: =IFERROR(E25/R25,"") | U25: =SUMIFS(Raw_Data!$AR$2:$AR$2552,Raw_Data!$F$2:$F$2552,$B25,Raw_Data!$J$2:$J$2552,$C25) | V25: =SUMIFS(Raw_Data!$AS$2:$AS$2552,Raw_Data!$F$2:$F$2552,$B25,Raw_Data!$J$2:$J$2552,$C25) | W25: =O25+U25 | X25: =SUMIFS(Raw_Data!$AU$2:$AU$2552,Raw_Data!$F$2:$F$2552,$B25,Raw_Data!$J$2:$J$2552,$C25) | Y25: =IFERROR(E25/Summary!$B$17,"") | Z25: =IFERROR(O25/Summary!$L$17,"")
A26: Meta (FB/IG) | B26: LEP_ZA_AUG26_META_TD_JAVAN_CONV | C26: MET_JAVAN_BROAD_28-55_ZA | D26: Prospecting | E26: =SUMIFS(Raw_Data!$R$2:$R$2552,Raw_Data!$F$2:$F$2552,$B26,Raw_Data!$J$2:$J$2552,$C26) | F26: =SUMIFS(Raw_Data!$S$2:$S$2552,Raw_Data!$F$2:$F$2552,$B26,Raw_Data!$J$2:$J$2552,$C26) | G26: =SUMIFS(Raw_Data!$T$2:$T$2552,Raw_Data!$F$2:$F$2552,$B26,Raw_Data!$J$2:$J$2552,$C26) | H26: =IFERROR(F26/G26,"") | I26: =SUMIFS(Raw_Data!$W$2:$W$2552,Raw_Data!$F$2:$F$2552,$B26,Raw_Data!$J$2:$J$2552,$C26) | J26: =IFERROR(I26/F26,"") | K26: =IFERROR(E26/I26,"") | L26: =IFERROR(E26/F26*1000,"") | M26: =SUMIFS(Raw_Data!$AA$2:$AA$2552,Raw_Data!$F$2:$F$2552,$B26,Raw_Data!$J$2:$J$2552,$C26) | N26: =IFERROR(M26/I26,"") | O26: =SUMIFS(Raw_Data!$AL$2:$AL$2552,Raw_Data!$F$2:$F$2552,$B26,Raw_Data!$J$2:$J$2552,$C26) | P26: =IFERROR(O26/M26,"") | Q26: =IFERROR(E26/O26,"") | R26: =SUMIFS(Raw_Data!$AO$2:$AO$2552,Raw_Data!$F$2:$F$2552,$B26,Raw_Data!$J$2:$J$2552,$C26) | S26: =IFERROR(R26/O26,"") | T26: =IFERROR(E26/R26,"") | U26: =SUMIFS(Raw_Data!$AR$2:$AR$2552,Raw_Data!$F$2:$F$2552,$B26,Raw_Data!$J$2:$J$2552,$C26) | V26: =SUMIFS(Raw_Data!$AS$2:$AS$2552,Raw_Data!$F$2:$F$2552,$B26,Raw_Data!$J$2:$J$2552,$C26) | W26: =O26+U26 | X26: =SUMIFS(Raw_Data!$AU$2:$AU$2552,Raw_Data!$F$2:$F$2552,$B26,Raw_Data!$J$2:$J$2552,$C26) | Y26: =IFERROR(E26/Summary!$B$17,"") | Z26: =IFERROR(O26/Summary!$L$17,"")
A27: Meta (FB/IG) | B27: LEP_ZA_AUG26_META_TD_JAVAN_CONV | C27: MET_JAVAN_LAL2_SITE_ZA | D27: Lookalike | E27: =SUMIFS(Raw_Data!$R$2:$R$2552,Raw_Data!$F$2:$F$2552,$B27,Raw_Data!$J$2:$J$2552,$C27) | F27: =SUMIFS(Raw_Data!$S$2:$S$2552,Raw_Data!$F$2:$F$2552,$B27,Raw_Data!$J$2:$J$2552,$C27) | G27: =SUMIFS(Raw_Data!$T$2:$T$2552,Raw_Data!$F$2:$F$2552,$B27,Raw_Data!$J$2:$J$2552,$C27) | H27: =IFERROR(F27/G27,"") | I27: =SUMIFS(Raw_Data!$W$2:$W$2552,Raw_Data!$F$2:$F$2552,$B27,Raw_Data!$J$2:$J$2552,$C27) | J27: =IFERROR(I27/F27,"") | K27: =IFERROR(E27/I27,"") | L27: =IFERROR(E27/F27*1000,"") | M27: =SUMIFS(Raw_Data!$AA$2:$AA$2552,Raw_Data!$F$2:$F$2552,$B27,Raw_Data!$J$2:$J$2552,$C27) | N27: =IFERROR(M27/I27,"") | O27: =SUMIFS(Raw_Data!$AL$2:$AL$2552,Raw_Data!$F$2:$F$2552,$B27,Raw_Data!$J$2:$J$2552,$C27) | P27: =IFERROR(O27/M27,"") | Q27: =IFERROR(E27/O27,"") | R27: =SUMIFS(Raw_Data!$AO$2:$AO$2552,Raw_Data!$F$2:$F$2552,$B27,Raw_Data!$J$2:$J$2552,$C27) | S27: =IFERROR(R27/O27,"") | T27: =IFERROR(E27/R27,"") | U27: =SUMIFS(Raw_Data!$AR$2:$AR$2552,Raw_Data!$F$2:$F$2552,$B27,Raw_Data!$J$2:$J$2552,$C27) | V27: =SUMIFS(Raw_Data!$AS$2:$AS$2552,Raw_Data!$F$2:$F$2552,$B27,Raw_Data!$J$2:$J$2552,$C27) | W27: =O27+U27 | X27: =SUMIFS(Raw_Data!$AU$2:$AU$2552,Raw_Data!$F$2:$F$2552,$B27,Raw_Data!$J$2:$J$2552,$C27) | Y27: =IFERROR(E27/Summary!$B$17,"") | Z27: =IFERROR(O27/Summary!$L$17,"")
A28: Meta (FB/IG) | B28: LEP_ZA_AUG26_META_TD_JAVAN_CONV | C28: MET_JAVAN_INMKT_SUV_ZA | D28: In-Market | E28: =SUMIFS(Raw_Data!$R$2:$R$2552,Raw_Data!$F$2:$F$2552,$B28,Raw_Data!$J$2:$J$2552,$C28) | F28: =SUMIFS(Raw_Data!$S$2:$S$2552,Raw_Data!$F$2:$F$2552,$B28,Raw_Data!$J$2:$J$2552,$C28) | G28: =SUMIFS(Raw_Data!$T$2:$T$2552,Raw_Data!$F$2:$F$2552,$B28,Raw_Data!$J$2:$J$2552,$C28) | H28: =IFERROR(F28/G28,"") | I28: =SUMIFS(Raw_Data!$W$2:$W$2552,Raw_Data!$F$2:$F$2552,$B28,Raw_Data!$J$2:$J$2552,$C28) | J28: =IFERROR(I28/F28,"") | K28: =IFERROR(E28/I28,"") | L28: =IFERROR(E28/F28*1000,"") | M28: =SUMIFS(Raw_Data!$AA$2:$AA$2552,Raw_Data!$F$2:$F$2552,$B28,Raw_Data!$J$2:$J$2552,$C28) | N28: =IFERROR(M28/I28,"") | O28: =SUMIFS(Raw_Data!$AL$2:$AL$2552,Raw_Data!$F$2:$F$2552,$B28,Raw_Data!$J$2:$J$2552,$C28) | P28: =IFERROR(O28/M28,"") | Q28: =IFERROR(E28/O28,"") | R28: =SUMIFS(Raw_Data!$AO$2:$AO$2552,Raw_Data!$F$2:$F$2552,$B28,Raw_Data!$J$2:$J$2552,$C28) | S28: =IFERROR(R28/O28,"") | T28: =IFERROR(E28/R28,"") | U28: =SUMIFS(Raw_Data!$AR$2:$AR$2552,Raw_Data!$F$2:$F$2552,$B28,Raw_Data!$J$2:$J$2552,$C28) | V28: =SUMIFS(Raw_Data!$AS$2:$AS$2552,Raw_Data!$F$2:$F$2552,$B28,Raw_Data!$J$2:$J$2552,$C28) | W28: =O28+U28 | X28: =SUMIFS(Raw_Data!$AU$2:$AU$2552,Raw_Data!$F$2:$F$2552,$B28,Raw_Data!$J$2:$J$2552,$C28) | Y28: =IFERROR(E28/Summary!$B$17,"") | Z28: =IFERROR(O28/Summary!$L$17,"")
A29: Meta (FB/IG) | B29: LEP_ZA_AUG26_META_TD_PANTERA_CONV | C29: MET_PANTERA_BROAD_30-60_ZA | D29: Prospecting | E29: =SUMIFS(Raw_Data!$R$2:$R$2552,Raw_Data!$F$2:$F$2552,$B29,Raw_Data!$J$2:$J$2552,$C29) | F29: =SUMIFS(Raw_Data!$S$2:$S$2552,Raw_Data!$F$2:$F$2552,$B29,Raw_Data!$J$2:$J$2552,$C29) | G29: =SUMIFS(Raw_Data!$T$2:$T$2552,Raw_Data!$F$2:$F$2552,$B29,Raw_Data!$J$2:$J$2552,$C29) | H29: =IFERROR(F29/G29,"") | I29: =SUMIFS(Raw_Data!$W$2:$W$2552,Raw_Data!$F$2:$F$2552,$B29,Raw_Data!$J$2:$J$2552,$C29) | J29: =IFERROR(I29/F29,"") | K29: =IFERROR(E29/I29,"") | L29: =IFERROR(E29/F29*1000,"") | M29: =SUMIFS(Raw_Data!$AA$2:$AA$2552,Raw_Data!$F$2:$F$2552,$B29,Raw_Data!$J$2:$J$2552,$C29) | N29: =IFERROR(M29/I29,"") | O29: =SUMIFS(Raw_Data!$AL$2:$AL$2552,Raw_Data!$F$2:$F$2552,$B29,Raw_Data!$J$2:$J$2552,$C29) | P29: =IFERROR(O29/M29,"") | Q29: =IFERROR(E29/O29,"") | R29: =SUMIFS(Raw_Data!$AO$2:$AO$2552,Raw_Data!$F$2:$F$2552,$B29,Raw_Data!$J$2:$J$2552,$C29) | S29: =IFERROR(R29/O29,"") | T29: =IFERROR(E29/R29,"") | U29: =SUMIFS(Raw_Data!$AR$2:$AR$2552,Raw_Data!$F$2:$F$2552,$B29,Raw_Data!$J$2:$J$2552,$C29) | V29: =SUMIFS(Raw_Data!$AS$2:$AS$2552,Raw_Data!$F$2:$F$2552,$B29,Raw_Data!$J$2:$J$2552,$C29) | W29: =O29+U29 | X29: =SUMIFS(Raw_Data!$AU$2:$AU$2552,Raw_Data!$F$2:$F$2552,$B29,Raw_Data!$J$2:$J$2552,$C29) | Y29: =IFERROR(E29/Summary!$B$17,"") | Z29: =IFERROR(O29/Summary!$L$17,"")
A30: Meta (FB/IG) | B30: LEP_ZA_AUG26_META_TD_PANTERA_CONV | C30: MET_PANTERA_LAL1_HIVAL_ZA | D30: Lookalike | E30: =SUMIFS(Raw_Data!$R$2:$R$2552,Raw_Data!$F$2:$F$2552,$B30,Raw_Data!$J$2:$J$2552,$C30) | F30: =SUMIFS(Raw_Data!$S$2:$S$2552,Raw_Data!$F$2:$F$2552,$B30,Raw_Data!$J$2:$J$2552,$C30) | G30: =SUMIFS(Raw_Data!$T$2:$T$2552,Raw_Data!$F$2:$F$2552,$B30,Raw_Data!$J$2:$J$2552,$C30) | H30: =IFERROR(F30/G30,"") | I30: =SUMIFS(Raw_Data!$W$2:$W$2552,Raw_Data!$F$2:$F$2552,$B30,Raw_Data!$J$2:$J$2552,$C30) | J30: =IFERROR(I30/F30,"") | K30: =IFERROR(E30/I30,"") | L30: =IFERROR(E30/F30*1000,"") | M30: =SUMIFS(Raw_Data!$AA$2:$AA$2552,Raw_Data!$F$2:$F$2552,$B30,Raw_Data!$J$2:$J$2552,$C30) | N30: =IFERROR(M30/I30,"") | O30: =SUMIFS(Raw_Data!$AL$2:$AL$2552,Raw_Data!$F$2:$F$2552,$B30,Raw_Data!$J$2:$J$2552,$C30) | P30: =IFERROR(O30/M30,"") | Q30: =IFERROR(E30/O30,"") | R30: =SUMIFS(Raw_Data!$AO$2:$AO$2552,Raw_Data!$F$2:$F$2552,$B30,Raw_Data!$J$2:$J$2552,$C30) | S30: =IFERROR(R30/O30,"") | T30: =IFERROR(E30/R30,"") | U30: =SUMIFS(Raw_Data!$AR$2:$AR$2552,Raw_Data!$F$2:$F$2552,$B30,Raw_Data!$J$2:$J$2552,$C30) | V30: =SUMIFS(Raw_Data!$AS$2:$AS$2552,Raw_Data!$F$2:$F$2552,$B30,Raw_Data!$J$2:$J$2552,$C30) | W30: =O30+U30 | X30: =SUMIFS(Raw_Data!$AU$2:$AU$2552,Raw_Data!$F$2:$F$2552,$B30,Raw_Data!$J$2:$J$2552,$C30) | Y30: =IFERROR(E30/Summary!$B$17,"") | Z30: =IFERROR(O30/Summary!$L$17,"")
A31: Meta (FB/IG) | B31: LEP_ZA_AUG26_META_TD_PANTERA_CONV | C31: MET_PANTERA_INT_PREMIUM_ZA | D31: Interest | E31: =SUMIFS(Raw_Data!$R$2:$R$2552,Raw_Data!$F$2:$F$2552,$B31,Raw_Data!$J$2:$J$2552,$C31) | F31: =SUMIFS(Raw_Data!$S$2:$S$2552,Raw_Data!$F$2:$F$2552,$B31,Raw_Data!$J$2:$J$2552,$C31) | G31: =SUMIFS(Raw_Data!$T$2:$T$2552,Raw_Data!$F$2:$F$2552,$B31,Raw_Data!$J$2:$J$2552,$C31) | H31: =IFERROR(F31/G31,"") | I31: =SUMIFS(Raw_Data!$W$2:$W$2552,Raw_Data!$F$2:$F$2552,$B31,Raw_Data!$J$2:$J$2552,$C31) | J31: =IFERROR(I31/F31,"") | K31: =IFERROR(E31/I31,"") | L31: =IFERROR(E31/F31*1000,"") | M31: =SUMIFS(Raw_Data!$AA$2:$AA$2552,Raw_Data!$F$2:$F$2552,$B31,Raw_Data!$J$2:$J$2552,$C31) | N31: =IFERROR(M31/I31,"") | O31: =SUMIFS(Raw_Data!$AL$2:$AL$2552,Raw_Data!$F$2:$F$2552,$B31,Raw_Data!$J$2:$J$2552,$C31) | P31: =IFERROR(O31/M31,"") | Q31: =IFERROR(E31/O31,"") | R31: =SUMIFS(Raw_Data!$AO$2:$AO$2552,Raw_Data!$F$2:$F$2552,$B31,Raw_Data!$J$2:$J$2552,$C31) | S31: =IFERROR(R31/O31,"") | T31: =IFERROR(E31/R31,"") | U31: =SUMIFS(Raw_Data!$AR$2:$AR$2552,Raw_Data!$F$2:$F$2552,$B31,Raw_Data!$J$2:$J$2552,$C31) | V31: =SUMIFS(Raw_Data!$AS$2:$AS$2552,Raw_Data!$F$2:$F$2552,$B31,Raw_Data!$J$2:$J$2552,$C31) | W31: =O31+U31 | X31: =SUMIFS(Raw_Data!$AU$2:$AU$2552,Raw_Data!$F$2:$F$2552,$B31,Raw_Data!$J$2:$J$2552,$C31) | Y31: =IFERROR(E31/Summary!$B$17,"") | Z31: =IFERROR(O31/Summary!$L$17,"")
A32: Meta (FB/IG) | B32: LEP_ZA_AUG26_META_RMKT_ALL_CONV | C32: MET_RMKT_SITE30D_ZA | D32: Retargeting | E32: =SUMIFS(Raw_Data!$R$2:$R$2552,Raw_Data!$F$2:$F$2552,$B32,Raw_Data!$J$2:$J$2552,$C32) | F32: =SUMIFS(Raw_Data!$S$2:$S$2552,Raw_Data!$F$2:$F$2552,$B32,Raw_Data!$J$2:$J$2552,$C32) | G32: =SUMIFS(Raw_Data!$T$2:$T$2552,Raw_Data!$F$2:$F$2552,$B32,Raw_Data!$J$2:$J$2552,$C32) | H32: =IFERROR(F32/G32,"") | I32: =SUMIFS(Raw_Data!$W$2:$W$2552,Raw_Data!$F$2:$F$2552,$B32,Raw_Data!$J$2:$J$2552,$C32) | J32: =IFERROR(I32/F32,"") | K32: =IFERROR(E32/I32,"") | L32: =IFERROR(E32/F32*1000,"") | M32: =SUMIFS(Raw_Data!$AA$2:$AA$2552,Raw_Data!$F$2:$F$2552,$B32,Raw_Data!$J$2:$J$2552,$C32) | N32: =IFERROR(M32/I32,"") | O32: =SUMIFS(Raw_Data!$AL$2:$AL$2552,Raw_Data!$F$2:$F$2552,$B32,Raw_Data!$J$2:$J$2552,$C32) | P32: =IFERROR(O32/M32,"") | Q32: =IFERROR(E32/O32,"") | R32: =SUMIFS(Raw_Data!$AO$2:$AO$2552,Raw_Data!$F$2:$F$2552,$B32,Raw_Data!$J$2:$J$2552,$C32) | S32: =IFERROR(R32/O32,"") | T32: =IFERROR(E32/R32,"") | U32: =SUMIFS(Raw_Data!$AR$2:$AR$2552,Raw_Data!$F$2:$F$2552,$B32,Raw_Data!$J$2:$J$2552,$C32) | V32: =SUMIFS(Raw_Data!$AS$2:$AS$2552,Raw_Data!$F$2:$F$2552,$B32,Raw_Data!$J$2:$J$2552,$C32) | W32: =O32+U32 | X32: =SUMIFS(Raw_Data!$AU$2:$AU$2552,Raw_Data!$F$2:$F$2552,$B32,Raw_Data!$J$2:$J$2552,$C32) | Y32: =IFERROR(E32/Summary!$B$17,"") | Z32: =IFERROR(O32/Summary!$L$17,"")
A33: Meta (FB/IG) | B33: LEP_ZA_AUG26_META_RMKT_ALL_CONV | C33: MET_RMKT_VIDVIEW75_ZA | D33: Retargeting | E33: =SUMIFS(Raw_Data!$R$2:$R$2552,Raw_Data!$F$2:$F$2552,$B33,Raw_Data!$J$2:$J$2552,$C33) | F33: =SUMIFS(Raw_Data!$S$2:$S$2552,Raw_Data!$F$2:$F$2552,$B33,Raw_Data!$J$2:$J$2552,$C33) | G33: =SUMIFS(Raw_Data!$T$2:$T$2552,Raw_Data!$F$2:$F$2552,$B33,Raw_Data!$J$2:$J$2552,$C33) | H33: =IFERROR(F33/G33,"") | I33: =SUMIFS(Raw_Data!$W$2:$W$2552,Raw_Data!$F$2:$F$2552,$B33,Raw_Data!$J$2:$J$2552,$C33) | J33: =IFERROR(I33/F33,"") | K33: =IFERROR(E33/I33,"") | L33: =IFERROR(E33/F33*1000,"") | M33: =SUMIFS(Raw_Data!$AA$2:$AA$2552,Raw_Data!$F$2:$F$2552,$B33,Raw_Data!$J$2:$J$2552,$C33) | N33: =IFERROR(M33/I33,"") | O33: =SUMIFS(Raw_Data!$AL$2:$AL$2552,Raw_Data!$F$2:$F$2552,$B33,Raw_Data!$J$2:$J$2552,$C33) | P33: =IFERROR(O33/M33,"") | Q33: =IFERROR(E33/O33,"") | R33: =SUMIFS(Raw_Data!$AO$2:$AO$2552,Raw_Data!$F$2:$F$2552,$B33,Raw_Data!$J$2:$J$2552,$C33) | S33: =IFERROR(R33/O33,"") | T33: =IFERROR(E33/R33,"") | U33: =SUMIFS(Raw_Data!$AR$2:$AR$2552,Raw_Data!$F$2:$F$2552,$B33,Raw_Data!$J$2:$J$2552,$C33) | V33: =SUMIFS(Raw_Data!$AS$2:$AS$2552,Raw_Data!$F$2:$F$2552,$B33,Raw_Data!$J$2:$J$2552,$C33) | W33: =O33+U33 | X33: =SUMIFS(Raw_Data!$AU$2:$AU$2552,Raw_Data!$F$2:$F$2552,$B33,Raw_Data!$J$2:$J$2552,$C33) | Y33: =IFERROR(E33/Summary!$B$17,"") | Z33: =IFERROR(O33/Summary!$L$17,"")
A34: Meta (FB/IG) | B34: LEP_ZA_AUG26_META_RMKT_ALL_CONV | C34: MET_RMKT_FORMABANDON_ZA | D34: Retargeting | E34: =SUMIFS(Raw_Data!$R$2:$R$2552,Raw_Data!$F$2:$F$2552,$B34,Raw_Data!$J$2:$J$2552,$C34) | F34: =SUMIFS(Raw_Data!$S$2:$S$2552,Raw_Data!$F$2:$F$2552,$B34,Raw_Data!$J$2:$J$2552,$C34) | G34: =SUMIFS(Raw_Data!$T$2:$T$2552,Raw_Data!$F$2:$F$2552,$B34,Raw_Data!$J$2:$J$2552,$C34) | H34: =IFERROR(F34/G34,"") | I34: =SUMIFS(Raw_Data!$W$2:$W$2552,Raw_Data!$F$2:$F$2552,$B34,Raw_Data!$J$2:$J$2552,$C34) | J34: =IFERROR(I34/F34,"") | K34: =IFERROR(E34/I34,"") | L34: =IFERROR(E34/F34*1000,"") | M34: =SUMIFS(Raw_Data!$AA$2:$AA$2552,Raw_Data!$F$2:$F$2552,$B34,Raw_Data!$J$2:$J$2552,$C34) | N34: =IFERROR(M34/I34,"") | O34: =SUMIFS(Raw_Data!$AL$2:$AL$2552,Raw_Data!$F$2:$F$2552,$B34,Raw_Data!$J$2:$J$2552,$C34) | P34: =IFERROR(O34/M34,"") | Q34: =IFERROR(E34/O34,"") | R34: =SUMIFS(Raw_Data!$AO$2:$AO$2552,Raw_Data!$F$2:$F$2552,$B34,Raw_Data!$J$2:$J$2552,$C34) | S34: =IFERROR(R34/O34,"") | T34: =IFERROR(E34/R34,"") | U34: =SUMIFS(Raw_Data!$AR$2:$AR$2552,Raw_Data!$F$2:$F$2552,$B34,Raw_Data!$J$2:$J$2552,$C34) | V34: =SUMIFS(Raw_Data!$AS$2:$AS$2552,Raw_Data!$F$2:$F$2552,$B34,Raw_Data!$J$2:$J$2552,$C34) | W34: =O34+U34 | X34: =SUMIFS(Raw_Data!$AU$2:$AU$2552,Raw_Data!$F$2:$F$2552,$B34,Raw_Data!$J$2:$J$2552,$C34) | Y34: =IFERROR(E34/Summary!$B$17,"") | Z34: =IFERROR(O34/Summary!$L$17,"")
... A53: Programmatic | B53: LEP_ZA_AUG26_PROG_RMKT_DYNAMIC | C53: PROG_LAL_SEED_CONVERTERS | D53: Lookalike | E53: =SUMIFS(Raw_Data!$R$2:$R$2552,Raw_Data!$F$2:$F$2552,$B53,Raw_Data!$J$2:$J$2552,$C53) | F53: =SUMIFS(Raw_Data!$S$2:$S$2552,Raw_Data!$F$2:$F$2552,$B53,Raw_Data!$J$2:$J$2552,$C53) | G53: =SUMIFS(Raw_Data!$T$2:$T$2552,Raw_Data!$F$2:$F$2552,$B53,Raw_Data!$J$2:$J$2552,$C53) | H53: =IFERROR(F53/G53,"") | I53: =SUMIFS(Raw_Data!$W$2:$W$2552,Raw_Data!$F$2:$F$2552,$B53,Raw_Data!$J$2:$J$2552,$C53) | J53: =IFERROR(I53/F53,"") | K53: =IFERROR(E53/I53,"") | L53: =IFERROR(E53/F53*1000,"") | M53: =SUMIFS(Raw_Data!$AA$2:$AA$2552,Raw_Data!$F$2:$F$2552,$B53,Raw_Data!$J$2:$J$2552,$C53) | N53: =IFERROR(M53/I53,"") | O53: =SUMIFS(Raw_Data!$AL$2:$AL$2552,Raw_Data!$F$2:$F$2552,$B53,Raw_Data!$J$2:$J$2552,$C53) | P53: =IFERROR(O53/M53,"") | Q53: =IFERROR(E53/O53,"") | R53: =SUMIFS(Raw_Data!$AO$2:$AO$2552,Raw_Data!$F$2:$F$2552,$B53,Raw_Data!$J$2:$J$2552,$C53) | S53: =IFERROR(R53/O53,"") | T53: =IFERROR(E53/R53,"") | U53: =SUMIFS(Raw_Data!$AR$2:$AR$2552,Raw_Data!$F$2:$F$2552,$B53,Raw_Data!$J$2:$J$2552,$C53) | V53: =SUMIFS(Raw_Data!$AS$2:$AS$2552,Raw_Data!$F$2:$F$2552,$B53,Raw_Data!$J$2:$J$2552,$C53) | W53: =O53+U53 | X53: =SUMIFS(Raw_Data!$AU$2:$AU$2552,Raw_Data!$F$2:$F$2552,$B53,Raw_Data!$J$2:$J$2552,$C53) | Y53: =IFERROR(E53/Summary!$B$17,"") | Z53: =IFERROR(O53/Summary!$L$17,"")
A54: TOTAL | H54: =IFERROR(F54/G54,"") | J54: =IFERROR(I54/F54,"") | K54: =IFERROR(E54/I54,"") | L54: =IFERROR(E54/F54*1000,"") | N54: =IFERROR(M54/I54,"") | P54: =IFERROR(O54/M54,"") | Q54: =IFERROR(E54/O54,"") | S54: =IFERROR(R54/O54,"") | T54: =IFERROR(E54/R54,"") | W54: =O54+U54 | Y54: =IFERROR(E54/Summary!$B$17,"") | Z54: =IFERROR(O54/Summary!$L$17,"")

Sheet Creative_Performance
A1: Creative Performance
A2: Every asset in market, its flight window, funnel efficiency and video engagement. Sorted by channel then creative name — filter on CPL to find the winners.
A4: Channel | B4: Creative Name | C4: Creative Format | D4: Creative Hook / Message | E4: Spend (ZAR) | F4: Impressions | G4: Reach (sum of daily) | H4: Avg Daily Frequency | I4: Link Clicks | J4: CTR (Link) | K4: CPC (Link) | L4: CPM | M4: Landing Page Views | N4: LPV Rate | O4: Test Drive Bookings | P4: CVR (Booking / LPV) | Q4: CPL (Cost / Booking) | R4: Qualified Leads | S4: Qualified Rate | T4: Cost per Qualified Lead | U4: View-Through Conv. | V4: Assisted Conv. | W4: Total Attributed Conv. | X4: Est. Revenue Pipeline (ZAR) | Y4: % of Spend | Z4: % of Bookings | AA4: First Day Live | AB4: Last Day Live | AC4: Days Live | AD4: Video Views 3s | AE4: Video Views 6s | AF4: Video 25% | AG4: Video 50% | AH4: Video 75% | AI4: Video 100% | AJ4: Hook Rate (3s) | AK4: Video Completion Rate | AL4: Engagements
A5: Meta (FB/IG) | B5: AMUR_VID_15s_CityDrive_v1 | C5: Video 9:16 | D5: Your first Lepas. R3 599pm. | E5: =SUMIFS(Raw_Data!$R$2:$R$2552,Raw_Data!$D$2:$D$2552,$A5,Raw_Data!$L$2:$L$2552,$B5) | F5: =SUMIFS(Raw_Data!$S$2:$S$2552,Raw_Data!$D$2:$D$2552,$A5,Raw_Data!$L$2:$L$2552,$B5) | G5: =SUMIFS(Raw_Data!$T$2:$T$2552,Raw_Data!$D$2:$D$2552,$A5,Raw_Data!$L$2:$L$2552,$B5) | H5: =IFERROR(F5/G5,"") | I5: =SUMIFS(Raw_Data!$W$2:$W$2552,Raw_Data!$D$2:$D$2552,$A5,Raw_Data!$L$2:$L$2552,$B5) | J5: =IFERROR(I5/F5,"") | K5: =IFERROR(E5/I5,"") | L5: =IFERROR(E5/F5*1000,"") | M5: =SUMIFS(Raw_Data!$AA$2:$AA$2552,Raw_Data!$D$2:$D$2552,$A5,Raw_Data!$L$2:$L$2552,$B5) | N5: =IFERROR(M5/I5,"") | O5: =SUMIFS(Raw_Data!$AL$2:$AL$2552,Raw_Data!$D$2:$D$2552,$A5,Raw_Data!$L$2:$L$2552,$B5) | P5: =IFERROR(O5/M5,"") | Q5: =IFERROR(E5/O5,"") | R5: =SUMIFS(Raw_Data!$AO$2:$AO$2552,Raw_Data!$D$2:$D$2552,$A5,Raw_Data!$L$2:$L$2552,$B5) | S5: =IFERROR(R5/O5,"") | T5: =IFERROR(E5/R5,"") | U5: =SUMIFS(Raw_Data!$AR$2:$AR$2552,Raw_Data!$D$2:$D$2552,$A5,Raw_Data!$L$2:$L$2552,$B5) | V5: =SUMIFS(Raw_Data!$AS$2:$AS$2552,Raw_Data!$D$2:$D$2552,$A5,Raw_Data!$L$2:$L$2552,$B5) | W5: =O5+U5 | X5: =SUMIFS(Raw_Data!$AU$2:$AU$2552,Raw_Data!$D$2:$D$2552,$A5,Raw_Data!$L$2:$L$2552,$B5) | Y5: =IFERROR(E5/Summary!$B$17,"") | Z5: =IFERROR(O5/Summary!$L$17,"") | AA5: 46235 | AB5: 46252 | AC5: =AB5-AA5+1 | AD5: =SUMIFS(Raw_Data!$AC$2:$AC$2552,Raw_Data!$D$2:$D$2552,$A5,Raw_Data!$L$2:$L$2552,$B5) | AE5: =SUMIFS(Raw_Data!$AD$2:$AD$2552,Raw_Data!$D$2:$D$2552,$A5,Raw_Data!$L$2:$L$2552,$B5) | AF5: =SUMIFS(Raw_Data!$AE$2:$AE$2552,Raw_Data!$D$2:$D$2552,$A5,Raw_Data!$L$2:$L$2552,$B5) | AG5: =SUMIFS(Raw_Data!$AF$2:$AF$2552,Raw_Data!$D$2:$D$2552,$A5,Raw_Data!$L$2:$L$2552,$B5) | AH5: =SUMIFS(Raw_Data!$AG$2:$AG$2552,Raw_Data!$D$2:$D$2552,$A5,Raw_Data!$L$2:$L$2552,$B5) | AI5: =SUMIFS(Raw_Data!$AH$2:$AH$2552,Raw_Data!$D$2:$D$2552,$A5,Raw_Data!$L$2:$L$2552,$B5) | AJ5: =IFERROR(AD5/F5,"") | AK5: =IFERROR(AI5/F5,"") | AL5: =SUMIFS(Raw_Data!$AK$2:$AK$2552,Raw_Data!$D$2:$D$2552,$A5,Raw_Data!$L$2:$L$2552,$B5)
A6: Meta (FB/IG) | B6: AMUR_CAR_4card_SpecStack_v1 | C6: Carousel | D6: 4 reasons the AMUR outsells its class | E6: =SUMIFS(Raw_Data!$R$2:$R$2552,Raw_Data!$D$2:$D$2552,$A6,Raw_Data!$L$2:$L$2552,$B6) | F6: =SUMIFS(Raw_Data!$S$2:$S$2552,Raw_Data!$D$2:$D$2552,$A6,Raw_Data!$L$2:$L$2552,$B6) | G6: =SUMIFS(Raw_Data!$T$2:$T$2552,Raw_Data!$D$2:$D$2552,$A6,Raw_Data!$L$2:$L$2552,$B6) | H6: =IFERROR(F6/G6,"") | I6: =SUMIFS(Raw_Data!$W$2:$W$2552,Raw_Data!$D$2:$D$2552,$A6,Raw_Data!$L$2:$L$2552,$B6) | J6: =IFERROR(I6/F6,"") | K6: =IFERROR(E6/I6,"") | L6: =IFERROR(E6/F6*1000,"") | M6: =SUMIFS(Raw_Data!$AA$2:$AA$2552,Raw_Data!$D$2:$D$2552,$A6,Raw_Data!$L$2:$L$2552,$B6) | N6: =IFERROR(M6/I6,"") | O6: =SUMIFS(Raw_Data!$AL$2:$AL$2552,Raw_Data!$D$2:$D$2552,$A6,Raw_Data!$L$2:$L$2552,$B6) | P6: =IFERROR(O6/M6,"") | Q6: =IFERROR(E6/O6,"") | R6: =SUMIFS(Raw_Data!$AO$2:$AO$2552,Raw_Data!$D$2:$D$2552,$A6,Raw_Data!$L$2:$L$2552,$B6) | S6: =IFERROR(R6/O6,"") | T6: =IFERROR(E6/R6,"") | U6: =SUMIFS(Raw_Data!$AR$2:$AR$2552,Raw_Data!$D$2:$D$2552,$A6,Raw_Data!$L$2:$L$2552,$B6) | V6: =SUMIFS(Raw_Data!$AS$2:$AS$2552,Raw_Data!$D$2:$D$2552,$A6,Raw_Data!$L$2:$L$2552,$B6) | W6: =O6+U6 | X6: =SUMIFS(Raw_Data!$AU$2:$AU$2552,Raw_Data!$D$2:$D$2552,$A6,Raw_Data!$L$2:$L$2552,$B6) | Y6: =IFERROR(E6/Summary!$B$17,"") | Z6: =IFERROR(O6/Summary!$L$17,"") | AA6: 46235 | AB6: 46265 | AC6: =AB6-AA6+1 | AD6: =SUMIFS(Raw_Data!$AC$2:$AC$2552,Raw_Data!$D$2:$D$2552,$A6,Raw_Data!$L$2:$L$2552,$B6) | AE6: =SUMIFS(Raw_Data!$AD$2:$AD$2552,Raw_Data!$D$2:$D$2552,$A6,Raw_Data!$L$2:$L$2552,$B6) | AF6: =SUMIFS(Raw_Data!$AE$2:$AE$2552,Raw_Data!$D$2:$D$2552,$A6,Raw_Data!$L$2:$L$2552,$B6) | AG6: =SUMIFS(Raw_Data!$AF$2:$AF$2552,Raw_Data!$D$2:$D$2552,$A6,Raw_Data!$L$2:$L$2552,$B6) | AH6: =SUMIFS(Raw_Data!$AG$2:$AG$2552,Raw_Data!$D$2:$D$2552,$A6,Raw_Data!$L$2:$L$2552,$B6) | AI6: =SUMIFS(Raw_Data!$AH$2:$AH$2552,Raw_Data!$D$2:$D$2552,$A6,Raw_Data!$L$2:$L$2552,$B6) | AJ6: =IFERROR(AD6/F6,"") | AK6: =IFERROR(AI6/F6,"") | AL6: =SUMIFS(Raw_Data!$AK$2:$AK$2552,Raw_Data!$D$2:$D$2552,$A6,Raw_Data!$L$2:$L$2552,$B6)
A7: Meta (FB/IG) | B7: AMUR_STA_Offer_0Dep_v1 | C7: Static 1:1 | D7: 0% deposit. Book your test drive. | E7: =SUMIFS(Raw_Data!$R$2:$R$2552,Raw_Data!$D$2:$D$2552,$A7,Raw_Data!$L$2:$L$2552,$B7) | F7: =SUMIFS(Raw_Data!$S$2:$S$2552,Raw_Data!$D$2:$D$2552,$A7,Raw_Data!$L$2:$L$2552,$B7) | G7: =SUMIFS(Raw_Data!$T$2:$T$2552,Raw_Data!$D$2:$D$2552,$A7,Raw_Data!$L$2:$L$2552,$B7) | H7: =IFERROR(F7/G7,"") | I7: =SUMIFS(Raw_Data!$W$2:$W$2552,Raw_Data!$D$2:$D$2552,$A7,Raw_Data!$L$2:$L$2552,$B7) | J7: =IFERROR(I7/F7,"") | K7: =IFERROR(E7/I7,"") | L7: =IFERROR(E7/F7*1000,"") | M7: =SUMIFS(Raw_Data!$AA$2:$AA$2552,Raw_Data!$D$2:$D$2552,$A7,Raw_Data!$L$2:$L$2552,$B7) | N7: =IFERROR(M7/I7,"") | O7: =SUMIFS(Raw_Data!$AL$2:$AL$2552,Raw_Data!$D$2:$D$2552,$A7,Raw_Data!$L$2:$L$2552,$B7) | P7: =IFERROR(O7/M7,"") | Q7: =IFERROR(E7/O7,"") | R7: =SUMIFS(Raw_Data!$AO$2:$AO$2552,Raw_Data!$D$2:$D$2552,$A7,Raw_Data!$L$2:$L$2552,$B7) | S7: =IFERROR(R7/O7,"") | T7: =IFERROR(E7/R7,"") | U7: =SUMIFS(Raw_Data!$AR$2:$AR$2552,Raw_Data!$D$2:$D$2552,$A7,Raw_Data!$L$2:$L$2552,$B7) | V7: =SUMIFS(Raw_Data!$AS$2:$AS$2552,Raw_Data!$D$2:$D$2552,$A7,Raw_Data!$L$2:$L$2552,$B7) | W7: =O7+U7 | X7: =SUMIFS(Raw_Data!$AU$2:$AU$2552,Raw_Data!$D$2:$D$2552,$A7,Raw_Data!$L$2:$L$2552,$B7) | Y7: =IFERROR(E7/Summary!$B$17,"") | Z7: =IFERROR(O7/Summary!$L$17,"") | AA7: 46235 | AB7: 46265 | AC7: =AB7-AA7+1 | AD7: =SUMIFS(Raw_Data!$AC$2:$AC$2552,Raw_Data!$D$2:$D$2552,$A7,Raw_Data!$L$2:$L$2552,$B7) | AE7: =SUMIFS(Raw_Data!$AD$2:$AD$2552,Raw_Data!$D$2:$D$2552,$A7,Raw_Data!$L$2:$L$2552,$B7) | AF7: =SUMIFS(Raw_Data!$AE$2:$AE$2552,Raw_Data!$D$2:$D$2552,$A7,Raw_Data!$L$2:$L$2552,$B7) | AG7: =SUMIFS(Raw_Data!$AF$2:$AF$2552,Raw_Data!$D$2:$D$2552,$A7,Raw_Data!$L$2:$L$2552,$B7) | AH7: =SUMIFS(Raw_Data!$AG$2:$AG$2552,Raw_Data!$D$2:$D$2552,$A7,Raw_Data!$L$2:$L$2552,$B7) | AI7: =SUMIFS(Raw_Data!$AH$2:$AH$2552,Raw_Data!$D$2:$D$2552,$A7,Raw_Data!$L$2:$L$2552,$B7) | AJ7: =IFERROR(AD7/F7,"") | AK7: =IFERROR(AI7/F7,"") | AL7: =SUMIFS(Raw_Data!$AK$2:$AK$2552,Raw_Data!$D$2:$D$2552,$A7,Raw_Data!$L$2:$L$2552,$B7)
A8: Meta (FB/IG) | B8: AMUR_VID_15s_CityDrive_v2 | C8: Video 9:16 | D8: Zero deposit. Real drive. Today. | E8: =SUMIFS(Raw_Data!$R$2:$R$2552,Raw_Data!$D$2:$D$2552,$A8,Raw_Data!$L$2:$L$2552,$B8) | F8: =SUMIFS(Raw_Data!$S$2:$S$2552,Raw_Data!$D$2:$D$2552,$A8,Raw_Data!$L$2:$L$2552,$B8) | G8: =SUMIFS(Raw_Data!$T$2:$T$2552,Raw_Data!$D$2:$D$2552,$A8,Raw_Data!$L$2:$L$2552,$B8) | H8: =IFERROR(F8/G8,"") | I8: =SUMIFS(Raw_Data!$W$2:$W$2552,Raw_Data!$D$2:$D$2552,$A8,Raw_Data!$L$2:$L$2552,$B8) | J8: =IFERROR(I8/F8,"") | K8: =IFERROR(E8/I8,"") | L8: =IFERROR(E8/F8*1000,"") | M8: =SUMIFS(Raw_Data!$AA$2:$AA$2552,Raw_Data!$D$2:$D$2552,$A8,Raw_Data!$L$2:$L$2552,$B8) | N8: =IFERROR(M8/I8,"") | O8: =SUMIFS(Raw_Data!$AL$2:$AL$2552,Raw_Data!$D$2:$D$2552,$A8,Raw_Data!$L$2:$L$2552,$B8) | P8: =IFERROR(O8/M8,"") | Q8: =IFERROR(E8/O8,"") | R8: =SUMIFS(Raw_Data!$AO$2:$AO$2552,Raw_Data!$D$2:$D$2552,$A8,Raw_Data!$L$2:$L$2552,$B8) | S8: =IFERROR(R8/O8,"") | T8: =IFERROR(E8/R8,"") | U8: =SUMIFS(Raw_Data!$AR$2:$AR$2552,Raw_Data!$D$2:$D$2552,$A8,Raw_Data!$L$2:$L$2552,$B8) | V8: =SUMIFS(Raw_Data!$AS$2:$AS$2552,Raw_Data!$D$2:$D$2552,$A8,Raw_Data!$L$2:$L$2552,$B8) | W8: =O8+U8 | X8: =SUMIFS(Raw_Data!$AU$2:$AU$2552,Raw_Data!$D$2:$D$2552,$A8,Raw_Data!$L$2:$L$2552,$B8) | Y8: =IFERROR(E8/Summary!$B$17,"") | Z8: =IFERROR(O8/Summary!$L$17,"") | AA8: 46247 | AB8: 46265 | AC8: =AB8-AA8+1 | AD8: =SUMIFS(Raw_Data!$AC$2:$AC$2552,Raw_Data!$D$2:$D$2552,$A8,Raw_Data!$L$2:$L$2552,$B8) | AE8: =SUMIFS(Raw_Data!$AD$2:$AD$2552,Raw_Data!$D$2:$D$2552,$A8,Raw_Data!$L$2:$L$2552,$B8) | AF8: =SUMIFS(Raw_Data!$AE$2:$AE$2552,Raw_Data!$D$2:$D$2552,$A8,Raw_Data!$L$2:$L$2552,$B8) | AG8: =SUMIFS(Raw_Data!$AF$2:$AF$2552,Raw_Data!$D$2:$D$2552,$A8,Raw_Data!$L$2:$L$2552,$B8) | AH8: =SUMIFS(Raw_Data!$AG$2:$AG$2552,Raw_Data!$D$2:$D$2552,$A8,Raw_Data!$L$2:$L$2552,$B8) | AI8: =SUMIFS(Raw_Data!$AH$2:$AH$2552,Raw_Data!$D$2:$D$2552,$A8,Raw_Data!$L$2:$L$2552,$B8) | AJ8: =IFERROR(AD8/F8,"") | AK8: =IFERROR(AI8/F8,"") | AL8: =SUMIFS(Raw_Data!$AK$2:$AK$2552,Raw_Data!$D$2:$D$2552,$A8,Raw_Data!$L$2:$L$2552,$B8)
A9: Meta (FB/IG) | B9: AMUR_VID_20s_OwnerStory_v1 | C9: Video 4:5 | D9: She booked a test drive on a Tuesday | E9: =SUMIFS(Raw_Data!$R$2:$R$2552,Raw_Data!$D$2:$D$2552,$A9,Raw_Data!$L$2:$L$2552,$B9) | F9: =SUMIFS(Raw_Data!$S$2:$S$2552,Raw_Data!$D$2:$D$2552,$A9,Raw_Data!$L$2:$L$2552,$B9) | G9: =SUMIFS(Raw_Data!$T$2:$T$2552,Raw_Data!$D$2:$D$2552,$A9,Raw_Data!$L$2:$L$2552,$B9) | H9: =IFERROR(F9/G9,"") | I9: =SUMIFS(Raw_Data!$W$2:$W$2552,Raw_Data!$D$2:$D$2552,$A9,Raw_Data!$L$2:$L$2552,$B9) | J9: =IFERROR(I9/F9,"") | K9: =IFERROR(E9/I9,"") | L9: =IFERROR(E9/F9*1000,"") | M9: =SUMIFS(Raw_Data!$AA$2:$AA$2552,Raw_Data!$D$2:$D$2552,$A9,Raw_Data!$L$2:$L$2552,$B9) | N9: =IFERROR(M9/I9,"") | O9: =SUMIFS(Raw_Data!$AL$2:$AL$2552,Raw_Data!$D$2:$D$2552,$A9,Raw_Data!$L$2:$L$2552,$B9) | P9: =IFERROR(O9/M9,"") | Q9: =IFERROR(E9/O9,"") | R9: =SUMIFS(Raw_Data!$AO$2:$AO$2552,Raw_Data!$D$2:$D$2552,$A9,Raw_Data!$L$2:$L$2552,$B9) | S9: =IFERROR(R9/O9,"") | T9: =IFERROR(E9/R9,"") | U9: =SUMIFS(Raw_Data!$AR$2:$AR$2552,Raw_Data!$D$2:$D$2552,$A9,Raw_Data!$L$2:$L$2552,$B9) | V9: =SUMIFS(Raw_Data!$AS$2:$AS$2552,Raw_Data!$D$2:$D$2552,$A9,Raw_Data!$L$2:$L$2552,$B9) | W9: =O9+U9 | X9: =SUMIFS(Raw_Data!$AU$2:$AU$2552,Raw_Data!$D$2:$D$2552,$A9,Raw_Data!$L$2:$L$2552,$B9) | Y9: =IFERROR(E9/Summary!$B$17,"") | Z9: =IFERROR(O9/Summary!$L$17,"") | AA9: 46235 | AB9: 46265 | AC9: =AB9-AA9+1 | AD9: =SUMIFS(Raw_Data!$AC$2:$AC$2552,Raw_Data!$D$2:$D$2552,$A9,Raw_Data!$L$2:$L$2552,$B9) | AE9: =SUMIFS(Raw_Data!$AD$2:$AD$2552,Raw_Data!$D$2:$D$2552,$A9,Raw_Data!$L$2:$L$2552,$B9) | AF9: =SUMIFS(Raw_Data!$AE$2:$AE$2552,Raw_Data!$D$2:$D$2552,$A9,Raw_Data!$L$2:$L$2552,$B9) | AG9: =SUMIFS(Raw_Data!$AF$2:$AF$2552,Raw_Data!$D$2:$D$2552,$A9,Raw_Data!$L$2:$L$2552,$B9) | AH9: =SUMIFS(Raw_Data!$AG$2:$AG$2552,Raw_Data!$D$2:$D$2552,$A9,Raw_Data!$L$2:$L$2552,$B9) | AI9: =SUMIFS(Raw_Data!$AH$2:$AH$2552,Raw_Data!$D$2:$D$2552,$A9,Raw_Data!$L$2:$L$2552,$B9) | AJ9: =IFERROR(AD9/F9,"") | AK9: =IFERROR(AI9/F9,"") | AL9: =SUMIFS(Raw_Data!$AK$2:$AK$2552,Raw_Data!$D$2:$D$2552,$A9,Raw_Data!$L$2:$L$2552,$B9)
A10: Meta (FB/IG) | B10: AMUR_STA_Compare_Hatch_v1 | C10: Static 4:5 | D10: Compare before you commit | E10: =SUMIFS(Raw_Data!$R$2:$R$2552,Raw_Data!$D$2:$D$2552,$A10,Raw_Data!$L$2:$L$2552,$B10) | F10: =SUMIFS(Raw_Data!$S$2:$S$2552,Raw_Data!$D$2:$D$2552,$A10,Raw_Data!$L$2:$L$2552,$B10) | G10: =SUMIFS(Raw_Data!$T$2:$T$2552,Raw_Data!$D$2:$D$2552,$A10,Raw_Data!$L$2:$L$2552,$B10) | H10: =IFERROR(F10/G10,"") | I10: =SUMIFS(Raw_Data!$W$2:$W$2552,Raw_Data!$D$2:$D$2552,$A10,Raw_Data!$L$2:$L$2552,$B10) | J10: =IFERROR(I10/F10,"") | K10: =IFERROR(E10/I10,"") | L10: =IFERROR(E10/F10*1000,"") | M10: =SUMIFS(Raw_Data!$AA$2:$AA$2552,Raw_Data!$D$2:$D$2552,$A10,Raw_Data!$L$2:$L$2552,$B10) | N10: =IFERROR(M10/I10,"") | O10: =SUMIFS(Raw_Data!$AL$2:$AL$2552,Raw_Data!$D$2:$D$2552,$A10,Raw_Data!$L$2:$L$2552,$B10) | P10: =IFERROR(O10/M10,"") | Q10: =IFERROR(E10/O10,"") | R10: =SUMIFS(Raw_Data!$AO$2:$AO$2552,Raw_Data!$D$2:$D$2552,$A10,Raw_Data!$L$2:$L$2552,$B10) | S10: =IFERROR(R10/O10,"") | T10: =IFERROR(E10/R10,"") | U10: =SUMIFS(Raw_Data!$AR$2:$AR$2552,Raw_Data!$D$2:$D$2552,$A10,Raw_Data!$L$2:$L$2552,$B10) | V10: =SUMIFS(Raw_Data!$AS$2:$AS$2552,Raw_Data!$D$2:$D$2552,$A10,Raw_Data!$L$2:$L$2552,$B10) | W10: =O10+U10 | X10: =SUMIFS(Raw_Data!$AU$2:$AU$2552,Raw_Data!$D$2:$D$2552,$A10,Raw_Data!$L$2:$L$2552,$B10) | Y10: =IFERROR(E10/Summary!$B$17,"") | Z10: =IFERROR(O10/Summary!$L$17,"") | AA10: 46235 | AB10: 46265 | AC10: =AB10-AA10+1 | AD10: =SUMIFS(Raw_Data!$AC$2:$AC$2552,Raw_Data!$D$2:$D$2552,$A10,Raw_Data!$L$2:$L$2552,$B10) | AE10: =SUMIFS(Raw_Data!$AD$2:$AD$2552,Raw_Data!$D$2:$D$2552,$A10,Raw_Data!$L$2:$L$2552,$B10) | AF10: =SUMIFS(Raw_Data!$AE$2:$AE$2552,Raw_Data!$D$2:$D$2552,$A10,Raw_Data!$L$2:$L$2552,$B10) | AG10: =SUMIFS(Raw_Data!$AF$2:$AF$2552,Raw_Data!$D$2:$D$2552,$A10,Raw_Data!$L$2:$L$2552,$B10) | AH10: =SUMIFS(Raw_Data!$AG$2:$AG$2552,Raw_Data!$D$2:$D$2552,$A10,Raw_Data!$L$2:$L$2552,$B10) | AI10: =SUMIFS(Raw_Data!$AH$2:$AH$2552,Raw_Data!$D$2:$D$2552,$A10,Raw_Data!$L$2:$L$2552,$B10) | AJ10: =IFERROR(AD10/F10,"") | AK10: =IFERROR(AI10/F10,"") | AL10: =SUMIFS(Raw_Data!$AK$2:$AK$2552,Raw_Data!$D$2:$D$2552,$A10,Raw_Data!$L$2:$L$2552,$B10)
A11: Meta (FB/IG) | B11: JAVAN_VID_20s_FamilyWeekend_v1 | C11: Video 9:16 | D11: The weekend car that works on Monday | E11: =SUMIFS(Raw_Data!$R$2:$R$2552,Raw_Data!$D$2:$D$2552,$A11,Raw_Data!$L$2:$L$2552,$B11) | F11: =SUMIFS(Raw_Data!$S$2:$S$2552,Raw_Data!$D$2:$D$2552,$A11,Raw_Data!$L$2:$L$2552,$B11) | G11: =SUMIFS(Raw_Data!$T$2:$T$2552,Raw_Data!$D$2:$D$2552,$A11,Raw_Data!$L$2:$L$2552,$B11) | H11: =IFERROR(F11/G11,"") | I11: =SUMIFS(Raw_Data!$W$2:$W$2552,Raw_Data!$D$2:$D$2552,$A11,Raw_Data!$L$2:$L$2552,$B11) | J11: =IFERROR(I11/F11,"") | K11: =IFERROR(E11/I11,"") | L11: =IFERROR(E11/F11*1000,"") | M11: =SUMIFS(Raw_Data!$AA$2:$AA$2552,Raw_Data!$D$2:$D$2552,$A11,Raw_Data!$L$2:$L$2552,$B11) | N11: =IFERROR(M11/I11,"") | O11: =SUMIFS(Raw_Data!$AL$2:$AL$2552,Raw_Data!$D$2:$D$2552,$A11,Raw_Data!$L$2:$L$2552,$B11) | P11: =IFERROR(O11/M11,"") | Q11: =IFERROR(E11/O11,"") | R11: =SUMIFS(Raw_Data!$AO$2:$AO$2552,Raw_Data!$D$2:$D$2552,$A11,Raw_Data!$L$2:$L$2552,$B11) | S11: =IFERROR(R11/O11,"") | T11: =IFERROR(E11/R11,"") | U11: =SUMIFS(Raw_Data!$AR$2:$AR$2552,Raw_Data!$D$2:$D$2552,$A11,Raw_Data!$L$2:$L$2552,$B11) | V11: =SUMIFS(Raw_Data!$AS$2:$AS$2552,Raw_Data!$D$2:$D$2552,$A11,Raw_Data!$L$2:$L$2552,$B11) | W11: =O11+U11 | X11: =SUMIFS(Raw_Data!$AU$2:$AU$2552,Raw_Data!$D$2:$D$2552,$A11,Raw_Data!$L$2:$L$2552,$B11) | Y11: =IFERROR(E11/Summary!$B$17,"") | Z11: =IFERROR(O11/Summary!$L$17,"") | AA11: 46235 | AB11: 46254 | AC11: =AB11-AA11+1 | AD11: =SUMIFS(Raw_Data!$AC$2:$AC$2552,Raw_Data!$D$2:$D$2552,$A11,Raw_Data!$L$2:$L$2552,$B11) | AE11: =SUMIFS(Raw_Data!$AD$2:$AD$2552,Raw_Data!$D$2:$D$2552,$A11,Raw_Data!$L$2:$L$2552,$B11) | AF11: =SUMIFS(Raw_Data!$AE$2:$AE$2552,Raw_Data!$D$2:$D$2552,$A11,Raw_Data!$L$2:$L$2552,$B11) | AG11: =SUMIFS(Raw_Data!$AF$2:$AF$2552,Raw_Data!$D$2:$D$2552,$A11,Raw_Data!$L$2:$L$2552,$B11) | AH11: =SUMIFS(Raw_Data!$AG$2:$AG$2552,Raw_Data!$D$2:$D$2552,$A11,Raw_Data!$L$2:$L$2552,$B11) | AI11: =SUMIFS(Raw_Data!$AH$2:$AH$2552,Raw_Data!$D$2:$D$2552,$A11,Raw_Data!$L$2:$L$2552,$B11) | AJ11: =IFERROR(AD11/F11,"") | AK11: =IFERROR(AI11/F11,"") | AL11: =SUMIFS(Raw_Data!$AK$2:$AK$2552,Raw_Data!$D$2:$D$2552,$A11,Raw_Data!$L$2:$L$2552,$B11)
